Workbook
Name BabyCoilIDList: 'Coil to Slit'!$D$3:$D$500
Name BundleIDList: OFFSET('Bundle Formation'!$G$3,0,0,MAX(COUNTIF('Bundle Formation'!$G$3:$G$117,"BND-*"),1),1)
Name CoilIDList: 'Coil Sheet at Plant'!$C$3:$C$100
Name Density_T_mm3: SOP!$B$8
Name MaterialInfoList: 'SKU Master'!$C$2:$C$233
Name SKU_1: "Helpers!$K$2:$K$20"
Name SKU_2: "Helpers!$L$2:$L$9"
Name SKU_3: "Helpers!$M$2:$M$9"
Name SKU_4: "Helpers!$N$2:$N$7"
Name SKU_5: "Helpers!$O$2:$O$11"
Name SKU_6: "Helpers!$P$2:$P$5"

Sheet Coil Sheet at Plant
A1: 🔵 Input Parameters | C1: 🟢 Auto-ID | N1: 🟢 Performance Metrics | Q1: 🔵 Chemistry (Input) | U1: 🟡 Validation Helpers
A2: Date of Inward | B2: HR Coil No. | C2: HR Coil ID | D2: Input Coil Number (Batch ID) | E2: Coil Grade | F2: Heat Number | G2: Thickness (mm) | H2: Length (mm) | I2: Width (mm) | J2: Invoice Weight (T) | K2: Actual Weight (T) | L2: Cost Price (₹) | M2: PO Number | N2: FG Readiness | O2: Dispatched Weight (T) | P2: Yield % (Dispatch/Total Weight) | Q2: Carbon | R2: Mn | S2: YS (MPa) | T2: Elongation (%) | U2: Total Baby Coil Width (mm) | V2: Width Check (Baby vs Parent) | W2: Duplicate ID Check
A3: 46108 | B3: 1 | C3: =IF(OR(A3="",B3=""),"","HYD-"&TEXT(A3,"MMYY")&"-"&TEXT(B3,"00")) -> HYD-0326-01 | D3: C102781102 | E3: E250- BR | F3: C102781 | G3: 2.8 | I3: 1250 | J3: 20.63 | U3: =IF(C3="","",SUMIF('Coil to Slit'!B:B,C3,'Coil to Slit'!G:G)) -> 1243 | V3: =IF(U3="","",IF(I3="","⚠ NO PARENT WIDTH",IF(U3>I3,"⚠ EXCEEDS PARENT","✔ OK"))) -> ✔ OK | W3: =IF(C3="","",IF(COUNTIF(C$3:C3,C3)>1,"⚠ DUPLICATE ID",""))
A4: 46108 | B4: 2 | C4: =IF(OR(A4="",B4=""),"","HYD-"&TEXT(A4,"MMYY")&"-"&TEXT(B4,"00")) -> HYD-0326-02 | D4: C202753205 | E4: E250- BR | F4: C202753 | G4: 2.8 | I4: 1250 | J4: 20.93 | U4: =IF(C4="","",SUMIF('Coil to Slit'!B:B,C4,'Coil to Slit'!G:G)) -> 1243 | V4: =IF(U4="","",IF(I4="","⚠ NO PARENT WIDTH",IF(U4>I4,"⚠ EXCEEDS PARENT","✔ OK"))) -> ✔ OK | W4: =IF(C4="","",IF(COUNTIF(C$3:C4,C4)>1,"⚠ DUPLICATE ID",""))
A5: 46109 | B5: 3 | C5: =IF(OR(A5="",B5=""),"","HYD-"&TEXT(A5,"MMYY")&"-"&TEXT(B5,"00")) -> HYD-0326-03 | D5: K633360481 | E5: IS10748 Gr 1 | F5: A3Y2286 | G5: 2.5 | I5: 1500 | J5: 29.29 | U5: =IF(C5="","",SUMIF('Coil to Slit'!B:B,C5,'Coil to Slit'!G:G)) -> 1504 | V5: =IF(U5="","",IF(I5="","⚠ NO PARENT WIDTH",IF(U5>I5,"⚠ EXCEEDS PARENT","✔ OK"))) -> ⚠ EXCEEDS PARENT | W5: =IF(C5="","",IF(COUNTIF(C$3:C5,C5)>1,"⚠ DUPLICATE ID",""))
A6: 46110 | B6: 4 | C6: =IF(OR(A6="",B6=""),"","HYD-"&TEXT(A6,"MMYY")&"-"&TEXT(B6,"00")) -> HYD-0326-04 | D6: 257334077 | E6: IS10748 Gr 2 | F6: 25A3330 | G6: 2.2 | I6: 1250 | J6: 28.46 | U6: =IF(C6="","",SUMIF('Coil to Slit'!B:B,C6,'Coil to Slit'!G:G)) -> 1251 | V6: =IF(U6="","",IF(I6="","⚠ NO PARENT WIDTH",IF(U6>I6,"⚠ EXCEEDS PARENT","✔ OK"))) -> ⚠ EXCEEDS PARENT | W6: =IF(C6="","",IF(COUNTIF(C$3:C6,C6)>1,"⚠ DUPLICATE ID",""))
A7: 46115 | B7: 5 | C7: =IF(OR(A7="",B7=""),"","HYD-"&TEXT(A7,"MMYY")&"-"&TEXT(B7,"00")) -> HYD-0426-05 | D7: 26210917 | E7: HR2 | F7: H111261 | G7: 2 | I7: 1260 | J7: 19.815 | K7: 19.815 | L7: 11,65,122.0 | M7: JOO-0BGCK1QR7 | U7: =IF(C7="","",SUMIF('Coil to Slit'!B:B,C7,'Coil to Slit'!G:G)) -> 1259 | V7: =IF(U7="","",IF(I7="","⚠ NO PARENT WIDTH",IF(U7>I7,"⚠ EXCEEDS PARENT","✔ OK"))) -> ✔ OK | W7: =IF(C7="","",IF(COUNTIF(C$3:C7,C7)>1,"⚠ DUPLICATE ID",""))
A8: 46115 | B8: 6 | C8: =IF(OR(A8="",B8=""),"","HYD-"&TEXT(A8,"MMYY")&"-"&TEXT(B8,"00")) -> HYD-0426-06 | D8: 26242114 | E8: HR2 | F8: H113559 | G8: 2 | I8: 1264 | J8: 22.13 | K8: 22.13 | L8: 13,01,244.0 | M8: JOO-0BGCK1QR7 | U8: =IF(C8="","",SUMIF('Coil to Slit'!B:B,C8,'Coil to Slit'!G:G)) -> 1259 | V8: =IF(U8="","",IF(I8="","⚠ NO PARENT WIDTH",IF(U8>I8,"⚠ EXCEEDS PARENT","✔ OK"))) -> ✔ OK | W8: =IF(C8="","",IF(COUNTIF(C$3:C8,C8)>1,"⚠ DUPLICATE ID",""))
A9: 46115 | B9: 7 | C9: =IF(OR(A9="",B9=""),"","HYD-"&TEXT(A9,"MMYY")&"-"&TEXT(B9,"00")) -> HYD-0426-07 | D9: 26004175 | E9: HR2 | F9: B589219 | G9: 2 | I9: 930 | J9: 14.08 | K9: 14.08 | L9: 8,37,760.00 | M9: JOO-0BGCK1QR7 | U9: =IF(C9="","",SUMIF('Coil to Slit'!B:B,C9,'Coil to Slit'!G:G)) -> 922 | V9: =IF(U9="","",IF(I9="","⚠ NO PARENT WIDTH",IF(U9>I9,"⚠ EXCEEDS PARENT","✔ OK"))) -> ✔ OK | W9: =IF(C9="","",IF(COUNTIF(C$3:C9,C9)>1,"⚠ DUPLICATE ID",""))
C10: =IF(OR(A10="",B10=""),"","HYD-"&TEXT(A10,"MMYY")&"-"&TEXT(B10,"00")) | U10: =IF(C10="","",SUMIF('Coil to Slit'!B:B,C10,'Coil to Slit'!G:G)) | V10: =IF(U10="","",IF(I10="","⚠ NO PARENT WIDTH",IF(U10>I10,"⚠ EXCEEDS PARENT","✔ OK"))) | W10: =IF(C10="","",IF(COUNTIF(C$3:C10,C10)>1,"⚠ DUPLICATE ID",""))
C11: =IF(OR(A11="",B11=""),"","HYD-"&TEXT(A11,"MMYY")&"-"&TEXT(B11,"00")) | U11: =IF(C11="","",SUMIF('Coil to Slit'!B:B,C11,'Coil to Slit'!G:G)) | V11: =IF(U11="","",IF(I11="","⚠ NO PARENT WIDTH",IF(U11>I11,"⚠ EXCEEDS PARENT","✔ OK"))) | W11: =IF(C11="","",IF(COUNTIF(C$3:C11,C11)>1,"⚠ DUPLICATE ID",""))
C12: =IF(OR(A12="",B12=""),"","HYD-"&TEXT(A12,"MMYY")&"-"&TEXT(B12,"00")) | U12: =IF(C12="","",SUMIF('Coil to Slit'!B:B,C12,'Coil to Slit'!G:G)) | V12: =IF(U12="","",IF(I12="","⚠ NO PARENT WIDTH",IF(U12>I12,"⚠ EXCEEDS PARENT","✔ OK"))) | W12: =IF(C12="","",IF(COUNTIF(C$3:C12,C12)>1,"⚠ DUPLICATE ID",""))
C13: =IF(OR(A13="",B13=""),"","HYD-"&TEXT(A13,"MMYY")&"-"&TEXT(B13,"00")) | U13: =IF(C13="","",SUMIF('Coil to Slit'!B:B,C13,'Coil to Slit'!G:G)) | V13: =IF(U13="","",IF(I13="","⚠ NO PARENT WIDTH",IF(U13>I13,"⚠ EXCEEDS PARENT","✔ OK"))) | W13: =IF(C13="","",IF(COUNTIF(C$3:C13,C13)>1,"⚠ DUPLICATE ID",""))
C14: =IF(OR(A14="",B14=""),"","HYD-"&TEXT(A14,"MMYY")&"-"&TEXT(B14,"00")) | U14: =IF(C14="","",SUMIF('Coil to Slit'!B:B,C14,'Coil to Slit'!G:G)) | V14: =IF(U14="","",IF(I14="","⚠ NO PARENT WIDTH",IF(U14>I14,"⚠ EXCEEDS PARENT","✔ OK"))) | W14: =IF(C14="","",IF(COUNTIF(C$3:C14,C14)>1,"⚠ DUPLICATE ID",""))
C15: =IF(OR(A15="",B15=""),"","HYD-"&TEXT(A15,"MMYY")&"-"&TEXT(B15,"00")) | U15: =IF(C15="","",SUMIF('Coil to Slit'!B:B,C15,'Coil to Slit'!G:G)) | V15: =IF(U15="","",IF(I15="","⚠ NO PARENT WIDTH",IF(U15>I15,"⚠ EXCEEDS PARENT","✔ OK"))) | W15: =IF(C15="","",IF(COUNTIF(C$3:C15,C15)>1,"⚠ DUPLICATE ID",""))
C16: =IF(OR(A16="",B16=""),"","HYD-"&TEXT(A16,"MMYY")&"-"&TEXT(B16,"00")) | U16: =IF(C16="","",SUMIF('Coil to Slit'!B:B,C16,'Coil to Slit'!G:G)) | V16: =IF(U16="","",IF(I16="","⚠ NO PARENT WIDTH",IF(U16>I16,"⚠ EXCEEDS PARENT","✔ OK"))) | W16: =IF(C16="","",IF(COUNTIF(C$3:C16,C16)>1,"⚠ DUPLICATE ID",""))
C17: =IF(OR(A17="",B17=""),"","HYD-"&TEXT(A17,"MMYY")&"-"&TEXT(B17,"00")) | U17: =IF(C17="","",SUMIF('Coil to Slit'!B:B,C17,'Coil to Slit'!G:G)) | V17: =IF(U17="","",IF(I17="","⚠ NO PARENT WIDTH",IF(U17>I17,"⚠ EXCEEDS PARENT","✔ OK"))) | W17: =IF(C17="","",IF(COUNTIF(C$3:C17,C17)>1,"⚠ DUPLICATE ID",""))
C18: =IF(OR(A18="",B18=""),"","HYD-"&TEXT(A18,"MMYY")&"-"&TEXT(B18,"00")) | U18: =IF(C18="","",SUMIF('Coil to Slit'!B:B,C18,'Coil to Slit'!G:G)) | V18: =IF(U18="","",IF(I18="","⚠ NO PARENT WIDTH",IF(U18>I18,"⚠ EXCEEDS PARENT","✔ OK"))) | W18: =IF(C18="","",IF(COUNTIF(C$3:C18,C18)>1,"⚠ DUPLICATE ID",""))
C19: =IF(OR(A19="",B19=""),"","HYD-"&TEXT(A19,"MMYY")&"-"&TEXT(B19,"00")) | U19: =IF(C19="","",SUMIF('Coil to Slit'!B:B,C19,'Coil to Slit'!G:G)) | V19: =IF(U19="","",IF(I19="","⚠ NO PARENT WIDTH",IF(U19>I19,"⚠ EXCEEDS PARENT","✔ OK"))) | W19: =IF(C19="","",IF(COUNTIF(C$3:C19,C19)>1,"⚠ DUPLICATE ID",""))
C20: =IF(OR(A20="",B20=""),"","HYD-"&TEXT(A20,"MMYY")&"-"&TEXT(B20,"00")) | U20: =IF(C20="","",SUMIF('Coil to Slit'!B:B,C20,'Coil to Slit'!G:G)) | V20: =IF(U20="","",IF(I20="","⚠ NO PARENT WIDTH",IF(U20>I20,"⚠ EXCEEDS PARENT","✔ OK"))) | W20: =IF(C20="","",IF(COUNTIF(C$3:C20,C20)>1,"⚠ DUPLICATE ID",""))
C21: =IF(OR(A21="",B21=""),"","HYD-"&TEXT(A21,"MMYY")&"-"&TEXT(B21,"00")) | U21: =IF(C21="","",SUMIF('Coil to Slit'!B:B,C21,'Coil to Slit'!G:G)) | V21: =IF(U21="","",IF(I21="","⚠ NO PARENT WIDTH",IF(U21>I21,"⚠ EXCEEDS PARENT","✔ OK"))) | W21: =IF(C21="","",IF(COUNTIF(C$3:C21,C21)>1,"⚠ DUPLICATE ID",""))
... C100: =IF(OR(A100="",B100=""),"","HYD-"&TEXT(A100,"MMYY")&"-"&TEXT(B100,"00")) | U100: =IF(C100="","",SUMIF('Coil to Slit'!B:B,C100,'Coil to Slit'!G:G)) | V100: =IF(U100="","",IF(I100="","⚠ NO PARENT WIDTH",IF(U100>I100,"⚠ EXCEEDS PARENT","✔ OK"))) | W100: =IF(C100="","",IF(COUNTIF(C$3:C100,C100)>1,"⚠ DUPLICATE ID",""))

Sheet Coil to Slit
A1: 🔵 Manual Entry ↓ | K1: 🟡 Validation Helpers ↓
A2: Date of Conversion | B2: HR Coil ID | C2: Baby Coil Entry (A,B,C...) | D2: Baby Coil ID | E2: Thickness (mm) | F2: Length (mm) | G2: Width (mm) | H2: Weight (T) | I2: Cost Price (₹) | J2: PO Number | K2: Sum Baby Width for HR Coil (mm) | L2: Parent Coil Width (mm) | M2: Width Validation | N2: Duplicate Baby ID Check | O2: Width Sum vs Parent (mm)
A3: 46108 | B3: HYD-0326-01 | C3: A | D3: =IF(OR(B3="",C3=""),"",CONCATENATE(B3,"-",C3)) -> HYD-0326-01-A | E3: =IF(B3="","",IFERROR(VLOOKUP(B3,'Coil Sheet at Plant'!$C:$G,5,FALSE),"ID Not Found")) -> 2.8 | F3: =IF(B3="","",IFERROR(VLOOKUP(B3,'Coil Sheet at Plant'!$C:$H,6,FALSE),"ID Not Found")) -> 0 | G3: 147 | H3: =IF(OR(B3="",G3=""),"",IFERROR(VLOOKUP(B3,'Coil Sheet at Plant'!$C:$J,8,FALSE),0)*G3/SUMIF(B:B,B3,G:G)) -> 2.4397506 | I3: =IF(B3="","",IFERROR(VLOOKUP(B3,'Coil Sheet at Plant'!$C:$L,9,FALSE),"")) -> 0 | J3: =IF(B3="","",IFERROR(VLOOKUP(B3,'Coil Sheet at Plant'!$C:$M,10,FALSE),"")) -> 0 | K3: =IF(B3="","",SUMIF(B:B,B3,G:G)) -> 1243 | L3: =IF(B3="","",IFERROR(VLOOKUP(B3,'Coil Sheet at Plant'!$C:$I,7,FALSE),"")) -> 1250 | M3: =IF(OR(K3="",L3=""),"",IF(L3=0,"⚠ NO PARENT WIDTH",IF(K3>L3,"⚠ BABY > PARENT","✔ OK"))) -> ✔ OK | N3: =IF(D3="","",IF(COUNTIF(D$3:D3,D3)>1,"⚠ DUPLICATE","")) | O3: =IF(B3="","",SUMIF(B:B,B3,G:G)&" / "&IFERROR(VLOOKUP(B3,'Coil Sheet at Plant'!$C:$I,7,FALSE),"?")&" mm") -> 1243 / 1250 mm
A4: 46108 | B4: HYD-0326-01 | C4: B | D4: =IF(OR(B4="",C4=""),"",CONCATENATE(B4,"-",C4)) -> HYD-0326-01-B | E4: =IF(B4="","",IFERROR(VLOOKUP(B4,'Coil Sheet at Plant'!$C:$G,5,FALSE),"ID Not Found")) -> 2.8 | F4: =IF(B4="","",IFERROR(VLOOKUP(B4,'Coil Sheet at Plant'!$C:$H,6,FALSE),"ID Not Found")) -> 0 | G4: 147 | H4: =IF(OR(B4="",G4=""),"",IFERROR(VLOOKUP(B4,'Coil Sheet at Plant'!$C:$J,8,FALSE),0)*G4/SUMIF(B:B,B4,G:G)) -> 2.4397506 | I4: =IF(B4="","",IFERROR(VLOOKUP(B4,'Coil Sheet at Plant'!$C:$L,9,FALSE),"")) -> 0 | J4: =IF(B4="","",IFERROR(VLOOKUP(B4,'Coil Sheet at Plant'!$C:$M,10,FALSE),"")) -> 0 | K4: =IF(B4="","",SUMIF(B:B,B4,G:G)) -> 1243 | L4: =IF(B4="","",IFERROR(VLOOKUP(B4,'Coil Sheet at Plant'!$C:$I,7,FALSE),"")) -> 1250 | M4: =IF(OR(K4="",L4=""),"",IF(L4=0,"⚠ NO PARENT WIDTH",IF(K4>L4,"⚠ BABY > PARENT","✔ OK"))) -> ✔ OK | N4: =IF(D4="","",IF(COUNTIF(D$3:D4,D4)>1,"⚠ DUPLICATE","")) | O4: =IF(B4="","",SUMIF(B:B,B4,G:G)&" / "&IFERROR(VLOOKUP(B4,'Coil Sheet at Plant'!$C:$I,7,FALSE),"?")&" mm") -> 1243 / 1250 mm
A5: 46108 | B5: HYD-0326-01 | C5: C | D5: =IF(OR(B5="",C5=""),"",CONCATENATE(B5,"-",C5)) -> HYD-0326-01-C | E5: =IF(B5="","",IFERROR(VLOOKUP(B5,'Coil Sheet at Plant'!$C:$G,5,FALSE),"ID Not Found")) -> 2.8 | F5: =IF(B5="","",IFERROR(VLOOKUP(B5,'Coil Sheet at Plant'!$C:$H,6,FALSE),"ID Not Found")) -> 0 | G5: 147 | H5: =IF(OR(B5="",G5=""),"",IFERROR(VLOOKUP(B5,'Coil Sheet at Plant'!$C:$J,8,FALSE),0)*G5/SUMIF(B:B,B5,G:G)) -> 2.4397506 | I5: =IF(B5="","",IFERROR(VLOOKUP(B5,'Coil Sheet at Plant'!$C:$L,9,FALSE),"")) -> 0 | J5: =IF(B5="","",IFERROR(VLOOKUP(B5,'Coil Sheet at Plant'!$C:$M,10,FALSE),"")) -> 0 | K5: =IF(B5="","",SUMIF(B:B,B5,G:G)) -> 1243 | L5: =IF(B5="","",IFERROR(VLOOKUP(B5,'Coil Sheet at Plant'!$C:$I,7,FALSE),"")) -> 1250 | M5: =IF(OR(K5="",L5=""),"",IF(L5=0,"⚠ NO PARENT WIDTH",IF(K5>L5,"⚠ BABY > PARENT","✔ OK"))) -> ✔ OK | N5: =IF(D5="","",IF(COUNTIF(D$3:D5,D5)>1,"⚠ DUPLICATE","")) | O5: =IF(B5="","",SUMIF(B:B,B5,G:G)&" / "&IFERROR(VLOOKUP(B5,'Coil Sheet at Plant'!$C:$I,7,FALSE),"?")&" mm") -> 1243 / 1250 mm
A6: 46108 | B6: HYD-0326-01 | C6: D | D6: =IF(OR(B6="",C6=""),"",CONCATENATE(B6,"-",C6)) -> HYD-0326-01-D | E6: =IF(B6="","",IFERROR(VLOOKUP(B6,'Coil Sheet at Plant'!$C:$G,5,FALSE),"ID Not Found")) -> 2.8 | F6: =IF(B6="","",IFERROR(VLOOKUP(B6,'Coil Sheet at Plant'!$C:$H,6,FALSE),"ID Not Found")) -> 0 | G6: 147 | H6: =IF(OR(B6="",G6=""),"",IFERROR(VLOOKUP(B6,'Coil Sheet at Plant'!$C:$J,8,FALSE),0)*G6/SUMIF(B:B,B6,G:G)) -> 2.4397506 | I6: =IF(B6="","",IFERROR(VLOOKUP(B6,'Coil Sheet at Plant'!$C:$L,9,FALSE),"")) -> 0 | J6: =IF(B6="","",IFERROR(VLOOKUP(B6,'Coil Sheet at Plant'!$C:$M,10,FALSE),"")) -> 0 | K6: =IF(B6="","",SUMIF(B:B,B6,G:G)) -> 1243 | L6: =IF(B6="","",IFERROR(VLOOKUP(B6,'Coil Sheet at Plant'!$C:$I,7,FALSE),"")) -> 1250 | M6: =IF(OR(K6="",L6=""),"",IF(L6=0,"⚠ NO PARENT WIDTH",IF(K6>L6,"⚠ BABY > PARENT","✔ OK"))) -> ✔ OK | N6: =IF(D6="","",IF(COUNTIF(D$3:D6,D6)>1,"⚠ DUPLICATE","")) | O6: =IF(B6="","",SUMIF(B:B,B6,G:G)&" / "&IFERROR(VLOOKUP(B6,'Coil Sheet at Plant'!$C:$I,7,FALSE),"?")&" mm") -> 1243 / 1250 mm
A7: 46108 | B7: HYD-0326-01 | C7: E | D7: =IF(OR(B7="",C7=""),"",CONCATENATE(B7,"-",C7)) -> HYD-0326-01-E | E7: =IF(B7="","",IFERROR(VLOOKUP(B7,'Coil Sheet at Plant'!$C:$G,5,FALSE),"ID Not Found")) -> 2.8 | F7: =IF(B7="","",IFERROR(VLOOKUP(B7,'Coil Sheet at Plant'!$C:$H,6,FALSE),"ID Not Found")) -> 0 | G7: 147 | H7: =IF(OR(B7="",G7=""),"",IFERROR(VLOOKUP(B7,'Coil Sheet at Plant'!$C:$J,8,FALSE),0)*G7/SUMIF(B:B,B7,G:G)) -> 2.4397506 | I7: =IF(B7="","",IFERROR(VLOOKUP(B7,'Coil Sheet at Plant'!$C:$L,9,FALSE),"")) -> 0 | J7: =IF(B7="","",IFERROR(VLOOKUP(B7,'Coil Sheet at Plant'!$C:$M,10,FALSE),"")) -> 0 | K7: =IF(B7="","",SUMIF(B:B,B7,G:G)) -> 1243 | L7: =IF(B7="","",IFERROR(VLOOKUP(B7,'Coil Sheet at Plant'!$C:$I,7,FALSE),"")) -> 1250 | M7: =IF(OR(K7="",L7=""),"",IF(L7=0,"⚠ NO PARENT WIDTH",IF(K7>L7,"⚠ BABY > PARENT","✔ OK"))) -> ✔ OK | N7: =IF(D7="","",IF(COUNTIF(D$3:D7,D7)>1,"⚠ DUPLICATE","")) | O7: =IF(B7="","",SUMIF(B:B,B7,G:G)&" / "&IFERROR(VLOOKUP(B7,'Coil Sheet at Plant'!$C:$I,7,FALSE),"?")&" mm") -> 1243 / 1250 mm
A8: 46108 | B8: HYD-0326-01 | C8: F | D8: =IF(OR(B8="",C8=""),"",CONCATENATE(B8,"-",C8)) -> HYD-0326-01-F | E8: =IF(B8="","",IFERROR(VLOOKUP(B8,'Coil Sheet at Plant'!$C:$G,5,FALSE),"ID Not Found")) -> 2.8 | F8: =IF(B8="","",IFERROR(VLOOKUP(B8,'Coil Sheet at Plant'!$C:$H,6,FALSE),"ID Not Found")) -> 0 | G8: 196 | H8: =IF(OR(B8="",G8=""),"",IFERROR(VLOOKUP(B8,'Coil Sheet at Plant'!$C:$J,8,FALSE),0)*G8/SUMIF(B:B,B8,G:G)) -> 3.2530008 | I8: =IF(B8="","",IFERROR(VLOOKUP(B8,'Coil Sheet at Plant'!$C:$L,9,FALSE),"")) -> 0 | J8: =IF(B8="","",IFERROR(VLOOKUP(B8,'Coil Sheet at Plant'!$C:$M,10,FALSE),"")) -> 0 | K8: =IF(B8="","",SUMIF(B:B,B8,G:G)) -> 1243 | L8: =IF(B8="","",IFERROR(VLOOKUP(B8,'Coil Sheet at Plant'!$C:$I,7,FALSE),"")) -> 1250 | M8: =IF(OR(K8="",L8=""),"",IF(L8=0,"⚠ NO PARENT WIDTH",IF(K8>L8,"⚠ BABY > PARENT","✔ OK"))) -> ✔ OK | N8: =IF(D8="","",IF(COUNTIF(D$3:D8,D8)>1,"⚠ DUPLICATE","")) | O8: =IF(B8="","",SUMIF(B:B,B8,G:G)&" / "&IFERROR(VLOOKUP(B8,'Coil Sheet at Plant'!$C:$I,7,FALSE),"?")&" mm") -> 1243 / 1250 mm
A9: 46108 | B9: HYD-0326-01 | C9: G | D9: =IF(OR(B9="",C9=""),"",CONCATENATE(B9,"-",C9)) -> HYD-0326-01-G | E9: =IF(B9="","",IFERROR(VLOOKUP(B9,'Coil Sheet at Plant'!$C:$G,5,FALSE),"ID Not Found")) -> 2.8 | F9: =IF(B9="","",IFERROR(VLOOKUP(B9,'Coil Sheet at Plant'!$C:$H,6,FALSE),"ID Not Found")) -> 0 | G9: 196 | H9: =IF(OR(B9="",G9=""),"",IFERROR(VLOOKUP(B9,'Coil Sheet at Plant'!$C:$J,8,FALSE),0)*G9/SUMIF(B:B,B9,G:G)) -> 3.2530008 | I9: =IF(B9="","",IFERROR(VLOOKUP(B9,'Coil Sheet at Plant'!$C:$L,9,FALSE),"")) -> 0 | J9: =IF(B9="","",IFERROR(VLOOKUP(B9,'Coil Sheet at Plant'!$C:$M,10,FALSE),"")) -> 0 | K9: =IF(B9="","",SUMIF(B:B,B9,G:G)) -> 1243 | L9: =IF(B9="","",IFERROR(VLOOKUP(B9,'Coil Sheet at Plant'!$C:$I,7,FALSE),"")) -> 1250 | M9: =IF(OR(K9="",L9=""),"",IF(L9=0,"⚠ NO PARENT WIDTH",IF(K9>L9,"⚠ BABY > PARENT","✔ OK"))) -> ✔ OK | N9: =IF(D9="","",IF(COUNTIF(D$3:D9,D9)>1,"⚠ DUPLICATE","")) | O9: =IF(B9="","",SUMIF(B:B,B9,G:G)&" / "&IFERROR(VLOOKUP(B9,'Coil Sheet at Plant'!$C:$I,7,FALSE),"?")&" mm") -> 1243 / 1250 mm
A10: 46108 | B10: HYD-0326-01 | C10: H | D10: =IF(OR(B10="",C10=""),"",CONCATENATE(B10,"-",C10)) -> HYD-0326-01-H | E10: =IF(B10="","",IFERROR(VLOOKUP(B10,'Coil Sheet at Plant'!$C:$G,5,FALSE),"ID Not Found")) -> 2.8 | F10: =IF(B10="","",IFERROR(VLOOKUP(B10,'Coil Sheet at Plant'!$C:$H,6,FALSE),"ID Not Found")) -> 0 | G10: 116 | H10: =IF(OR(B10="",G10=""),"",IFERROR(VLOOKUP(B10,'Coil Sheet at Plant'!$C:$J,8,FALSE),0)*G10/SUMIF(B:B,B10,G:G)) -> 1.9252454 | I10: =IF(B10="","",IFERROR(VLOOKUP(B10,'Coil Sheet at Plant'!$C:$L,9,FALSE),"")) -> 0 | J10: =IF(B10="","",IFERROR(VLOOKUP(B10,'Coil Sheet at Plant'!$C:$M,10,FALSE),"")) -> 0 | K10: =IF(B10="","",SUMIF(B:B,B10,G:G)) -> 1243 | L10: =IF(B10="","",IFERROR(VLOOKUP(B10,'Coil Sheet at Plant'!$C:$I,7,FALSE),"")) -> 1250 | M10: =IF(OR(K10="",L10=""),"",IF(L10=0,"⚠ NO PARENT WIDTH",IF(K10>L10,"⚠ BABY > PARENT","✔ OK"))) -> ✔ OK | N10: =IF(D10="","",IF(COUNTIF(D$3:D10,D10)>1,"⚠ DUPLICATE","")) | O10: =IF(B10="","",SUMIF(B:B,B10,G:G)&" / "&IFERROR(VLOOKUP(B10,'Coil Sheet at Plant'!$C:$I,7,FALSE),"?")&" mm") -> 1243 / 1250 mm
A11: 46108 | B11: HYD-0326-02 | C11: A | D11: =IF(OR(B11="",C11=""),"",CONCATENATE(B11,"-",C11)) -> HYD-0326-02-A | E11: =IF(B11="","",IFERROR(VLOOKUP(B11,'Coil Sheet at Plant'!$C:$G,5,FALSE),"ID Not Found")) -> 2.8 | F11: =IF(B11="","",IFERROR(VLOOKUP(B11,'Coil Sheet at Plant'!$C:$H,6,FALSE),"ID Not Found")) -> 0 | G11: 147 | H11: =IF(OR(B11="",G11=""),"",IFERROR(VLOOKUP(B11,'Coil Sheet at Plant'!$C:$J,8,FALSE),0)*G11/SUMIF(B:B,B11,G:G)) -> 2.4752293 | I11: =IF(B11="","",IFERROR(VLOOKUP(B11,'Coil Sheet at Plant'!$C:$L,9,FALSE),"")) -> 0 | J11: =IF(B11="","",IFERROR(VLOOKUP(B11,'Coil Sheet at Plant'!$C:$M,10,FALSE),"")) -> 0 | K11: =IF(B11="","",SUMIF(B:B,B11,G:G)) -> 1243 | L11: =IF(B11="","",IFERROR(VLOOKUP(B11,'Coil Sheet at Plant'!$C:$I,7,FALSE),"")) -> 1250 | M11: =IF(OR(K11="",L11=""),"",IF(L11=0,"⚠ NO PARENT WIDTH",IF(K11>L11,"⚠ BABY > PARENT","✔ OK"))) -> ✔ OK | N11: =IF(D11="","",IF(COUNTIF(D$3:D11,D11)>1,"⚠ DUPLICATE","")) | O11: =IF(B11="","",SUMIF(B:B,B11,G:G)&" / "&IFERROR(VLOOKUP(B11,'Coil Sheet at Plant'!$C:$I,7,FALSE),"?")&" mm") -> 1243 / 1250 mm
A12: 46108 | B12: HYD-0326-02 | C12: B | D12: =IF(OR(B12="",C12=""),"",CONCATENATE(B12,"-",C12)) -> HYD-0326-02-B | E12: =IF(B12="","",IFERROR(VLOOKUP(B12,'Coil Sheet at Plant'!$C:$G,5,FALSE),"ID Not Found")) -> 2.8 | F12: =IF(B12="","",IFERROR(VLOOKUP(B12,'Coil Sheet at Plant'!$C:$H,6,FALSE),"ID Not Found")) -> 0 | G12: 147 | H12: =IF(OR(B12="",G12=""),"",IFERROR(VLOOKUP(B12,'Coil Sheet at Plant'!$C:$J,8,FALSE),0)*G12/SUMIF(B:B,B12,G:G)) -> 2.4752293 | I12: =IF(B12="","",IFERROR(VLOOKUP(B12,'Coil Sheet at Plant'!$C:$L,9,FALSE),"")) -> 0 | J12: =IF(B12="","",IFERROR(VLOOKUP(B12,'Coil Sheet at Plant'!$C:$M,10,FALSE),"")) -> 0 | K12: =IF(B12="","",SUMIF(B:B,B12,G:G)) -> 1243 | L12: =IF(B12="","",IFERROR(VLOOKUP(B12,'Coil Sheet at Plant'!$C:$I,7,FALSE),"")) -> 1250 | M12: =IF(OR(K12="",L12=""),"",IF(L12=0,"⚠ NO PARENT WIDTH",IF(K12>L12,"⚠ BABY > PARENT","✔ OK"))) -> ✔ OK | N12: =IF(D12="","",IF(COUNTIF(D$3:D12,D12)>1,"⚠ DUPLICATE","")) | O12: =IF(B12="","",SUMIF(B:B,B12,G:G)&" / "&IFERROR(VLOOKUP(B12,'Coil Sheet at Plant'!$C:$I,7,FALSE),"?")&" mm") -> 1243 / 1250 mm
A13: 46108 | B13: HYD-0326-02 | C13: C | D13: =IF(OR(B13="",C13=""),"",CONCATENATE(B13,"-",C13)) -> HYD-0326-02-C | E13: =IF(B13="","",IFERROR(VLOOKUP(B13,'Coil Sheet at Plant'!$C:$G,5,FALSE),"ID Not Found")) -> 2.8 | F13: =IF(B13="","",IFERROR(VLOOKUP(B13,'Coil Sheet at Plant'!$C:$H,6,FALSE),"ID Not Found")) -> 0 | G13: 147 | H13: =IF(OR(B13="",G13=""),"",IFERROR(VLOOKUP(B13,'Coil Sheet at Plant'!$C:$J,8,FALSE),0)*G13/SUMIF(B:B,B13,G:G)) -> 2.4752293 | I13: =IF(B13="","",IFERROR(VLOOKUP(B13,'Coil Sheet at Plant'!$C:$L,9,FALSE),"")) -> 0 | J13: =IF(B13="","",IFERROR(VLOOKUP(B13,'Coil Sheet at Plant'!$C:$M,10,FALSE),"")) -> 0 | K13: =IF(B13="","",SUMIF(B:B,B13,G:G)) -> 1243 | L13: =IF(B13="","",IFERROR(VLOOKUP(B13,'Coil Sheet at Plant'!$C:$I,7,FALSE),"")) -> 1250 | M13: =IF(OR(K13="",L13=""),"",IF(L13=0,"⚠ NO PARENT WIDTH",IF(K13>L13,"⚠ BABY > PARENT","✔ OK"))) -> ✔ OK | N13: =IF(D13="","",IF(COUNTIF(D$3:D13,D13)>1,"⚠ DUPLICATE","")) | O13: =IF(B13="","",SUMIF(B:B,B13,G:G)&" / "&IFERROR(VLOOKUP(B13,'Coil Sheet at Plant'!$C:$I,7,FALSE),"?")&" mm") -> 1243 / 1250 mm
A14: 46108 | B14: HYD-0326-02 | C14: D | D14: =IF(OR(B14="",C14=""),"",CONCATENATE(B14,"-",C14)) -> HYD-0326-02-D | E14: =IF(B14="","",IFERROR(VLOOKUP(B14,'Coil Sheet at Plant'!$C:$G,5,FALSE),"ID Not Found")) -> 2.8 | F14: =IF(B14="","",IFERROR(VLOOKUP(B14,'Coil Sheet at Plant'!$C:$H,6,FALSE),"ID Not Found")) -> 0 | G14: 147 | H14: =IF(OR(B14="",G14=""),"",IFERROR(VLOOKUP(B14,'Coil Sheet at Plant'!$C:$J,8,FALSE),0)*G14/SUMIF(B:B,B14,G:G)) -> 2.4752293 | I14: =IF(B14="","",IFERROR(VLOOKUP(B14,'Coil Sheet at Plant'!$C:$L,9,FALSE),"")) -> 0 | J14: =IF(B14="","",IFERROR(VLOOKUP(B14,'Coil Sheet at Plant'!$C:$M,10,FALSE),"")) -> 0 | K14: =IF(B14="","",SUMIF(B:B,B14,G:G)) -> 1243 | L14: =IF(B14="","",IFERROR(VLOOKUP(B14,'Coil Sheet at Plant'!$C:$I,7,FALSE),"")) -> 1250 | M14: =IF(OR(K14="",L14=""),"",IF(L14=0,"⚠ NO PARENT WIDTH",IF(K14>L14,"⚠ BABY > PARENT","✔ OK"))) -> ✔ OK | N14: =IF(D14="","",IF(COUNTIF(D$3:D14,D14)>1,"⚠ DUPLICATE","")) | O14: =IF(B14="","",SUMIF(B:B,B14,G:G)&" / "&IFERROR(VLOOKUP(B14,'Coil Sheet at Plant'!$C:$I,7,FALSE),"?")&" mm") -> 1243 / 1250 mm
... A28: 46109 | B28: HYD-0326-03 | C28: J | D28: =IF(OR(B28="",C28=""),"",CONCATENATE(B28,"-",C28)) -> HYD-0326-03-J | E28: =IF(B28="","",IFERROR(VLOOKUP(B28,'Coil Sheet at Plant'!$C:$G,5,FALSE),"ID Not Found")) -> 2.5 | F28: =IF(B28="","",IFERROR(VLOOKUP(B28,'Coil Sheet at Plant'!$C:$H,6,FALSE),"ID Not Found")) -> 0 | G28: 96 | H28: =IF(OR(B28="",G28=""),"",IFERROR(VLOOKUP(B28,'Coil Sheet at Plant'!$C:$J,8,FALSE),0)*G28/SUMIF(B:B,B28,G:G)) -> 1.8695745 | I28: =IF(B28="","",IFERROR(VLOOKUP(B28,'Coil Sheet at Plant'!$C:$L,9,FALSE),"")) -> 0 | J28: =IF(B28="","",IFERROR(VLOOKUP(B28,'Coil Sheet at Plant'!$C:$M,10,FALSE),"")) -> 0 | K28: =IF(B28="","",SUMIF(B:B,B28,G:G)) -> 1504 | L28: =IF(B28="","",IFERROR(VLOOKUP(B28,'Coil Sheet at Plant'!$C:$I,7,FALSE),"")) -> 1500 | M28: =IF(OR(K28="",L28=""),"",IF(L28=0,"⚠ NO PARENT WIDTH",IF(K28>L28,"⚠ BABY > PARENT","✔ OK"))) -> ⚠ BABY > PARENT | N28: =IF(D28="","",IF(COUNTIF(D$3:D28,D28)>1,"⚠ DUPLICATE","")) | O28: =IF(B28="","",SUMIF(B:B,B28,G:G)&" / "&IFERROR(VLOOKUP(B28,'Coil Sheet at Plant'!$C:$I,7,FALSE),"?")&" mm") -> 1504 / 1500 mm
A29: 29-03-2026 | B29: HYD-0326-04 | C29: A | D29: =IF(OR(B29="",C29=""),"",CONCATENATE(B29,"-",C29)) -> HYD-0326-04-A | E29: =IF(B29="","",IFERROR(VLOOKUP(B29,'Coil Sheet at Plant'!$C:$G,5,FALSE),"ID Not Found")) -> 2.2 | F29: =IF(B29="","",IFERROR(VLOOKUP(B29,'Coil Sheet at Plant'!$C:$H,6,FALSE),"ID Not Found")) -> 0 | G29: 148 | H29: =IF(OR(B29="",G29=""),"",IFERROR(VLOOKUP(B29,'Coil Sheet at Plant'!$C:$J,8,FALSE),0)*G29/SUMIF(B:B,B29,G:G)) -> 3.3669704 | I29: =IF(B29="","",IFERROR(VLOOKUP(B29,'Coil Sheet at Plant'!$C:$L,9,FALSE),"")) -> 0 | J29: =IF(B29="","",IFERROR(VLOOKUP(B29,'Coil Sheet at Plant'!$C:$M,10,FALSE),"")) -> 0 | K29: =IF(B29="","",SUMIF(B:B,B29,G:G)) -> 1251 | L29: =IF(B29="","",IFERROR(VLOOKUP(B29,'Coil Sheet at Plant'!$C:$I,7,FALSE),"")) -> 1250 | M29: =IF(OR(K29="",L29=""),"",IF(L29=0,"⚠ NO PARENT WIDTH",IF(K29>L29,"⚠ BABY > PARENT","✔ OK"))) -> ⚠ BABY > PARENT | N29: =IF(D29="","",IF(COUNTIF(D$3:D29,D29)>1,"⚠ DUPLICATE","")) | O29: =IF(B29="","",SUMIF(B:B,B29,G:G)&" / "&IFERROR(VLOOKUP(B29,'Coil Sheet at Plant'!$C:$I,7,FALSE),"?")&" mm") -> 1251 / 1250 mm
A30: 29-03-2026 | B30: HYD-0326-04 | C30: B | D30: =IF(OR(B30="",C30=""),"",CONCATENATE(B30,"-",C30)) -> HYD-0326-04-B | E30: =IF(B30="","",IFERROR(VLOOKUP(B30,'Coil Sheet at Plant'!$C:$G,5,FALSE),"ID Not Found")) -> 2.2 | F30: =IF(B30="","",IFERROR(VLOOKUP(B30,'Coil Sheet at Plant'!$C:$H,6,FALSE),"ID Not Found")) -> 0 | G30: 148 | H30: =IF(OR(B30="",G30=""),"",IFERROR(VLOOKUP(B30,'Coil Sheet at Plant'!$C:$J,8,FALSE),0)*G30/SUMIF(B:B,B30,G:G)) -> 3.3669704 | I30: =IF(B30="","",IFERROR(VLOOKUP(B30,'Coil Sheet at Plant'!$C:$L,9,FALSE),"")) -> 0 | J30: =IF(B30="","",IFERROR(VLOOKUP(B30,'Coil Sheet at Plant'!$C:$M,10,FALSE),"")) -> 0 | K30: =IF(B30="","",SUMIF(B:B,B30,G:G)) -> 1251 | L30: =IF(B30="","",IFERROR(VLOOKUP(B30,'Coil Sheet at Plant'!$C:$I,7,FALSE),"")) -> 1250 | M30: =IF(OR(K30="",L30=""),"",IF(L30=0,"⚠ NO PARENT WIDTH",IF(K30>L30,"⚠ BABY > PARENT","✔ OK"))) -> ⚠ BABY > PARENT | N30: =IF(D30="","",IF(COUNTIF(D$3:D30,D30)>1,"⚠ DUPLICATE","")) | O30: =IF(B30="","",SUMIF(B:B,B30,G:G)&" / "&IFERROR(VLOOKUP(B30,'Coil Sheet at Plant'!$C:$I,7,FALSE),"?")&" mm") -> 1251 / 1250 mm
A31: 29-03-2026 | B31: HYD-0326-04 | C31: C | D31: =IF(OR(B31="",C31=""),"",CONCATENATE(B31,"-",C31)) -> HYD-0326-04-C | E31: =IF(B31="","",IFERROR(VLOOKUP(B31,'Coil Sheet at Plant'!$C:$G,5,FALSE),"ID Not Found")) -> 2.2 | F31: =IF(B31="","",IFERROR(VLOOKUP(B31,'Coil Sheet at Plant'!$C:$H,6,FALSE),"ID Not Found")) -> 0 | G31: 148 | H31: =IF(OR(B31="",G31=""),"",IFERROR(VLOOKUP(B31,'Coil Sheet at Plant'!$C:$J,8,FALSE),0)*G31/SUMIF(B:B,B31,G:G)) -> 3.3669704 | I31: =IF(B31="","",IFERROR(VLOOKUP(B31,'Coil Sheet at Plant'!$C:$L,9,FALSE),"")) -> 0 | J31: =IF(B31="","",IFERROR(VLOOKUP(B31,'Coil Sheet at Plant'!$C:$M,10,FALSE),"")) -> 0 | K31: =IF(B31="","",SUMIF(B:B,B31,G:G)) -> 1251 | L31: =IF(B31="","",IFERROR(VLOOKUP(B31,'Coil Sheet at Plant'!$C:$I,7,FALSE),"")) -> 1250 | M31: =IF(OR(K31="",L31=""),"",IF(L31=0,"⚠ NO PARENT WIDTH",IF(K31>L31,"⚠ BABY > PARENT","✔ OK"))) -> ⚠ BABY > PARENT | N31: =IF(D31="","",IF(COUNTIF(D$3:D31,D31)>1,"⚠ DUPLICATE","")) | O31: =IF(B31="","",SUMIF(B:B,B31,G:G)&" / "&IFERROR(VLOOKUP(B31,'Coil Sheet at Plant'!$C:$I,7,FALSE),"?")&" mm") -> 1251 / 1250 mm
A32: 29-03-2026 | B32: HYD-0326-04 | C32: D | D32: =IF(OR(B32="",C32=""),"",CONCATENATE(B32,"-",C32)) -> HYD-0326-04-D | E32: =IF(B32="","",IFERROR(VLOOKUP(B32,'Coil Sheet at Plant'!$C:$G,5,FALSE),"ID Not Found")) -> 2.2 | F32: =IF(B32="","",IFERROR(VLOOKUP(B32,'Coil Sheet at Plant'!$C:$H,6,FALSE),"ID Not Found")) -> 0 | G32: 148 | H32: =IF(OR(B32="",G32=""),"",IFERROR(VLOOKUP(B32,'Coil Sheet at Plant'!$C:$J,8,FALSE),0)*G32/SUMIF(B:B,B32,G:G)) -> 3.3669704 | I32: =IF(B32="","",IFERROR(VLOOKUP(B32,'Coil Sheet at Plant'!$C:$L,9,FALSE),"")) -> 0 | J32: =IF(B32="","",IFERROR(VLOOKUP(B32,'Coil Sheet at Plant'!$C:$M,10,FALSE),"")) -> 0 | K32: =IF(B32="","",SUMIF(B:B,B32,G:G)) -> 1251 | L32: =IF(B32="","",IFERROR(VLOOKUP(B32,'Coil Sheet at Plant'!$C:$I,7,FALSE),"")) -> 1250 | M32: =IF(OR(K32="",L32=""),"",IF(L32=0,"⚠ NO PARENT WIDTH",IF(K32>L32,"⚠ BABY > PARENT","✔ OK"))) -> ⚠ BABY > PARENT | N32: =IF(D32="","",IF(COUNTIF(D$3:D32,D32)>1,"⚠ DUPLICATE","")) | O32: =IF(B32="","",SUMIF(B:B,B32,G:G)&" / "&IFERROR(VLOOKUP(B32,'Coil Sheet at Plant'!$C:$I,7,FALSE),"?")&" mm") -> 1251 / 1250 mm
A33: 29-03-2026 | B33: HYD-0326-04 | C33: E | D33: =IF(OR(B33="",C33=""),"",CONCATENATE(B33,"-",C33)) -> HYD-0326-04-E | E33: =IF(B33="","",IFERROR(VLOOKUP(B33,'Coil Sheet at Plant'!$C:$G,5,FALSE),"ID Not Found")) -> 2.2 | F33: =IF(B33="","",IFERROR(VLOOKUP(B33,'Coil Sheet at Plant'!$C:$H,6,FALSE),"ID Not Found")) -> 0 | G33: 148 | H33: =IF(OR(B33="",G33=""),"",IFERROR(VLOOKUP(B33,'Coil Sheet at Plant'!$C:$J,8,FALSE),0)*G33/SUMIF(B:B,B33,G:G)) -> 3.3669704 | I33: =IF(B33="","",IFERROR(VLOOKUP(B33,'Coil Sheet at Plant'!$C:$L,9,FALSE),"")) -> 0 | J33: =IF(B33="","",IFERROR(VLOOKUP(B33,'Coil Sheet at Plant'!$C:$M,10,FALSE),"")) -> 0 | K33: =IF(B33="","",SUMIF(B:B,B33,G:G)) -> 1251 | L33: =IF(B33="","",IFERROR(VLOOKUP(B33,'Coil Sheet at Plant'!$C:$I,7,FALSE),"")) -> 1250 | M33: =IF(OR(K33="",L33=""),"",IF(L33=0,"⚠ NO PARENT WIDTH",IF(K33>L33,"⚠ BABY > PARENT","✔ OK"))) -> ⚠ BABY > PARENT | N33: =IF(D33="","",IF(COUNTIF(D$3:D33,D33)>1,"⚠ DUPLICATE","")) | O33: =IF(B33="","",SUMIF(B:B,B33,G:G)&" / "&IFERROR(VLOOKUP(B33,'Coil Sheet at Plant'!$C:$I,7,FALSE),"?")&" mm") -> 1251 / 1250 mm
A34: 29-03-2026 | B34: HYD-0326-04 | C34: F | D34: =IF(OR(B34="",C34=""),"",CONCATENATE(B34,"-",C34)) -> HYD-0326-04-F | E34: =IF(B34="","",IFERROR(VLOOKUP(B34,'Coil Sheet at Plant'!$C:$G,5,FALSE),"ID Not Found")) -> 2.2 | F34: =IF(B34="","",IFERROR(VLOOKUP(B34,'Coil Sheet at Plant'!$C:$H,6,FALSE),"ID Not Found")) -> 0 | G34: 197 | H34: =IF(OR(B34="",G34=""),"",IFERROR(VLOOKUP(B34,'Coil Sheet at Plant'!$C:$J,8,FALSE),0)*G34/SUMIF(B:B,B34,G:G)) -> 4.4817106 | I34: =IF(B34="","",IFERROR(VLOOKUP(B34,'Coil Sheet at Plant'!$C:$L,9,FALSE),"")) -> 0 | J34: =IF(B34="","",IFERROR(VLOOKUP(B34,'Coil Sheet at Plant'!$C:$M,10,FALSE),"")) -> 0 | K34: =IF(B34="","",SUMIF(B:B,B34,G:G)) -> 1251 | L34: =IF(B34="","",IFERROR(VLOOKUP(B34,'Coil Sheet at Plant'!$C:$I,7,FALSE),"")) -> 1250 | M34: =IF(OR(K34="",L34=""),"",IF(L34=0,"⚠ NO PARENT WIDTH",IF(K34>L34,"⚠ BABY > PARENT","✔ OK"))) -> ⚠ BABY > PARENT | N34: =IF(D34="","",IF(COUNTIF(D$3:D34,D34)>1,"⚠ DUPLICATE","")) | O34: =IF(B34="","",SUMIF(B:B,B34,G:G)&" / "&IFERROR(VLOOKUP(B34,'Coil Sheet at Plant'!$C:$I,7,FALSE),"?")&" mm") -> 1251 / 1250 mm
A35: 29-03-2026 | B35: HYD-0326-04 | C35: G | D35: =IF(OR(B35="",C35=""),"",CONCATENATE(B35,"-",C35)) -> HYD-0326-04-G | E35: =IF(B35="","",IFERROR(VLOOKUP(B35,'Coil Sheet at Plant'!$C:$G,5,FALSE),"ID Not Found")) -> 2.2 | F35: =IF(B35="","",IFERROR(VLOOKUP(B35,'Coil Sheet at Plant'!$C:$H,6,FALSE),"ID Not Found")) -> 0 | G35: 197 | H35: =IF(OR(B35="",G35=""),"",IFERROR(VLOOKUP(B35,'Coil Sheet at Plant'!$C:$J,8,FALSE),0)*G35/SUMIF(B:B,B35,G:G)) -> 4.4817106 | I35: =IF(B35="","",IFERROR(VLOOKUP(B35,'Coil Sheet at Plant'!$C:$L,9,FALSE),"")) -> 0 | J35: =IF(B35="","",IFERROR(VLOOKUP(B35,'Coil Sheet at Plant'!$C:$M,10,FALSE),"")) -> 0 | K35: =IF(B35="","",SUMIF(B:B,B35,G:G)) -> 1251 | L35: =IF(B35="","",IFERROR(VLOOKUP(B35,'Coil Sheet at Plant'!$C:$I,7,FALSE),"")) -> 1250 | M35: =IF(OR(K35="",L35=""),"",IF(L35=0,"⚠ NO PARENT WIDTH",IF(K35>L35,"⚠ BABY > PARENT","✔ OK"))) -> ⚠ BABY > PARENT | N35: =IF(D35="","",IF(COUNTIF(D$3:D35,D35)>1,"⚠ DUPLICATE","")) | O35: =IF(B35="","",SUMIF(B:B,B35,G:G)&" / "&IFERROR(VLOOKUP(B35,'Coil Sheet at Plant'!$C:$I,7,FALSE),"?")&" mm") -> 1251 / 1250 mm
A36: 29-03-2026 | B36: HYD-0326-04 | C36: H | D36: =IF(OR(B36="",C36=""),"",CONCATENATE(B36,"-",C36)) -> HYD-0326-04-H | E36: =IF(B36="","",IFERROR(VLOOKUP(B36,'Coil Sheet at Plant'!$C:$G,5,FALSE),"ID Not Found")) -> 2.2 | F36: =IF(B36="","",IFERROR(VLOOKUP(B36,'Coil Sheet at Plant'!$C:$H,6,FALSE),"ID Not Found")) -> 0 | G36: 117 | H36: =IF(OR(B36="",G36=""),"",IFERROR(VLOOKUP(B36,'Coil Sheet at Plant'!$C:$J,8,FALSE),0)*G36/SUMIF(B:B,B36,G:G)) -> 2.6617266 | I36: =IF(B36="","",IFERROR(VLOOKUP(B36,'Coil Sheet at Plant'!$C:$L,9,FALSE),"")) -> 0 | J36: =IF(B36="","",IFERROR(VLOOKUP(B36,'Coil Sheet at Plant'!$C:$M,10,FALSE),"")) -> 0 | K36: =IF(B36="","",SUMIF(B:B,B36,G:G)) -> 1251 | L36: =IF(B36="","",IFERROR(VLOOKUP(B36,'Coil Sheet at Plant'!$C:$I,7,FALSE),"")) -> 1250 | M36: =IF(OR(K36="",L36=""),"",IF(L36=0,"⚠ NO PARENT WIDTH",IF(K36>L36,"⚠ BABY > PARENT","✔ OK"))) -> ⚠ BABY > PARENT | N36: =IF(D36="","",IF(COUNTIF(D$3:D36,D36)>1,"⚠ DUPLICATE","")) | O36: =IF(B36="","",SUMIF(B:B,B36,G:G)&" / "&IFERROR(VLOOKUP(B36,'Coil Sheet at Plant'!$C:$I,7,FALSE),"?")&" mm") -> 1251 / 1250 mm
A37: 46116 | B37: HYD-0426-05 | C37: A | D37: =IF(OR(B37="",C37=""),"",CONCATENATE(B37,"-",C37)) -> HYD-0426-05-A | E37: =IF(B37="","",IFERROR(VLOOKUP(B37,'Coil Sheet at Plant'!$C:$G,5,FALSE),"ID Not Found")) -> 2 | F37: =IF(B37="","",IFERROR(VLOOKUP(B37,'Coil Sheet at Plant'!$C:$H,6,FALSE),"ID Not Found")) | G37: 197 | H37: =IF(OR(B37="",G37=""),"",IFERROR(VLOOKUP(B37,'Coil Sheet at Plant'!$C:$J,8,FALSE),0)*G37/SUMIF(B:B,B37,G:G)) -> 3.1005203 | I37: =IF(B37="","",IFERROR(VLOOKUP(B37,'Coil Sheet at Plant'!$C:$L,9,FALSE),"")) -> 19.815 | J37: =IF(B37="","",IFERROR(VLOOKUP(B37,'Coil Sheet at Plant'!$C:$M,10,FALSE),"")) -> 11,65,122.0 | K37: =IF(B37="","",SUMIF(B:B,B37,G:G)) -> 1259 | L37: =IF(B37="","",IFERROR(VLOOKUP(B37,'Coil Sheet at Plant'!$C:$I,7,FALSE),"")) -> 1260 | M37: =IF(OR(K37="",L37=""),"",IF(L37=0,"⚠ NO PARENT WIDTH",IF(K37>L37,"⚠ BABY > PARENT","✔ OK"))) -> ✔ OK | N37: =IF(D37="","",IF(COUNTIF(D$3:D37,D37)>1,"⚠ DUPLICATE","")) | O37: =IF(B37="","",SUMIF(B:B,B37,G:G)&" / "&IFERROR(VLOOKUP(B37,'Coil Sheet at Plant'!$C:$I,7,FALSE),"?")&" mm") -> 1259 / 1260 mm
A38: 46116 | B38: HYD-0426-05 | C38: B | D38: =IF(OR(B38="",C38=""),"",CONCATENATE(B38,"-",C38)) -> HYD-0426-05-B | E38: =IF(B38="","",IFERROR(VLOOKUP(B38,'Coil Sheet at Plant'!$C:$G,5,FALSE),"ID Not Found")) -> 2 | F38: =IF(B38="","",IFERROR(VLOOKUP(B38,'Coil Sheet at Plant'!$C:$H,6,FALSE),"ID Not Found")) | G38: 197 | H38: =IF(OR(B38="",G38=""),"",IFERROR(VLOOKUP(B38,'Coil Sheet at Plant'!$C:$J,8,FALSE),0)*G38/SUMIF(B:B,B38,G:G)) -> 3.1005203 | I38: =IF(B38="","",IFERROR(VLOOKUP(B38,'Coil Sheet at Plant'!$C:$L,9,FALSE),"")) -> 19.815 | J38: =IF(B38="","",IFERROR(VLOOKUP(B38,'Coil Sheet at Plant'!$C:$M,10,FALSE),"")) -> 11,65,122.0 | K38: =IF(B38="","",SUMIF(B:B,B38,G:G)) -> 1259 | L38: =IF(B38="","",IFERROR(VLOOKUP(B38,'Coil Sheet at Plant'!$C:$I,7,FALSE),"")) -> 1260 | M38: =IF(OR(K38="",L38=""),"",IF(L38=0,"⚠ NO PARENT WIDTH",IF(K38>L38,"⚠ BABY > PARENT","✔ OK"))) -> ✔ OK | N38: =IF(D38="","",IF(COUNTIF(D$3:D38,D38)>1,"⚠ DUPLICATE","")) | O38: =IF(B38="","",SUMIF(B:B,B38,G:G)&" / "&IFERROR(VLOOKUP(B38,'Coil Sheet at Plant'!$C:$I,7,FALSE),"?")&" mm") -> 1259 / 1260 mm
A39: 46116 | B39: HYD-0426-05 | C39: C | D39: =IF(OR(B39="",C39=""),"",CONCATENATE(B39,"-",C39)) -> HYD-0426-05-C | E39: =IF(B39="","",IFERROR(VLOOKUP(B39,'Coil Sheet at Plant'!$C:$G,5,FALSE),"ID Not Found")) -> 2 | F39: =IF(B39="","",IFERROR(VLOOKUP(B39,'Coil Sheet at Plant'!$C:$H,6,FALSE),"ID Not Found")) | G39: 197 | H39: =IF(OR(B39="",G39=""),"",IFERROR(VLOOKUP(B39,'Coil Sheet at Plant'!$C:$J,8,FALSE),0)*G39/SUMIF(B:B,B39,G:G)) -> 3.1005203 | I39: =IF(B39="","",IFERROR(VLOOKUP(B39,'Coil Sheet at Plant'!$C:$L,9,FALSE),"")) -> 19.815 | J39: =IF(B39="","",IFERROR(VLOOKUP(B39,'Coil Sheet at Plant'!$C:$M,10,FALSE),"")) -> 11,65,122.0 | K39: =IF(B39="","",SUMIF(B:B,B39,G:G)) -> 1259 | L39: =IF(B39="","",IFERROR(VLOOKUP(B39,'Coil Sheet at Plant'!$C:$I,7,FALSE),"")) -> 1260 | M39: =IF(OR(K39="",L39=""),"",IF(L39=0,"⚠ NO PARENT WIDTH",IF(K39>L39,"⚠ BABY > PARENT","✔ OK"))) -> ✔ OK | N39: =IF(D39="","",IF(COUNTIF(D$3:D39,D39)>1,"⚠ DUPLICATE","")) | O39: =IF(B39="","",SUMIF(B:B,B39,G:G)&" / "&IFERROR(VLOOKUP(B39,'Coil Sheet at Plant'!$C:$I,7,FALSE),"?")&" mm") -> 1259 / 1260 mm
A40: 46116 | B40: HYD-0426-05 | C40: D | D40: =IF(OR(B40="",C40=""),"",CONCATENATE(B40,"-",C40)) -> HYD-0426-05-D | E40: =IF(B40="","",IFERROR(VLOOKUP(B40,'Coil Sheet at Plant'!$C:$G,5,FALSE),"ID Not Found")) -> 2 | F40: =IF(B40="","",IFERROR(VLOOKUP(B40,'Coil Sheet at Plant'!$C:$H,6,FALSE),"ID Not Found")) | G40: 197 | H40: =IF(OR(B40="",G40=""),"",IFERROR(VLOOKUP(B40,'Coil Sheet at Plant'!$C:$J,8,FALSE),0)*G40/SUMIF(B:B,B40,G:G)) -> 3.1005203 | I40: =IF(B40="","",IFERROR(VLOOKUP(B40,'Coil Sheet at Plant'!$C:$L,9,FALSE),"")) -> 19.815 | J40: =IF(B40="","",IFERROR(VLOOKUP(B40,'Coil Sheet at Plant'!$C:$M,10,FALSE),"")) -> 11,65,122.0 | K40: =IF(B40="","",SUMIF(B:B,B40,G:G)) -> 1259 | L40: =IF(B40="","",IFERROR(VLOOKUP(B40,'Coil Sheet at Plant'!$C:$I,7,FALSE),"")) -> 1260 | M40: =IF(OR(K40="",L40=""),"",IF(L40=0,"⚠ NO PARENT WIDTH",IF(K40>L40,"⚠ BABY > PARENT","✔ OK"))) -> ✔ OK | N40: =IF(D40="","",IF(COUNTIF(D$3:D40,D40)>1,"⚠ DUPLICATE","")) | O40: =IF(B40="","",SUMIF(B:B,B40,G:G)&" / "&IFERROR(VLOOKUP(B40,'Coil Sheet at Plant'!$C:$I,7,FALSE),"?")&" mm") -> 1259 / 1260 mm
A41: 46116 | B41: HYD-0426-05 | C41: E | D41: =IF(OR(B41="",C41=""),"",CONCATENATE(B41,"-",C41)) -> HYD-0426-05-E | E41: =IF(B41="","",IFERROR(VLOOKUP(B41,'Coil Sheet at Plant'!$C:$G,5,FALSE),"ID Not Found")) -> 2 | F41: =IF(B41="","",IFERROR(VLOOKUP(B41,'Coil Sheet at Plant'!$C:$H,6,FALSE),"ID Not Found")) | G41: 197 | H41: =IF(OR(B41="",G41=""),"",IFERROR(VLOOKUP(B41,'Coil Sheet at Plant'!$C:$J,8,FALSE),0)*G41/SUMIF(B:B,B41,G:G)) -> 3.1005203 | I41: =IF(B41="","",IFERROR(VLOOKUP(B41,'Coil Sheet at Plant'!$C:$L,9,FALSE),"")) -> 19.815 | J41: =IF(B41="","",IFERROR(VLOOKUP(B41,'Coil Sheet at Plant'!$C:$M,10,FALSE),"")) -> 11,65,122.0 | K41: =IF(B41="","",SUMIF(B:B,B41,G:G)) -> 1259 | L41: =IF(B41="","",IFERROR(VLOOKUP(B41,'Coil Sheet at Plant'!$C:$I,7,FALSE),"")) -> 1260 | M41: =IF(OR(K41="",L41=""),"",IF(L41=0,"⚠ NO PARENT WIDTH",IF(K41>L41,"⚠ BABY > PARENT","✔ OK"))) -> ✔ OK | N41: =IF(D41="","",IF(COUNTIF(D$3:D41,D41)>1,"⚠ DUPLICATE","")) | O41: =IF(B41="","",SUMIF(B:B,B41,G:G)&" / "&IFERROR(VLOOKUP(B41,'Coil Sheet at Plant'!$C:$I,7,FALSE),"?")&" mm") -> 1259 / 1260 mm
A42: 46116 | B42: HYD-0426-05 | C42: F | D42: =IF(OR(B42="",C42=""),"",CONCATENATE(B42,"-",C42)) -> HYD-0426-05-F | E42: =IF(B42="","",IFERROR(VLOOKUP(B42,'Coil Sheet at Plant'!$C:$G,5,FALSE),"ID Not Found")) -> 2 | F42: =IF(B42="","",IFERROR(VLOOKUP(B42,'Coil Sheet at Plant'!$C:$H,6,FALSE),"ID Not Found")) | G42: 197 | H42: =IF(OR(B42="",G42=""),"",IFERROR(VLOOKUP(B42,'Coil Sheet at Plant'!$C:$J,8,FALSE),0)*G42/SUMIF(B:B,B42,G:G)) -> 3.1005203 | I42: =IF(B42="","",IFERROR(VLOOKUP(B42,'Coil Sheet at Plant'!$C:$L,9,FALSE),"")) -> 19.815 | J42: =IF(B42="","",IFERROR(VLOOKUP(B42,'Coil Sheet at Plant'!$C:$M,10,FALSE),"")) -> 11,65,122.0 | K42: =IF(B42="","",SUMIF(B:B,B42,G:G)) -> 1259 | L42: =IF(B42="","",IFERROR(VLOOKUP(B42,'Coil Sheet at Plant'!$C:$I,7,FALSE),"")) -> 1260 | M42: =IF(OR(K42="",L42=""),"",IF(L42=0,"⚠ NO PARENT WIDTH",IF(K42>L42,"⚠ BABY > PARENT","✔ OK"))) -> ✔ OK | N42: =IF(D42="","",IF(COUNTIF(D$3:D42,D42)>1,"⚠ DUPLICATE","")) | O42: =IF(B42="","",SUMIF(B:B,B42,G:G)&" / "&IFERROR(VLOOKUP(B42,'Coil Sheet at Plant'!$C:$I,7,FALSE),"?")&" mm") -> 1259 / 1260 mm
A43: 46116 | B43: HYD-0426-05 | C43: G | D43: =IF(OR(B43="",C43=""),"",CONCATENATE(B43,"-",C43)) -> HYD-0426-05-G | E43: =IF(B43="","",IFERROR(VLOOKUP(B43,'Coil Sheet at Plant'!$C:$G,5,FALSE),"ID Not Found")) -> 2 | F43: =IF(B43="","",IFERROR(VLOOKUP(B43,'Coil Sheet at Plant'!$C:$H,6,FALSE),"ID Not Found")) | G43: 77 | H43: =IF(OR(B43="",G43=""),"",IFERROR(VLOOKUP(B43,'Coil Sheet at Plant'!$C:$J,8,FALSE),0)*G43/SUMIF(B:B,B43,G:G)) -> 1.2118785 | I43: =IF(B43="","",IFERROR(VLOOKUP(B43,'Coil Sheet at Plant'!$C:$L,9,FALSE),"")) -> 19.815 | J43: =IF(B43="","",IFERROR(VLOOKUP(B43,'Coil Sheet at Plant'!$C:$M,10,FALSE),"")) -> 11,65,122.0 | K43: =IF(B43="","",SUMIF(B:B,B43,G:G)) -> 1259 | L43: =IF(B43="","",IFERROR(VLOOKUP(B43,'Coil Sheet at Plant'!$C:$I,7,FALSE),"")) -> 1260 | M43: =IF(OR(K43="",L43=""),"",IF(L43=0,"⚠ NO PARENT WIDTH",IF(K43>L43,"⚠ BABY > PARENT","✔ OK"))) -> ✔ OK | N43: =IF(D43="","",IF(COUNTIF(D$3:D43,D43)>1,"⚠ DUPLICATE","")) | O43: =IF(B43="","",SUMIF(B:B,B43,G:G)&" / "&IFERROR(VLOOKUP(B43,'Coil Sheet at Plant'!$C:$I,7,FALSE),"?")&" mm") -> 1259 / 1260 mm
A44: 46116 | B44: HYD-0426-06 | C44: A | D44: =IF(OR(B44="",C44=""),"",CONCATENATE(B44,"-",C44)) -> HYD-0426-06-A | E44: =IF(B44="","",IFERROR(VLOOKUP(B44,'Coil Sheet at Plant'!$C:$G,5,FALSE),"ID Not Found")) -> 2 | F44: =IF(B44="","",IFERROR(VLOOKUP(B44,'Coil Sheet at Plant'!$C:$H,6,FALSE),"ID Not Found")) | G44: 197 | H44: =IF(OR(B44="",G44=""),"",IFERROR(VLOOKUP(B44,'Coil Sheet at Plant'!$C:$J,8,FALSE),0)*G44/SUMIF(B:B,B44,G:G)) -> 3.4627562 | I44: =IF(B44="","",IFERROR(VLOOKUP(B44,'Coil Sheet at Plant'!$C:$L,9,FALSE),"")) -> 22.13 | J44: =IF(B44="","",IFERROR(VLOOKUP(B44,'Coil Sheet at Plant'!$C:$M,10,FALSE),"")) -> 13,01,244.0 | K44: =IF(B44="","",SUMIF(B:B,B44,G:G)) -> 1259 | L44: =IF(B44="","",IFERROR(VLOOKUP(B44,'Coil Sheet at Plant'!$C:$I,7,FALSE),"")) -> 1264 | M44: =IF(OR(K44="",L44=""),"",IF(L44=0,"⚠ NO PARENT WIDTH",IF(K44>L44,"⚠ BABY > PARENT","✔ OK"))) -> ✔ OK | N44: =IF(D44="","",IF(COUNTIF(D$3:D44,D44)>1,"⚠ DUPLICATE","")) | O44: =IF(B44="","",SUMIF(B:B,B44,G:G)&" / "&IFERROR(VLOOKUP(B44,'Coil Sheet at Plant'!$C:$I,7,FALSE),"?")&" mm") -> 1259 / 1264 mm
A45: 46116 | B45: HYD-0426-06 | C45: B | D45: =IF(OR(B45="",C45=""),"",CONCATENATE(B45,"-",C45)) -> HYD-0426-06-B | E45: =IF(B45="","",IFERROR(VLOOKUP(B45,'Coil Sheet at Plant'!$C:$G,5,FALSE),"ID Not Found")) -> 2 | F45: =IF(B45="","",IFERROR(VLOOKUP(B45,'Coil Sheet at Plant'!$C:$H,6,FALSE),"ID Not Found")) | G45: 197 | H45: =IF(OR(B45="",G45=""),"",IFERROR(VLOOKUP(B45,'Coil Sheet at Plant'!$C:$J,8,FALSE),0)*G45/SUMIF(B:B,B45,G:G)) -> 3.4627562 | I45: =IF(B45="","",IFERROR(VLOOKUP(B45,'Coil Sheet at Plant'!$C:$L,9,FALSE),"")) -> 22.13 | J45: =IF(B45="","",IFERROR(VLOOKUP(B45,'Coil Sheet at Plant'!$C:$M,10,FALSE),"")) -> 13,01,244.0 | K45: =IF(B45="","",SUMIF(B:B,B45,G:G)) -> 1259 | L45: =IF(B45="","",IFERROR(VLOOKUP(B45,'Coil Sheet at Plant'!$C:$I,7,FALSE),"")) -> 1264 | M45: =IF(OR(K45="",L45=""),"",IF(L45=0,"⚠ NO PARENT WIDTH",IF(K45>L45,"⚠ BABY > PARENT","✔ OK"))) -> ✔ OK | N45: =IF(D45="","",IF(COUNTIF(D$3:D45,D45)>1,"⚠ DUPLICATE","")) | O45: =IF(B45="","",SUMIF(B:B,B45,G:G)&" / "&IFERROR(VLOOKUP(B45,'Coil Sheet at Plant'!$C:$I,7,FALSE),"?")&" mm") -> 1259 / 1264 mm
A46: 46116 | B46: HYD-0426-06 | C46: C | D46: =IF(OR(B46="",C46=""),"",CONCATENATE(B46,"-",C46)) -> HYD-0426-06-C | E46: =IF(B46="","",IFERROR(VLOOKUP(B46,'Coil Sheet at Plant'!$C:$G,5,FALSE),"ID Not Found")) -> 2 | F46: =IF(B46="","",IFERROR(VLOOKUP(B46,'Coil Sheet at Plant'!$C:$H,6,FALSE),"ID Not Found")) | G46: 197 | H46: =IF(OR(B46="",G46=""),"",IFERROR(VLOOKUP(B46,'Coil Sheet at Plant'!$C:$J,8,FALSE),0)*G46/SUMIF(B:B,B46,G:G)) -> 3.4627562 | I46: =IF(B46="","",IFERROR(VLOOKUP(B46,'Coil Sheet at Plant'!$C:$L,9,FALSE),"")) -> 22.13 | J46: =IF(B46="","",IFERROR(VLOOKUP(B46,'Coil Sheet at Plant'!$C:$M,10,FALSE),"")) -> 13,01,244.0 | K46: =IF(B46="","",SUMIF(B:B,B46,G:G)) -> 1259 | L46: =IF(B46="","",IFERROR(VLOOKUP(B46,'Coil Sheet at Plant'!$C:$I,7,FALSE),"")) -> 1264 | M46: =IF(OR(K46="",L46=""),"",IF(L46=0,"⚠ NO PARENT WIDTH",IF(K46>L46,"⚠ BABY > PARENT","✔ OK"))) -> ✔ OK | N46: =IF(D46="","",IF(COUNTIF(D$3:D46,D46)>1,"⚠ DUPLICATE","")) | O46: =IF(B46="","",SUMIF(B:B,B46,G:G)&" / "&IFERROR(VLOOKUP(B46,'Coil Sheet at Plant'!$C:$I,7,FALSE),"?")&" mm") -> 1259 / 1264 mm
A47: 46116 | B47: HYD-0426-06 | C47: D | D47: =IF(OR(B47="",C47=""),"",CONCATENATE(B47,"-",C47)) -> HYD-0426-06-D | E47: =IF(B47="","",IFERROR(VLOOKUP(B47,'Coil Sheet at Plant'!$C:$G,5,FALSE),"ID Not Found")) -> 2 | F47: =IF(B47="","",IFERROR(VLOOKUP(B47,'Coil Sheet at Plant'!$C:$H,6,FALSE),"ID Not Found")) | G47: 197 | H47: =IF(OR(B47="",G47=""),"",IFERROR(VLOOKUP(B47,'Coil Sheet at Plant'!$C:$J,8,FALSE),0)*G47/SUMIF(B:B,B47,G:G)) -> 3.4627562 | I47: =IF(B47="","",IFERROR(VLOOKUP(B47,'Coil Sheet at Plant'!$C:$L,9,FALSE),"")) -> 22.13 | J47: =IF(B47="","",IFERROR(VLOOKUP(B47,'Coil Sheet at Plant'!$C:$M,10,FALSE),"")) -> 13,01,244.0 | K47: =IF(B47="","",SUMIF(B:B,B47,G:G)) -> 1259 | L47: =IF(B47="","",IFERROR(VLOOKUP(B47,'Coil Sheet at Plant'!$C:$I,7,FALSE),"")) -> 1264 | M47: =IF(OR(K47="",L47=""),"",IF(L47=0,"⚠ NO PARENT WIDTH",IF(K47>L47,"⚠ BABY > PARENT","✔ OK"))) -> ✔ OK | N47: =IF(D47="","",IF(COUNTIF(D$3:D47,D47)>1,"⚠ DUPLICATE","")) | O47: =IF(B47="","",SUMIF(B:B,B47,G:G)&" / "&IFERROR(VLOOKUP(B47,'Coil Sheet at Plant'!$C:$I,7,FALSE),"?")&" mm") -> 1259 / 1264 mm
A48: 46116 | B48: HYD-0426-06 | C48: E | D48: =IF(OR(B48="",C48=""),"",CONCATENATE(B48,"-",C48)) -> HYD-0426-06-E | E48: =IF(B48="","",IFERROR(VLOOKUP(B48,'Coil Sheet at Plant'!$C:$G,5,FALSE),"ID Not Found")) -> 2 | F48: =IF(B48="","",IFERROR(VLOOKUP(B48,'Coil Sheet at Plant'!$C:$H,6,FALSE),"ID Not Found")) | G48: 197 | H48: =IF(OR(B48="",G48=""),"",IFERROR(VLOOKUP(B48,'Coil Sheet at Plant'!$C:$J,8,FALSE),0)*G48/SUMIF(B:B,B48,G:G)) -> 3.4627562 | I48: =IF(B48="","",IFERROR(VLOOKUP(B48,'Coil Sheet at Plant'!$C:$L,9,FALSE),"")) -> 22.13 | J48: =IF(B48="","",IFERROR(VLOOKUP(B48,'Coil Sheet at Plant'!$C:$M,10,FALSE),"")) -> 13,01,244.0 | K48: =IF(B48="","",SUMIF(B:B,B48,G:G)) -> 1259 | L48: =IF(B48="","",IFERROR(VLOOKUP(B48,'Coil Sheet at Plant'!$C:$I,7,FALSE),"")) -> 1264 | M48: =IF(OR(K48="",L48=""),"",IF(L48=0,"⚠ NO PARENT WIDTH",IF(K48>L48,"⚠ BABY > PARENT","✔ OK"))) -> ✔ OK | N48: =IF(D48="","",IF(COUNTIF(D$3:D48,D48)>1,"⚠ DUPLICATE","")) | O48: =IF(B48="","",SUMIF(B:B,B48,G:G)&" / "&IFERROR(VLOOKUP(B48,'Coil Sheet at Plant'!$C:$I,7,FALSE),"?")&" mm") -> 1259 / 1264 mm
... A56: 46118 | B56: HYD-0426-07 | C56: F | D56: =IF(OR(B56="",C56=""),"",CONCATENATE(B56,"-",C56)) -> HYD-0426-07-F | E56: =IF(B56="","",IFERROR(VLOOKUP(B56,'Coil Sheet at Plant'!$C:$G,5,FALSE),"ID Not Found")) -> 2 | F56: =IF(B56="","",IFERROR(VLOOKUP(B56,'Coil Sheet at Plant'!$C:$H,6,FALSE),"ID Not Found")) | G56: 97 | H56: =IF(OR(B56="",G56=""),"",IFERROR(VLOOKUP(B56,'Coil Sheet at Plant'!$C:$J,8,FALSE),0)*G56/SUMIF(B:B,B56,G:G)) -> 1.4813015 | I56: =IF(B56="","",IFERROR(VLOOKUP(B56,'Coil Sheet at Plant'!$C:$L,9,FALSE),"")) -> 14.08 | J56: =IF(B56="","",IFERROR(VLOOKUP(B56,'Coil Sheet at Plant'!$C:$M,10,FALSE),"")) -> 8,37,760.00 | K56: =IF(B56="","",SUMIF(B:B,B56,G:G)) -> 922 | L56: =IF(B56="","",IFERROR(VLOOKUP(B56,'Coil Sheet at Plant'!$C:$I,7,FALSE),"")) -> 930 | M56: =IF(OR(K56="",L56=""),"",IF(L56=0,"⚠ NO PARENT WIDTH",IF(K56>L56,"⚠ BABY > PARENT","✔ OK"))) -> ✔ OK | N56: =IF(D56="","",IF(COUNTIF(D$3:D56,D56)>1,"⚠ DUPLICATE","")) | O56: =IF(B56="","",SUMIF(B:B,B56,G:G)&" / "&IFERROR(VLOOKUP(B56,'Coil Sheet at Plant'!$C:$I,7,FALSE),"?")&" mm") -> 922 / 930 mm
D57: =IF(OR(B57="",C57=""),"",CONCATENATE(B57,"-",C57)) | E57: =IF(B57="","",IFERROR(VLOOKUP(B57,'Coil Sheet at Plant'!$C:$G,5,FALSE),"ID Not Found")) | F57: =IF(B57="","",IFERROR(VLOOKUP(B57,'Coil Sheet at Plant'!$C:$H,6,FALSE),"ID Not Found")) | H57: =IF(OR(B57="",G57=""),"",IFERROR(VLOOKUP(B57,'Coil Sheet at Plant'!$C:$J,8,FALSE),0)*G57/SUMIF(B:B,B57,G:G)) | I57: =IF(B57="","",IFERROR(VLOOKUP(B57,'Coil Sheet at Plant'!$C:$L,9,FALSE),"")) | J57: =IF(B57="","",IFERROR(VLOOKUP(B57,'Coil Sheet at Plant'!$C:$M,10,FALSE),"")) | K57: =IF(B57="","",SUMIF(B:B,B57,G:G)) | L57: =IF(B57="","",IFERROR(VLOOKUP(B57,'Coil Sheet at Plant'!$C:$I,7,FALSE),"")) | M57: =IF(OR(K57="",L57=""),"",IF(L57=0,"⚠ NO PARENT WIDTH",IF(K57>L57,"⚠ BABY > PARENT","✔ OK"))) | N57: =IF(D57="","",IF(COUNTIF(D$3:D57,D57)>1,"⚠ DUPLICATE","")) | O57: =IF(B57="","",SUMIF(B:B,B57,G:G)&" / "&IFERROR(VLOOKUP(B57,'Coil Sheet at Plant'!$C:$I,7,FALSE),"?")&" mm")
D58: =IF(OR(B58="",C58=""),"",CONCATENATE(B58,"-",C58)) | E58: =IF(B58="","",IFERROR(VLOOKUP(B58,'Coil Sheet at Plant'!$C:$G,5,FALSE),"ID Not Found")) | F58: =IF(B58="","",IFERROR(VLOOKUP(B58,'Coil Sheet at Plant'!$C:$H,6,FALSE),"ID Not Found")) | H58: =IF(OR(B58="",G58=""),"",IFERROR(VLOOKUP(B58,'Coil Sheet at Plant'!$C:$J,8,FALSE),0)*G58/SUMIF(B:B,B58,G:G)) | I58: =IF(B58="","",IFERROR(VLOOKUP(B58,'Coil Sheet at Plant'!$C:$L,9,FALSE),"")) | J58: =IF(B58="","",IFERROR(VLOOKUP(B58,'Coil Sheet at Plant'!$C:$M,10,FALSE),"")) | K58: =IF(B58="","",SUMIF(B:B,B58,G:G)) | L58: =IF(B58="","",IFERROR(VLOOKUP(B58,'Coil Sheet at Plant'!$C:$I,7,FALSE),"")) | M58: =IF(OR(K58="",L58=""),"",IF(L58=0,"⚠ NO PARENT WIDTH",IF(K58>L58,"⚠ BABY > PARENT","✔ OK"))) | N58: =IF(D58="","",IF(COUNTIF(D$3:D58,D58)>1,"⚠ DUPLICATE","")) | O58: =IF(B58="","",SUMIF(B:B,B58,G:G)&" / "&IFERROR(VLOOKUP(B58,'Coil Sheet at Plant'!$C:$I,7,FALSE),"?")&" mm")
D59: =IF(OR(B59="",C59=""),"",CONCATENATE(B59,"-",C59)) | E59: =IF(B59="","",IFERROR(VLOOKUP(B59,'Coil Sheet at Plant'!$C:$G,5,FALSE),"ID Not Found")) | F59: =IF(B59="","",IFERROR(VLOOKUP(B59,'Coil Sheet at Plant'!$C:$H,6,FALSE),"ID Not Found")) | H59: =IF(OR(B59="",G59=""),"",IFERROR(VLOOKUP(B59,'Coil Sheet at Plant'!$C:$J,8,FALSE),0)*G59/SUMIF(B:B,B59,G:G)) | I59: =IF(B59="","",IFERROR(VLOOKUP(B59,'Coil Sheet at Plant'!$C:$L,9,FALSE),"")) | J59: =IF(B59="","",IFERROR(VLOOKUP(B59,'Coil Sheet at Plant'!$C:$M,10,FALSE),"")) | K59: =IF(B59="","",SUMIF(B:B,B59,G:G)) | L59: =IF(B59="","",IFERROR(VLOOKUP(B59,'Coil Sheet at Plant'!$C:$I,7,FALSE),"")) | M59: =IF(OR(K59="",L59=""),"",IF(L59=0,"⚠ NO PARENT WIDTH",IF(K59>L59,"⚠ BABY > PARENT","✔ OK"))) | N59: =IF(D59="","",IF(COUNTIF(D$3:D59,D59)>1,"⚠ DUPLICATE","")) | O59: =IF(B59="","",SUMIF(B:B,B59,G:G)&" / "&IFERROR(VLOOKUP(B59,'Coil Sheet at Plant'!$C:$I,7,FALSE),"?")&" mm")
D60: =IF(OR(B60="",C60=""),"",CONCATENATE(B60,"-",C60)) | E60: =IF(B60="","",IFERROR(VLOOKUP(B60,'Coil Sheet at Plant'!$C:$G,5,FALSE),"ID Not Found")) | F60: =IF(B60="","",IFERROR(VLOOKUP(B60,'Coil Sheet at Plant'!$C:$H,6,FALSE),"ID Not Found")) | H60: =IF(OR(B60="",G60=""),"",IFERROR(VLOOKUP(B60,'Coil Sheet at Plant'!$C:$J,8,FALSE),0)*G60/SUMIF(B:B,B60,G:G)) | I60: =IF(B60="","",IFERROR(VLOOKUP(B60,'Coil Sheet at Plant'!$C:$L,9,FALSE),"")) | J60: =IF(B60="","",IFERROR(VLOOKUP(B60,'Coil Sheet at Plant'!$C:$M,10,FALSE),"")) | K60: =IF(B60="","",SUMIF(B:B,B60,G:G)) | L60: =IF(B60="","",IFERROR(VLOOKUP(B60,'Coil Sheet at Plant'!$C:$I,7,FALSE),"")) | M60: =IF(OR(K60="",L60=""),"",IF(L60=0,"⚠ NO PARENT WIDTH",IF(K60>L60,"⚠ BABY > PARENT","✔ OK"))) | N60: =IF(D60="","",IF(COUNTIF(D$3:D60,D60)>1,"⚠ DUPLICATE","")) | O60: =IF(B60="","",SUMIF(B:B,B60,G:G)&" / "&IFERROR(VLOOKUP(B60,'Coil Sheet at Plant'!$C:$I,7,FALSE),"?")&" mm")
D61: =IF(OR(B61="",C61=""),"",CONCATENATE(B61,"-",C61)) | E61: =IF(B61="","",IFERROR(VLOOKUP(B61,'Coil Sheet at Plant'!$C:$G,5,FALSE),"ID Not Found")) | F61: =IF(B61="","",IFERROR(VLOOKUP(B61,'Coil Sheet at Plant'!$C:$H,6,FALSE),"ID Not Found")) | H61: =IF(OR(B61="",G61=""),"",IFERROR(VLOOKUP(B61,'Coil Sheet at Plant'!$C:$J,8,FALSE),0)*G61/SUMIF(B:B,B61,G:G)) | I61: =IF(B61="","",IFERROR(VLOOKUP(B61,'Coil Sheet at Plant'!$C:$L,9,FALSE),"")) | J61: =IF(B61="","",IFERROR(VLOOKUP(B61,'Coil Sheet at Plant'!$C:$M,10,FALSE),"")) | K61: =IF(B61="","",SUMIF(B:B,B61,G:G)) | L61: =IF(B61="","",IFERROR(VLOOKUP(B61,'Coil Sheet at Plant'!$C:$I,7,FALSE),"")) | M61: =IF(OR(K61="",L61=""),"",IF(L61=0,"⚠ NO PARENT WIDTH",IF(K61>L61,"⚠ BABY > PARENT","✔ OK"))) | N61: =IF(D61="","",IF(COUNTIF(D$3:D61,D61)>1,"⚠ DUPLICATE","")) | O61: =IF(B61="","",SUMIF(B:B,B61,G:G)&" / "&IFERROR(VLOOKUP(B61,'Coil Sheet at Plant'!$C:$I,7,FALSE),"?")&" mm")
D62: =IF(OR(B62="",C62=""),"",CONCATENATE(B62,"-",C62)) | E62: =IF(B62="","",IFERROR(VLOOKUP(B62,'Coil Sheet at Plant'!$C:$G,5,FALSE),"ID Not Found")) | F62: =IF(B62="","",IFERROR(VLOOKUP(B62,'Coil Sheet at Plant'!$C:$H,6,FALSE),"ID Not Found")) | H62: =IF(OR(B62="",G62=""),"",IFERROR(VLOOKUP(B62,'Coil Sheet at Plant'!$C:$J,8,FALSE),0)*G62/SUMIF(B:B,B62,G:G)) | I62: =IF(B62="","",IFERROR(VLOOKUP(B62,'Coil Sheet at Plant'!$C:$L,9,FALSE),"")) | J62: =IF(B62="","",IFERROR(VLOOKUP(B62,'Coil Sheet at Plant'!$C:$M,10,FALSE),"")) | K62: =IF(B62="","",SUMIF(B:B,B62,G:G)) | L62: =IF(B62="","",IFERROR(VLOOKUP(B62,'Coil Sheet at Plant'!$C:$I,7,FALSE),"")) | M62: =IF(OR(K62="",L62=""),"",IF(L62=0,"⚠ NO PARENT WIDTH",IF(K62>L62,"⚠ BABY > PARENT","✔ OK"))) | N62: =IF(D62="","",IF(COUNTIF(D$3:D62,D62)>1,"⚠ DUPLICATE","")) | O62: =IF(B62="","",SUMIF(B:B,B62,G:G)&" / "&IFERROR(VLOOKUP(B62,'Coil Sheet at Plant'!$C:$I,7,FALSE),"?")&" mm")
D63: =IF(OR(B63="",C63=""),"",CONCATENATE(B63,"-",C63)) | E63: =IF(B63="","",IFERROR(VLOOKUP(B63,'Coil Sheet at Plant'!$C:$G,5,FALSE),"ID Not Found")) | F63: =IF(B63="","",IFERROR(VLOOKUP(B63,'Coil Sheet at Plant'!$C:$H,6,FALSE),"ID Not Found")) | H63: =IF(OR(B63="",G63=""),"",IFERROR(VLOOKUP(B63,'Coil Sheet at Plant'!$C:$J,8,FALSE),0)*G63/SUMIF(B:B,B63,G:G)) | I63: =IF(B63="","",IFERROR(VLOOKUP(B63,'Coil Sheet at Plant'!$C:$L,9,FALSE),"")) | J63: =IF(B63="","",IFERROR(VLOOKUP(B63,'Coil Sheet at Plant'!$C:$M,10,FALSE),"")) | K63: =IF(B63="","",SUMIF(B:B,B63,G:G)) | L63: =IF(B63="","",IFERROR(VLOOKUP(B63,'Coil Sheet at Plant'!$C:$I,7,FALSE),"")) | M63: =IF(OR(K63="",L63=""),"",IF(L63=0,"⚠ NO PARENT WIDTH",IF(K63>L63,"⚠ BABY > PARENT","✔ OK"))) | N63: =IF(D63="","",IF(COUNTIF(D$3:D63,D63)>1,"⚠ DUPLICATE","")) | O63: =IF(B63="","",SUMIF(B:B,B63,G:G)&" / "&IFERROR(VLOOKUP(B63,'Coil Sheet at Plant'!$C:$I,7,FALSE),"?")&" mm")
D64: =IF(OR(B64="",C64=""),"",CONCATENATE(B64,"-",C64)) | E64: =IF(B64="","",IFERROR(VLOOKUP(B64,'Coil Sheet at Plant'!$C:$G,5,FALSE),"ID Not Found")) | F64: =IF(B64="","",IFERROR(VLOOKUP(B64,'Coil Sheet at Plant'!$C:$H,6,FALSE),"ID Not Found")) | H64: =IF(OR(B64="",G64=""),"",IFERROR(VLOOKUP(B64,'Coil Sheet at Plant'!$C:$J,8,FALSE),0)*G64/SUMIF(B:B,B64,G:G)) | I64: =IF(B64="","",IFERROR(VLOOKUP(B64,'Coil Sheet at Plant'!$C:$L,9,FALSE),"")) | J64: =IF(B64="","",IFERROR(VLOOKUP(B64,'Coil Sheet at Plant'!$C:$M,10,FALSE),"")) | K64: =IF(B64="","",SUMIF(B:B,B64,G:G)) | L64: =IF(B64="","",IFERROR(VLOOKUP(B64,'Coil Sheet at Plant'!$C:$I,7,FALSE),"")) | M64: =IF(OR(K64="",L64=""),"",IF(L64=0,"⚠ NO PARENT WIDTH",IF(K64>L64,"⚠ BABY > PARENT","✔ OK"))) | N64: =IF(D64="","",IF(COUNTIF(D$3:D64,D64)>1,"⚠ DUPLICATE","")) | O64: =IF(B64="","",SUMIF(B:B,B64,G:G)&" / "&IFERROR(VLOOKUP(B64,'Coil Sheet at Plant'!$C:$I,7,FALSE),"?")&" mm")
D65: =IF(OR(B65="",C65=""),"",CONCATENATE(B65,"-",C65)) | E65: =IF(B65="","",IFERROR(VLOOKUP(B65,'Coil Sheet at Plant'!$C:$G,5,FALSE),"ID Not Found")) | F65: =IF(B65="","",IFERROR(VLOOKUP(B65,'Coil Sheet at Plant'!$C:$H,6,FALSE),"ID Not Found")) | H65: =IF(OR(B65="",G65=""),"",IFERROR(VLOOKUP(B65,'Coil Sheet at Plant'!$C:$J,8,FALSE),0)*G65/SUMIF(B:B,B65,G:G)) | I65: =IF(B65="","",IFERROR(VLOOKUP(B65,'Coil Sheet at Plant'!$C:$L,9,FALSE),"")) | J65: =IF(B65="","",IFERROR(VLOOKUP(B65,'Coil Sheet at Plant'!$C:$M,10,FALSE),"")) | K65: =IF(B65="","",SUMIF(B:B,B65,G:G)) | L65: =IF(B65="","",IFERROR(VLOOKUP(B65,'Coil Sheet at Plant'!$C:$I,7,FALSE),"")) | M65: =IF(OR(K65="",L65=""),"",IF(L65=0,"⚠ NO PARENT WIDTH",IF(K65>L65,"⚠ BABY > PARENT","✔ OK"))) | N65: =IF(D65="","",IF(COUNTIF(D$3:D65,D65)>1,"⚠ DUPLICATE","")) | O65: =IF(B65="","",SUMIF(B:B,B65,G:G)&" / "&IFERROR(VLOOKUP(B65,'Coil Sheet at Plant'!$C:$I,7,FALSE),"?")&" mm")
D66: =IF(OR(B66="",C66=""),"",CONCATENATE(B66,"-",C66)) | E66: =IF(B66="","",IFERROR(VLOOKUP(B66,'Coil Sheet at Plant'!$C:$G,5,FALSE),"ID Not Found")) | F66: =IF(B66="","",IFERROR(VLOOKUP(B66,'Coil Sheet at Plant'!$C:$H,6,FALSE),"ID Not Found")) | H66: =IF(OR(B66="",G66=""),"",IFERROR(VLOOKUP(B66,'Coil Sheet at Plant'!$C:$J,8,FALSE),0)*G66/SUMIF(B:B,B66,G:G)) | I66: =IF(B66="","",IFERROR(VLOOKUP(B66,'Coil Sheet at Plant'!$C:$L,9,FALSE),"")) | J66: =IF(B66="","",IFERROR(VLOOKUP(B66,'Coil Sheet at Plant'!$C:$M,10,FALSE),"")) | K66: =IF(B66="","",SUMIF(B:B,B66,G:G)) | L66: =IF(B66="","",IFERROR(VLOOKUP(B66,'Coil Sheet at Plant'!$C:$I,7,FALSE),"")) | M66: =IF(OR(K66="",L66=""),"",IF(L66=0,"⚠ NO PARENT WIDTH",IF(K66>L66,"⚠ BABY > PARENT","✔ OK"))) | N66: =IF(D66="","",IF(COUNTIF(D$3:D66,D66)>1,"⚠ DUPLICATE","")) | O66: =IF(B66="","",SUMIF(B:B,B66,G:G)&" / "&IFERROR(VLOOKUP(B66,'Coil Sheet at Plant'!$C:$I,7,FALSE),"?")&" mm")
D67: =IF(OR(B67="",C67=""),"",CONCATENATE(B67,"-",C67)) | E67: =IF(B67="","",IFERROR(VLOOKUP(B67,'Coil Sheet at Plant'!$C:$G,5,FALSE),"ID Not Found")) | F67: =IF(B67="","",IFERROR(VLOOKUP(B67,'Coil Sheet at Plant'!$C:$H,6,FALSE),"ID Not Found")) | H67: =IF(OR(B67="",G67=""),"",IFERROR(VLOOKUP(B67,'Coil Sheet at Plant'!$C:$J,8,FALSE),0)*G67/SUMIF(B:B,B67,G:G)) | I67: =IF(B67="","",IFERROR(VLOOKUP(B67,'Coil Sheet at Plant'!$C:$L,9,FALSE),"")) | J67: =IF(B67="","",IFERROR(VLOOKUP(B67,'Coil Sheet at Plant'!$C:$M,10,FALSE),"")) | K67: =IF(B67="","",SUMIF(B:B,B67,G:G)) | L67: =IF(B67="","",IFERROR(VLOOKUP(B67,'Coil Sheet at Plant'!$C:$I,7,FALSE),"")) | M67: =IF(OR(K67="",L67=""),"",IF(L67=0,"⚠ NO PARENT WIDTH",IF(K67>L67,"⚠ BABY > PARENT","✔ OK"))) | N67: =IF(D67="","",IF(COUNTIF(D$3:D67,D67)>1,"⚠ DUPLICATE","")) | O67: =IF(B67="","",SUMIF(B:B,B67,G:G)&" / "&IFERROR(VLOOKUP(B67,'Coil Sheet at Plant'!$C:$I,7,FALSE),"?")&" mm")
D68: =IF(OR(B68="",C68=""),"",CONCATENATE(B68,"-",C68)) | E68: =IF(B68="","",IFERROR(VLOOKUP(B68,'Coil Sheet at Plant'!$C:$G,5,FALSE),"ID Not Found")) | F68: =IF(B68="","",IFERROR(VLOOKUP(B68,'Coil Sheet at Plant'!$C:$H,6,FALSE),"ID Not Found")) | H68: =IF(OR(B68="",G68=""),"",IFERROR(VLOOKUP(B68,'Coil Sheet at Plant'!$C:$J,8,FALSE),0)*G68/SUMIF(B:B,B68,G:G)) | I68: =IF(B68="","",IFERROR(VLOOKUP(B68,'Coil Sheet at Plant'!$C:$L,9,FALSE),"")) | J68: =IF(B68="","",IFERROR(VLOOKUP(B68,'Coil Sheet at Plant'!$C:$M,10,FALSE),"")) | K68: =IF(B68="","",SUMIF(B:B,B68,G:G)) | L68: =IF(B68="","",IFERROR(VLOOKUP(B68,'Coil Sheet at Plant'!$C:$I,7,FALSE),"")) | M68: =IF(OR(K68="",L68=""),"",IF(L68=0,"⚠ NO PARENT WIDTH",IF(K68>L68,"⚠ BABY > PARENT","✔ OK"))) | N68: =IF(D68="","",IF(COUNTIF(D$3:D68,D68)>1,"⚠ DUPLICATE","")) | O68: =IF(B68="","",SUMIF(B:B,B68,G:G)&" / "&IFERROR(VLOOKUP(B68,'Coil Sheet at Plant'!$C:$I,7,FALSE),"?")&" mm")
... D100: =IF(OR(B100="",C100=""),"",CONCATENATE(B100,"-",C100)) | E100: =IF(B100="","",IFERROR(VLOOKUP(B100,'Coil Sheet at Plant'!$C:$G,5,FALSE),"ID Not Found")) | F100: =IF(B100="","",IFERROR(VLOOKUP(B100,'Coil Sheet at Plant'!$C:$H,6,FALSE),"ID Not Found")) | H100: =IF(OR(B100="",G100=""),"",IFERROR(VLOOKUP(B100,'Coil Sheet at Plant'!$C:$J,8,FALSE),0)*G100/SUMIF(B:B,B100,G:G)) | I100: =IF(B100="","",IFERROR(VLOOKUP(B100,'Coil Sheet at Plant'!$C:$L,9,FALSE),"")) | J100: =IF(B100="","",IFERROR(VLOOKUP(B100,'Coil Sheet at Plant'!$C:$M,10,FALSE),"")) | K100: =IF(B100="","",SUMIF(B:B,B100,G:G)) | L100: =IF(B100="","",IFERROR(VLOOKUP(B100,'Coil Sheet at Plant'!$C:$I,7,FALSE),"")) | M100: =IF(OR(K100="",L100=""),"",IF(L100=0,"⚠ NO PARENT WIDTH",IF(K100>L100,"⚠ BABY > PARENT","✔ OK"))) | N100: =IF(D100="","",IF(COUNTIF(D$3:D100,D100)>1,"⚠ DUPLICATE","")) | O100: =IF(B100="","",SUMIF(B:B,B100,G:G)&" / "&IFERROR(VLOOKUP(B100,'Coil Sheet at Plant'!$C:$I,7,FALSE),"?")&" mm")
D101: =IF(OR(B101="",C101=""),"",CONCATENATE(B101,"-",C101)) | E101: =IF(B101="","",IFERROR(VLOOKUP(B101,'Coil Sheet at Plant'!$C:$G,5,FALSE),"ID Not Found")) | F101: =IF(B101="","",IFERROR(VLOOKUP(B101,'Coil Sheet at Plant'!$C:$H,6,FALSE),"ID Not Found")) | G101: 248 | H101: =IF(OR(B101="",G101=""),"",IFERROR(VLOOKUP(B101,'Coil Sheet at Plant'!$C:$J,8,FALSE),0)*G101/SUMIF(B:B,B101,G:G)) | I101: =IF(B101="","",IFERROR(VLOOKUP(B101,'Coil Sheet at Plant'!$C:$L,9,FALSE),"")) | J101: =IF(B101="","",IFERROR(VLOOKUP(B101,'Coil Sheet at Plant'!$C:$M,10,FALSE),"")) | K101: =IF(B101="","",SUMIF(B:B,B101,G:G)) | L101: =IF(B101="","",IFERROR(VLOOKUP(B101,'Coil Sheet at Plant'!$C:$I,7,FALSE),"")) | M101: =IF(OR(K101="",L101=""),"",IF(L101=0,"⚠ NO PARENT WIDTH",IF(K101>L101,"⚠ BABY > PARENT","✔ OK"))) | N101: =IF(D101="","",IF(COUNTIF(D$3:D101,D101)>1,"⚠ DUPLICATE","")) | O101: =IF(B101="","",SUMIF(B:B,B101,G:G)&" / "&IFERROR(VLOOKUP(B101,'Coil Sheet at Plant'!$C:$I,7,FALSE),"?")&" mm")
D102: =IF(OR(B102="",C102=""),"",CONCATENATE(B102,"-",C102)) | E102: =IF(B102="","",IFERROR(VLOOKUP(B102,'Coil Sheet at Plant'!$C:$G,5,FALSE),"ID Not Found")) | F102: =IF(B102="","",IFERROR(VLOOKUP(B102,'Coil Sheet at Plant'!$C:$H,6,FALSE),"ID Not Found")) | G102: 249 | H102: =IF(OR(B102="",G102=""),"",IFERROR(VLOOKUP(B102,'Coil Sheet at Plant'!$C:$J,8,FALSE),0)*G102/SUMIF(B:B,B102,G:G)) | I102: =IF(B102="","",IFERROR(VLOOKUP(B102,'Coil Sheet at Plant'!$C:$L,9,FALSE),"")) | J102: =IF(B102="","",IFERROR(VLOOKUP(B102,'Coil Sheet at Plant'!$C:$M,10,FALSE),"")) | K102: =IF(B102="","",SUMIF(B:B,B102,G:G)) | L102: =IF(B102="","",IFERROR(VLOOKUP(B102,'Coil Sheet at Plant'!$C:$I,7,FALSE),"")) | M102: =IF(OR(K102="",L102=""),"",IF(L102=0,"⚠ NO PARENT WIDTH",IF(K102>L102,"⚠ BABY > PARENT","✔ OK"))) | N102: =IF(D102="","",IF(COUNTIF(D$3:D102,D102)>1,"⚠ DUPLICATE","")) | O102: =IF(B102="","",SUMIF(B:B,B102,G:G)&" / "&IFERROR(VLOOKUP(B102,'Coil Sheet at Plant'!$C:$I,7,FALSE),"?")&" mm")
D103: =IF(OR(B103="",C103=""),"",CONCATENATE(B103,"-",C103)) | E103: =IF(B103="","",IFERROR(VLOOKUP(B103,'Coil Sheet at Plant'!$C:$G,5,FALSE),"ID Not Found")) | F103: =IF(B103="","",IFERROR(VLOOKUP(B103,'Coil Sheet at Plant'!$C:$H,6,FALSE),"ID Not Found")) | G103: 250 | H103: =IF(OR(B103="",G103=""),"",IFERROR(VLOOKUP(B103,'Coil Sheet at Plant'!$C:$J,8,FALSE),0)*G103/SUMIF(B:B,B103,G:G)) | I103: =IF(B103="","",IFERROR(VLOOKUP(B103,'Coil Sheet at Plant'!$C:$L,9,FALSE),"")) | J103: =IF(B103="","",IFERROR(VLOOKUP(B103,'Coil Sheet at Plant'!$C:$M,10,FALSE),"")) | K103: =IF(B103="","",SUMIF(B:B,B103,G:G)) | L103: =IF(B103="","",IFERROR(VLOOKUP(B103,'Coil Sheet at Plant'!$C:$I,7,FALSE),"")) | M103: =IF(OR(K103="",L103=""),"",IF(L103=0,"⚠ NO PARENT WIDTH",IF(K103>L103,"⚠ BABY > PARENT","✔ OK"))) | N103: =IF(D103="","",IF(COUNTIF(D$3:D103,D103)>1,"⚠ DUPLICATE","")) | O103: =IF(B103="","",SUMIF(B:B,B103,G:G)&" / "&IFERROR(VLOOKUP(B103,'Coil Sheet at Plant'!$C:$I,7,FALSE),"?")&" mm")
D104: =IF(OR(B104="",C104=""),"",CONCATENATE(B104,"-",C104)) | E104: =IF(B104="","",IFERROR(VLOOKUP(B104,'Coil Sheet at Plant'!$C:$G,5,FALSE),"ID Not Found")) | F104: =IF(B104="","",IFERROR(VLOOKUP(B104,'Coil Sheet at Plant'!$C:$H,6,FALSE),"ID Not Found")) | G104: 251 | H104: =IF(OR(B104="",G104=""),"",IFERROR(VLOOKUP(B104,'Coil Sheet at Plant'!$C:$J,8,FALSE),0)*G104/SUMIF(B:B,B104,G:G)) | I104: =IF(B104="","",IFERROR(VLOOKUP(B104,'Coil Sheet at Plant'!$C:$L,9,FALSE),"")) | J104: =IF(B104="","",IFERROR(VLOOKUP(B104,'Coil Sheet at Plant'!$C:$M,10,FALSE),"")) | K104: =IF(B104="","",SUMIF(B:B,B104,G:G)) | L104: =IF(B104="","",IFERROR(VLOOKUP(B104,'Coil Sheet at Plant'!$C:$I,7,FALSE),"")) | M104: =IF(OR(K104="",L104=""),"",IF(L104=0,"⚠ NO PARENT WIDTH",IF(K104>L104,"⚠ BABY > PARENT","✔ OK"))) | N104: =IF(D104="","",IF(COUNTIF(D$3:D104,D104)>1,"⚠ DUPLICATE","")) | O104: =IF(B104="","",SUMIF(B:B,B104,G:G)&" / "&IFERROR(VLOOKUP(B104,'Coil Sheet at Plant'!$C:$I,7,FALSE),"?")&" mm")
D105: =IF(OR(B105="",C105=""),"",CONCATENATE(B105,"-",C105)) | E105: =IF(B105="","",IFERROR(VLOOKUP(B105,'Coil Sheet at Plant'!$C:$G,5,FALSE),"ID Not Found")) | F105: =IF(B105="","",IFERROR(VLOOKUP(B105,'Coil Sheet at Plant'!$C:$H,6,FALSE),"ID Not Found")) | G105: 252 | H105: =IF(OR(B105="",G105=""),"",IFERROR(VLOOKUP(B105,'Coil Sheet at Plant'!$C:$J,8,FALSE),0)*G105/SUMIF(B:B,B105,G:G)) | I105: =IF(B105="","",IFERROR(VLOOKUP(B105,'Coil Sheet at Plant'!$C:$L,9,FALSE),"")) | J105: =IF(B105="","",IFERROR(VLOOKUP(B105,'Coil Sheet at Plant'!$C:$M,10,FALSE),"")) | K105: =IF(B105="","",SUMIF(B:B,B105,G:G)) | L105: =IF(B105="","",IFERROR(VLOOKUP(B105,'Coil Sheet at Plant'!$C:$I,7,FALSE),"")) | M105: =IF(OR(K105="",L105=""),"",IF(L105=0,"⚠ NO PARENT WIDTH",IF(K105>L105,"⚠ BABY > PARENT","✔ OK"))) | N105: =IF(D105="","",IF(COUNTIF(D$3:D105,D105)>1,"⚠ DUPLICATE","")) | O105: =IF(B105="","",SUMIF(B:B,B105,G:G)&" / "&IFERROR(VLOOKUP(B105,'Coil Sheet at Plant'!$C:$I,7,FALSE),"?")&" mm")
D106: =IF(OR(B106="",C106=""),"",CONCATENATE(B106,"-",C106)) | E106: =IF(B106="","",IFERROR(VLOOKUP(B106,'Coil Sheet at Plant'!$C:$G,5,FALSE),"ID Not Found")) | F106: =IF(B106="","",IFERROR(VLOOKUP(B106,'Coil Sheet at Plant'!$C:$H,6,FALSE),"ID Not Found")) | G106: 253 | H106: =IF(OR(B106="",G106=""),"",IFERROR(VLOOKUP(B106,'Coil Sheet at Plant'!$C:$J,8,FALSE),0)*G106/SUMIF(B:B,B106,G:G)) | I106: =IF(B106="","",IFERROR(VLOOKUP(B106,'Coil Sheet at Plant'!$C:$L,9,FALSE),"")) | J106: =IF(B106="","",IFERROR(VLOOKUP(B106,'Coil Sheet at Plant'!$C:$M,10,FALSE),"")) | K106: =IF(B106="","",SUMIF(B:B,B106,G:G)) | L106: =IF(B106="","",IFERROR(VLOOKUP(B106,'Coil Sheet at Plant'!$C:$I,7,FALSE),"")) | M106: =IF(OR(K106="",L106=""),"",IF(L106=0,"⚠ NO PARENT WIDTH",IF(K106>L106,"⚠ BABY > PARENT","✔ OK"))) | N106: =IF(D106="","",IF(COUNTIF(D$3:D106,D106)>1,"⚠ DUPLICATE","")) | O106: =IF(B106="","",SUMIF(B:B,B106,G:G)&" / "&IFERROR(VLOOKUP(B106,'Coil Sheet at Plant'!$C:$I,7,FALSE),"?")&" mm")
D107: =IF(OR(B107="",C107=""),"",CONCATENATE(B107,"-",C107)) | E107: =IF(B107="","",IFERROR(VLOOKUP(B107,'Coil Sheet at Plant'!$C:$G,5,FALSE),"ID Not Found")) | F107: =IF(B107="","",IFERROR(VLOOKUP(B107,'Coil Sheet at Plant'!$C:$H,6,FALSE),"ID Not Found")) | G107: 254 | H107: =IF(OR(B107="",G107=""),"",IFERROR(VLOOKUP(B107,'Coil Sheet at Plant'!$C:$J,8,FALSE),0)*G107/SUMIF(B:B,B107,G:G)) | I107: =IF(B107="","",IFERROR(VLOOKUP(B107,'Coil Sheet at Plant'!$C:$L,9,FALSE),"")) | J107: =IF(B107="","",IFERROR(VLOOKUP(B107,'Coil Sheet at Plant'!$C:$M,10,FALSE),"")) | K107: =IF(B107="","",SUMIF(B:B,B107,G:G)) | L107: =IF(B107="","",IFERROR(VLOOKUP(B107,'Coil Sheet at Plant'!$C:$I,7,FALSE),"")) | M107: =IF(OR(K107="",L107=""),"",IF(L107=0,"⚠ NO PARENT WIDTH",IF(K107>L107,"⚠ BABY > PARENT","✔ OK"))) | N107: =IF(D107="","",IF(COUNTIF(D$3:D107,D107)>1,"⚠ DUPLICATE","")) | O107: =IF(B107="","",SUMIF(B:B,B107,G:G)&" / "&IFERROR(VLOOKUP(B107,'Coil Sheet at Plant'!$C:$I,7,FALSE),"?")&" mm")
D108: =IF(OR(B108="",C108=""),"",CONCATENATE(B108,"-",C108)) | E108: =IF(B108="","",IFERROR(VLOOKUP(B108,'Coil Sheet at Plant'!$C:$G,5,FALSE),"ID Not Found")) | F108: =IF(B108="","",IFERROR(VLOOKUP(B108,'Coil Sheet at Plant'!$C:$H,6,FALSE),"ID Not Found")) | G108: 255 | H108: =IF(OR(B108="",G108=""),"",IFERROR(VLOOKUP(B108,'Coil Sheet at Plant'!$C:$J,8,FALSE),0)*G108/SUMIF(B:B,B108,G:G)) | I108: =IF(B108="","",IFERROR(VLOOKUP(B108,'Coil Sheet at Plant'!$C:$L,9,FALSE),"")) | J108: =IF(B108="","",IFERROR(VLOOKUP(B108,'Coil Sheet at Plant'!$C:$M,10,FALSE),"")) | K108: =IF(B108="","",SUMIF(B:B,B108,G:G)) | L108: =IF(B108="","",IFERROR(VLOOKUP(B108,'Coil Sheet at Plant'!$C:$I,7,FALSE),"")) | M108: =IF(OR(K108="",L108=""),"",IF(L108=0,"⚠ NO PARENT WIDTH",IF(K108>L108,"⚠ BABY > PARENT","✔ OK"))) | N108: =IF(D108="","",IF(COUNTIF(D$3:D108,D108)>1,"⚠ DUPLICATE","")) | O108: =IF(B108="","",SUMIF(B:B,B108,G:G)&" / "&IFERROR(VLOOKUP(B108,'Coil Sheet at Plant'!$C:$I,7,FALSE),"?")&" mm")
D109: =IF(OR(B109="",C109=""),"",CONCATENATE(B109,"-",C109)) | E109: =IF(B109="","",IFERROR(VLOOKUP(B109,'Coil Sheet at Plant'!$C:$G,5,FALSE),"ID Not Found")) | F109: =IF(B109="","",IFERROR(VLOOKUP(B109,'Coil Sheet at Plant'!$C:$H,6,FALSE),"ID Not Found")) | G109: 256 | H109: =IF(OR(B109="",G109=""),"",IFERROR(VLOOKUP(B109,'Coil Sheet at Plant'!$C:$J,8,FALSE),0)*G109/SUMIF(B:B,B109,G:G)) | I109: =IF(B109="","",IFERROR(VLOOKUP(B109,'Coil Sheet at Plant'!$C:$L,9,FALSE),"")) | J109: =IF(B109="","",IFERROR(VLOOKUP(B109,'Coil Sheet at Plant'!$C:$M,10,FALSE),"")) | K109: =IF(B109="","",SUMIF(B:B,B109,G:G)) | L109: =IF(B109="","",IFERROR(VLOOKUP(B109,'Coil Sheet at Plant'!$C:$I,7,FALSE),"")) | M109: =IF(OR(K109="",L109=""),"",IF(L109=0,"⚠ NO PARENT WIDTH",IF(K109>L109,"⚠ BABY > PARENT","✔ OK"))) | N109: =IF(D109="","",IF(COUNTIF(D$3:D109,D109)>1,"⚠ DUPLICATE","")) | O109: =IF(B109="","",SUMIF(B:B,B109,G:G)&" / "&IFERROR(VLOOKUP(B109,'Coil Sheet at Plant'!$C:$I,7,FALSE),"?")&" mm")
D110: =IF(OR(B110="",C110=""),"",CONCATENATE(B110,"-",C110)) | E110: =IF(B110="","",IFERROR(VLOOKUP(B110,'Coil Sheet at Plant'!$C:$G,5,FALSE),"ID Not Found")) | F110: =IF(B110="","",IFERROR(VLOOKUP(B110,'Coil Sheet at Plant'!$C:$H,6,FALSE),"ID Not Found")) | G110: 257 | H110: =IF(OR(B110="",G110=""),"",IFERROR(VLOOKUP(B110,'Coil Sheet at Plant'!$C:$J,8,FALSE),0)*G110/SUMIF(B:B,B110,G:G)) | I110: =IF(B110="","",IFERROR(VLOOKUP(B110,'Coil Sheet at Plant'!$C:$L,9,FALSE),"")) | J110: =IF(B110="","",IFERROR(VLOOKUP(B110,'Coil Sheet at Plant'!$C:$M,10,FALSE),"")) | K110: =IF(B110="","",SUMIF(B:B,B110,G:G)) | L110: =IF(B110="","",IFERROR(VLOOKUP(B110,'Coil Sheet at Plant'!$C:$I,7,FALSE),"")) | M110: =IF(OR(K110="",L110=""),"",IF(L110=0,"⚠ NO PARENT WIDTH",IF(K110>L110,"⚠ BABY > PARENT","✔ OK"))) | N110: =IF(D110="","",IF(COUNTIF(D$3:D110,D110)>1,"⚠ DUPLICATE","")) | O110: =IF(B110="","",SUMIF(B:B,B110,G:G)&" / "&IFERROR(VLOOKUP(B110,'Coil Sheet at Plant'!$C:$I,7,FALSE),"?")&" mm")
D111: =IF(OR(B111="",C111=""),"",CONCATENATE(B111,"-",C111)) | E111: =IF(B111="","",IFERROR(VLOOKUP(B111,'Coil Sheet at Plant'!$C:$G,5,FALSE),"ID Not Found")) | F111: =IF(B111="","",IFERROR(VLOOKUP(B111,'Coil Sheet at Plant'!$C:$H,6,FALSE),"ID Not Found")) | G111: 258 | H111: =IF(OR(B111="",G111=""),"",IFERROR(VLOOKUP(B111,'Coil Sheet at Plant'!$C:$J,8,FALSE),0)*G111/SUMIF(B:B,B111,G:G)) | I111: =IF(B111="","",IFERROR(VLOOKUP(B111,'Coil Sheet at Plant'!$C:$L,9,FALSE),"")) | J111: =IF(B111="","",IFERROR(VLOOKUP(B111,'Coil Sheet at Plant'!$C:$M,10,FALSE),"")) | K111: =IF(B111="","",SUMIF(B:B,B111,G:G)) | L111: =IF(B111="","",IFERROR(VLOOKUP(B111,'Coil Sheet at Plant'!$C:$I,7,FALSE),"")) | M111: =IF(OR(K111="",L111=""),"",IF(L111=0,"⚠ NO PARENT WIDTH",IF(K111>L111,"⚠ BABY > PARENT","✔ OK"))) | N111: =IF(D111="","",IF(COUNTIF(D$3:D111,D111)>1,"⚠ DUPLICATE","")) | O111: =IF(B111="","",SUMIF(B:B,B111,G:G)&" / "&IFERROR(VLOOKUP(B111,'Coil Sheet at Plant'!$C:$I,7,FALSE),"?")&" mm")
D112: =IF(OR(B112="",C112=""),"",CONCATENATE(B112,"-",C112)) | E112: =IF(B112="","",IFERROR(VLOOKUP(B112,'Coil Sheet at Plant'!$C:$G,5,FALSE),"ID Not Found")) | F112: =IF(B112="","",IFERROR(VLOOKUP(B112,'Coil Sheet at Plant'!$C:$H,6,FALSE),"ID Not Found")) | G112: 259 | H112: =IF(OR(B112="",G112=""),"",IFERROR(VLOOKUP(B112,'Coil Sheet at Plant'!$C:$J,8,FALSE),0)*G112/SUMIF(B:B,B112,G:G)) | I112: =IF(B112="","",IFERROR(VLOOKUP(B112,'Coil Sheet at Plant'!$C:$L,9,FALSE),"")) | J112: =IF(B112="","",IFERROR(VLOOKUP(B112,'Coil Sheet at Plant'!$C:$M,10,FALSE),"")) | K112: =IF(B112="","",SUMIF(B:B,B112,G:G)) | L112: =IF(B112="","",IFERROR(VLOOKUP(B112,'Coil Sheet at Plant'!$C:$I,7,FALSE),"")) | M112: =IF(OR(K112="",L112=""),"",IF(L112=0,"⚠ NO PARENT WIDTH",IF(K112>L112,"⚠ BABY > PARENT","✔ OK"))) | N112: =IF(D112="","",IF(COUNTIF(D$3:D112,D112)>1,"⚠ DUPLICATE","")) | O112: =IF(B112="","",SUMIF(B:B,B112,G:G)&" / "&IFERROR(VLOOKUP(B112,'Coil Sheet at Plant'!$C:$I,7,FALSE),"?")&" mm")
... D1000: =IF(OR(B1000="",C1000=""),"",CONCATENATE(B1000,"-",C1000)) | E1000: =IF(B1000="","",IFERROR(VLOOKUP(B1000,'Coil Sheet at Plant'!$C:$G,5,FALSE),"ID Not Found")) | F1000: =IF(B1000="","",IFERROR(VLOOKUP(B1000,'Coil Sheet at Plant'!$C:$H,6,FALSE),"ID Not Found")) | G1000: 1147 | H1000: =IF(OR(B1000="",G1000=""),"",IFERROR(VLOOKUP(B1000,'Coil Sheet at Plant'!$C:$J,8,FALSE),0)*G1000/SUMIF(B:B,B1000,G:G)) | I1000: =IF(B1000="","",IFERROR(VLOOKUP(B1000,'Coil Sheet at Plant'!$C:$L,9,FALSE),"")) | J1000: =IF(B1000="","",IFERROR(VLOOKUP(B1000,'Coil Sheet at Plant'!$C:$M,10,FALSE),"")) | K1000: =IF(B1000="","",SUMIF(B:B,B1000,G:G)) | L1000: =IF(B1000="","",IFERROR(VLOOKUP(B1000,'Coil Sheet at Plant'!$C:$I,7,FALSE),"")) | M1000: =IF(OR(K1000="",L1000=""),"",IF(L1000=0,"⚠ NO PARENT WIDTH",IF(K1000>L1000,"⚠ BABY > PARENT","✔ OK"))) | N1000: =IF(D1000="","",IF(COUNTIF(D$3:D1000,D1000)>1,"⚠ DUPLICATE","")) | O1000: =IF(B1000="","",SUMIF(B:B,B1000,G:G)&" / "&IFERROR(VLOOKUP(B1000,'Coil Sheet at Plant'!$C:$I,7,FALSE),"?")&" mm")

Sheet Slit to Tube Conversion
A1: 🔵 Manual Entry | I1: 🟡 Validation Helpers
A2: Date of Conversion | B2: SKU Code | C2: Baby Coil ID | D2: Number of Pieces | E2: Length (mm) | F2: Width (mm) | G2: Thickness (mm) | H2: Theortical Weight (T) | I2: Mother Coil Wt (T) | J2: Sum Bundle Wt (T) | K2: Wt Validation | L2: Duplicate Bundle ID Check
A3: 46109 | B3: MS SHS One Helix IS 4923 YSt 210 Black 38x38x2.80x6000 | C3: HYD-0326-01-A | D3: 124 | E3: =IF(C3="","",IFERROR(VLOOKUP(C3,'Coil to Slit'!$D:$H,3,FALSE),"")) -> 0 | F3: =IF(C3="","",IFERROR(VLOOKUP(C3,'Coil to Slit'!$D:$H,4,FALSE),"")) -> 147 | G3: =IF(C3="","",IFERROR(VLOOKUP(C3,'Coil to Slit'!$D:$H,2,FALSE),"")) -> 2.8 | H3: =IF(OR(C3="",D3=""),"",IFERROR(VLOOKUP(C3,'Coil to Slit'!$D:$H,5,FALSE),"")) -> 2.4397506 | I3: =IF(C3="","",IFERROR(VLOOKUP(LEFT(C3,LEN(C3)-2),'Coil Sheet at Plant'!$C:$J,8,FALSE),"")) -> 20.63 | J3: =IF(C3="","",SUMIF(C:C,C3,H:H)) -> 2.4397506 | K3: =IF(OR(I3="",J3=""),"",IF(J3>I3,"⚠ BUNDLES > MOTHER COIL","✔ OK")) -> ✔ OK | L3: =IF(#REF!="","",IF(COUNTIF(#REF!,#REF!)>1,"⚠ DUPLICATE","")) -> #REF!
A4: 46109 | B4: MS SHS One Helix IS 4923 YSt 210 Black 38x38x2.80x6000 | C4: HYD-0326-01-B | D4: 124 | E4: =IF(C4="","",IFERROR(VLOOKUP(C4,'Coil to Slit'!$D:$H,3,FALSE),"")) -> 0 | F4: =IF(C4="","",IFERROR(VLOOKUP(C4,'Coil to Slit'!$D:$H,4,FALSE),"")) -> 147 | G4: =IF(C4="","",IFERROR(VLOOKUP(C4,'Coil to Slit'!$D:$H,2,FALSE),"")) -> 2.8 | H4: =IF(OR(C4="",D4=""),"",IFERROR(VLOOKUP(C4,'Coil to Slit'!$D:$H,5,FALSE),"")) -> 2.4397506 | I4: =IF(C4="","",IFERROR(VLOOKUP(LEFT(C4,LEN(C4)-2),'Coil Sheet at Plant'!$C:$J,8,FALSE),"")) -> 20.63 | J4: =IF(C4="","",SUMIF(C:C,C4,H:H)) -> 2.4397506 | K4: =IF(OR(I4="",J4=""),"",IF(J4>I4,"⚠ BUNDLES > MOTHER COIL","✔ OK")) -> ✔ OK | L4: =IF(#REF!="","",IF(COUNTIF(#REF!,#REF!)>1,"⚠ DUPLICATE","")) -> #REF!
A5: 46111 | B5: MS SHS One Helix IS 4923 YSt 210 Black 38x38x2.80x6000 | C5: HYD-0326-01-C | D5: 126 | E5: =IF(C5="","",IFERROR(VLOOKUP(C5,'Coil to Slit'!$D:$H,3,FALSE),"")) -> 0 | F5: =IF(C5="","",IFERROR(VLOOKUP(C5,'Coil to Slit'!$D:$H,4,FALSE),"")) -> 147 | G5: =IF(C5="","",IFERROR(VLOOKUP(C5,'Coil to Slit'!$D:$H,2,FALSE),"")) -> 2.8 | H5: =IF(OR(C5="",D5=""),"",IFERROR(VLOOKUP(C5,'Coil to Slit'!$D:$H,5,FALSE),"")) -> 2.4397506 | I5: =IF(C5="","",IFERROR(VLOOKUP(LEFT(C5,LEN(C5)-2),'Coil Sheet at Plant'!$C:$J,8,FALSE),"")) -> 20.63 | J5: =IF(C5="","",SUMIF(C:C,C5,H:H)) -> 2.4397506 | K5: =IF(OR(I5="",J5=""),"",IF(J5>I5,"⚠ BUNDLES > MOTHER COIL","✔ OK")) -> ✔ OK | L5: =IF(#REF!="","",IF(COUNTIF(#REF!,#REF!)>1,"⚠ DUPLICATE","")) -> #REF!
A6: 46111 | B6: MS SHS One Helix IS 4923 YSt 210 Black 38x38x2.80x6000 | C6: HYD-0326-01-D | D6: 126 | E6: =IF(C6="","",IFERROR(VLOOKUP(C6,'Coil to Slit'!$D:$H,3,FALSE),"")) -> 0 | F6: =IF(C6="","",IFERROR(VLOOKUP(C6,'Coil to Slit'!$D:$H,4,FALSE),"")) -> 147 | G6: =IF(C6="","",IFERROR(VLOOKUP(C6,'Coil to Slit'!$D:$H,2,FALSE),"")) -> 2.8 | H6: =IF(OR(C6="",D6=""),"",IFERROR(VLOOKUP(C6,'Coil to Slit'!$D:$H,5,FALSE),"")) -> 2.4397506 | I6: =IF(C6="","",IFERROR(VLOOKUP(LEFT(C6,LEN(C6)-2),'Coil Sheet at Plant'!$C:$J,8,FALSE),"")) -> 20.63 | J6: =IF(C6="","",SUMIF(C:C,C6,H:H)) -> 2.4397506 | K6: =IF(OR(I6="",J6=""),"",IF(J6>I6,"⚠ BUNDLES > MOTHER COIL","✔ OK")) -> ✔ OK | L6: =IF(#REF!="","",IF(COUNTIF(#REF!,#REF!)>1,"⚠ DUPLICATE","")) -> #REF!
A7: 46111 | B7: MS SHS One Helix IS 4923 YSt 210 Black 38x38x2.80x6000 | C7: HYD-0326-01-E | D7: 128 | E7: =IF(C7="","",IFERROR(VLOOKUP(C7,'Coil to Slit'!$D:$H,3,FALSE),"")) -> 0 | F7: =IF(C7="","",IFERROR(VLOOKUP(C7,'Coil to Slit'!$D:$H,4,FALSE),"")) -> 147 | G7: =IF(C7="","",IFERROR(VLOOKUP(C7,'Coil to Slit'!$D:$H,2,FALSE),"")) -> 2.8 | H7: =IF(OR(C7="",D7=""),"",IFERROR(VLOOKUP(C7,'Coil to Slit'!$D:$H,5,FALSE),"")) -> 2.4397506 | I7: =IF(C7="","",IFERROR(VLOOKUP(LEFT(C7,LEN(C7)-2),'Coil Sheet at Plant'!$C:$J,8,FALSE),"")) -> 20.63 | J7: =IF(C7="","",SUMIF(C:C,C7,H:H)) -> 2.4397506 | K7: =IF(OR(I7="",J7=""),"",IF(J7>I7,"⚠ BUNDLES > MOTHER COIL","✔ OK")) -> ✔ OK | L7: =IF(#REF!="","",IF(COUNTIF(#REF!,#REF!)>1,"⚠ DUPLICATE","")) -> #REF!
A8: 46111 | B8: MS SHS One Helix IS 4923 YSt 210 Black 38x38x2.80x6000 | C8: HYD-0326-02-A | D8: 127 | E8: =IF(C8="","",IFERROR(VLOOKUP(C8,'Coil to Slit'!$D:$H,3,FALSE),"")) -> 0 | F8: =IF(C8="","",IFERROR(VLOOKUP(C8,'Coil to Slit'!$D:$H,4,FALSE),"")) -> 147 | G8: =IF(C8="","",IFERROR(VLOOKUP(C8,'Coil to Slit'!$D:$H,2,FALSE),"")) -> 2.8 | H8: =IF(OR(C8="",D8=""),"",IFERROR(VLOOKUP(C8,'Coil to Slit'!$D:$H,5,FALSE),"")) -> 2.4752293 | I8: =IF(C8="","",IFERROR(VLOOKUP(LEFT(C8,LEN(C8)-2),'Coil Sheet at Plant'!$C:$J,8,FALSE),"")) -> 20.93 | J8: =IF(C8="","",SUMIF(C:C,C8,H:H)) -> 2.4752293 | K8: =IF(OR(I8="",J8=""),"",IF(J8>I8,"⚠ BUNDLES > MOTHER COIL","✔ OK")) -> ✔ OK | L8: =IF(#REF!="","",IF(COUNTIF(#REF!,#REF!)>1,"⚠ DUPLICATE","")) -> #REF!
A9: 46111 | B9: MS SHS One Helix IS 4923 YSt 210 Black 38x38x2.80x6000 | C9: HYD-0326-02-B | D9: 127 | E9: =IF(C9="","",IFERROR(VLOOKUP(C9,'Coil to Slit'!$D:$H,3,FALSE),"")) -> 0 | F9: =IF(C9="","",IFERROR(VLOOKUP(C9,'Coil to Slit'!$D:$H,4,FALSE),"")) -> 147 | G9: =IF(C9="","",IFERROR(VLOOKUP(C9,'Coil to Slit'!$D:$H,2,FALSE),"")) -> 2.8 | H9: =IF(OR(C9="",D9=""),"",IFERROR(VLOOKUP(C9,'Coil to Slit'!$D:$H,5,FALSE),"")) -> 2.4752293 | I9: =IF(C9="","",IFERROR(VLOOKUP(LEFT(C9,LEN(C9)-2),'Coil Sheet at Plant'!$C:$J,8,FALSE),"")) -> 20.93 | J9: =IF(C9="","",SUMIF(C:C,C9,H:H)) -> 2.4752293 | K9: =IF(OR(I9="",J9=""),"",IF(J9>I9,"⚠ BUNDLES > MOTHER COIL","✔ OK")) -> ✔ OK | L9: =IF(#REF!="","",IF(COUNTIF(#REF!,#REF!)>1,"⚠ DUPLICATE","")) -> #REF!
A10: 46111 | B10: MS SHS One Helix IS 4923 YSt 210 Black 38x38x2.80x6000 | C10: HYD-0326-02-C | D10: 127 | E10: =IF(C10="","",IFERROR(VLOOKUP(C10,'Coil to Slit'!$D:$H,3,FALSE),"")) -> 0 | F10: =IF(C10="","",IFERROR(VLOOKUP(C10,'Coil to Slit'!$D:$H,4,FALSE),"")) -> 147 | G10: =IF(C10="","",IFERROR(VLOOKUP(C10,'Coil to Slit'!$D:$H,2,FALSE),"")) -> 2.8 | H10: =IF(OR(C10="",D10=""),"",IFERROR(VLOOKUP(C10,'Coil to Slit'!$D:$H,5,FALSE),"")) -> 2.4752293 | I10: =IF(C10="","",IFERROR(VLOOKUP(LEFT(C10,LEN(C10)-2),'Coil Sheet at Plant'!$C:$J,8,FALSE),"")) -> 20.93 | J10: =IF(C10="","",SUMIF(C:C,C10,H:H)) -> 2.4752293 | K10: =IF(OR(I10="",J10=""),"",IF(J10>I10,"⚠ BUNDLES > MOTHER COIL","✔ OK")) -> ✔ OK | L10: =IF(#REF!="","",IF(COUNTIF(#REF!,#REF!)>1,"⚠ DUPLICATE","")) -> #REF!
A11: 46111 | B11: MS SHS One Helix IS 4923 YSt 210 Black 38x38x2.80x6000 | C11: HYD-0326-02-D | D11: 127 | E11: =IF(C11="","",IFERROR(VLOOKUP(C11,'Coil to Slit'!$D:$H,3,FALSE),"")) -> 0 | F11: =IF(C11="","",IFERROR(VLOOKUP(C11,'Coil to Slit'!$D:$H,4,FALSE),"")) -> 147 | G11: =IF(C11="","",IFERROR(VLOOKUP(C11,'Coil to Slit'!$D:$H,2,FALSE),"")) -> 2.8 | H11: =IF(OR(C11="",D11=""),"",IFERROR(VLOOKUP(C11,'Coil to Slit'!$D:$H,5,FALSE),"")) -> 2.4752293 | I11: =IF(C11="","",IFERROR(VLOOKUP(LEFT(C11,LEN(C11)-2),'Coil Sheet at Plant'!$C:$J,8,FALSE),"")) -> 20.93 | J11: =IF(C11="","",SUMIF(C:C,C11,H:H)) -> 2.4752293 | K11: =IF(OR(I11="",J11=""),"",IF(J11>I11,"⚠ BUNDLES > MOTHER COIL","✔ OK")) -> ✔ OK | L11: =IF(#REF!="","",IF(COUNTIF(#REF!,#REF!)>1,"⚠ DUPLICATE","")) -> #REF!
A12: 46111 | B12: MS SHS One Helix IS 4923 YSt 210 Black 38x38x2.80x6000 | C12: HYD-0326-02-E | D12: 130 | E12: =IF(C12="","",IFERROR(VLOOKUP(C12,'Coil to Slit'!$D:$H,3,FALSE),"")) -> 0 | F12: =IF(C12="","",IFERROR(VLOOKUP(C12,'Coil to Slit'!$D:$H,4,FALSE),"")) -> 147 | G12: =IF(C12="","",IFERROR(VLOOKUP(C12,'Coil to Slit'!$D:$H,2,FALSE),"")) -> 2.8 | H12: =IF(OR(C12="",D12=""),"",IFERROR(VLOOKUP(C12,'Coil to Slit'!$D:$H,5,FALSE),"")) -> 2.4752293 | I12: =IF(C12="","",IFERROR(VLOOKUP(LEFT(C12,LEN(C12)-2),'Coil Sheet at Plant'!$C:$J,8,FALSE),"")) -> 20.93 | J12: =IF(C12="","",SUMIF(C:C,C12,H:H)) -> 2.4752293 | K12: =IF(OR(I12="",J12=""),"",IF(J12>I12,"⚠ BUNDLES > MOTHER COIL","✔ OK")) -> ✔ OK | L12: =IF(#REF!="","",IF(COUNTIF(#REF!,#REF!)>1,"⚠ DUPLICATE","")) -> #REF!
A13: 46111 | B13: MS SHS One Helix IS 4923 YSt 210 Black 38x38x2.50x6000 | C13: HYD-0326-03-A | D13: 161 | E13: =IF(C13="","",IFERROR(VLOOKUP(C13,'Coil to Slit'!$D:$H,3,FALSE),"")) -> 0 | F13: =IF(C13="","",IFERROR(VLOOKUP(C13,'Coil to Slit'!$D:$H,4,FALSE),"")) -> 147 | G13: =IF(C13="","",IFERROR(VLOOKUP(C13,'Coil to Slit'!$D:$H,2,FALSE),"")) -> 2.5 | H13: =IF(OR(C13="",D13=""),"",IFERROR(VLOOKUP(C13,'Coil to Slit'!$D:$H,5,FALSE),"")) -> 2.8627859 | I13: =IF(C13="","",IFERROR(VLOOKUP(LEFT(C13,LEN(C13)-2),'Coil Sheet at Plant'!$C:$J,8,FALSE),"")) -> 29.29 | J13: =IF(C13="","",SUMIF(C:C,C13,H:H)) -> 2.8627859 | K13: =IF(OR(I13="",J13=""),"",IF(J13>I13,"⚠ BUNDLES > MOTHER COIL","✔ OK")) -> ✔ OK | L13: =IF(#REF!="","",IF(COUNTIF(#REF!,#REF!)>1,"⚠ DUPLICATE","")) -> #REF!
A14: 46111 | B14: MS SHS One Helix IS 4923 YSt 210 Black 38x38x2.50x6000 | C14: HYD-0326-03-B | D14: 161 | E14: =IF(C14="","",IFERROR(VLOOKUP(C14,'Coil to Slit'!$D:$H,3,FALSE),"")) -> 0 | F14: =IF(C14="","",IFERROR(VLOOKUP(C14,'Coil to Slit'!$D:$H,4,FALSE),"")) -> 147 | G14: =IF(C14="","",IFERROR(VLOOKUP(C14,'Coil to Slit'!$D:$H,2,FALSE),"")) -> 2.5 | H14: =IF(OR(C14="",D14=""),"",IFERROR(VLOOKUP(C14,'Coil to Slit'!$D:$H,5,FALSE),"")) -> 2.8627859 | I14: =IF(C14="","",IFERROR(VLOOKUP(LEFT(C14,LEN(C14)-2),'Coil Sheet at Plant'!$C:$J,8,FALSE),"")) -> 29.29 | J14: =IF(C14="","",SUMIF(C:C,C14,H:H)) -> 2.8627859 | K14: =IF(OR(I14="",J14=""),"",IF(J14>I14,"⚠ BUNDLES > MOTHER COIL","✔ OK")) -> ✔ OK | L14: =IF(#REF!="","",IF(COUNTIF(#REF!,#REF!)>1,"⚠ DUPLICATE","")) -> #REF!
... A23: 46112 | B23: MS SHS One Helix IS 4923 YSt 210 Black 50x50x2.80x6000 | C23: HYD-0326-02-G | D23: 125 | E23: =IF(C23="","",IFERROR(VLOOKUP(C23,'Coil to Slit'!$D:$H,3,FALSE),"")) -> 0 | F23: =IF(C23="","",IFERROR(VLOOKUP(C23,'Coil to Slit'!$D:$H,4,FALSE),"")) -> 196 | G23: =IF(C23="","",IFERROR(VLOOKUP(C23,'Coil to Slit'!$D:$H,2,FALSE),"")) -> 2.8 | H23: =IF(OR(C23="",D23=""),"",IFERROR(VLOOKUP(C23,'Coil to Slit'!$D:$H,5,FALSE),"")) -> 3.3003057 | I23: =IF(C23="","",IFERROR(VLOOKUP(LEFT(C23,LEN(C23)-2),'Coil Sheet at Plant'!$C:$J,8,FALSE),"")) -> 20.93 | J23: =IF(C23="","",SUMIF(C:C,C23,H:H)) -> 3.3003057 | K23: =IF(OR(I23="",J23=""),"",IF(J23>I23,"⚠ BUNDLES > MOTHER COIL","✔ OK")) -> ✔ OK | L23: =IF(#REF!="","",IF(COUNTIF(#REF!,#REF!)>1,"⚠ DUPLICATE","")) -> #REF!
A24: 46113 | B24: MS SHS One Helix IS 4923 YSt 210 Black 50x50x2.20x6000 | C24: HYD-0326-04-F | D24: 213 | E24: =IF(C24="","",IFERROR(VLOOKUP(C24,'Coil to Slit'!$D:$H,3,FALSE),"")) -> 0 | F24: =IF(C24="","",IFERROR(VLOOKUP(C24,'Coil to Slit'!$D:$H,4,FALSE),"")) -> 197 | G24: =IF(C24="","",IFERROR(VLOOKUP(C24,'Coil to Slit'!$D:$H,2,FALSE),"")) -> 2.2 | H24: =IF(OR(C24="",D24=""),"",IFERROR(VLOOKUP(C24,'Coil to Slit'!$D:$H,5,FALSE),"")) -> 4.4817106 | I24: =IF(C24="","",IFERROR(VLOOKUP(LEFT(C24,LEN(C24)-2),'Coil Sheet at Plant'!$C:$J,8,FALSE),"")) -> 28.46 | J24: =IF(C24="","",SUMIF(C:C,C24,H:H)) -> 4.4817106 | K24: =IF(OR(I24="",J24=""),"",IF(J24>I24,"⚠ BUNDLES > BABY COIL","✔ OK")) -> ✔ OK | L24: =IF(#REF!="","",IF(COUNTIF(#REF!,#REF!)>1,"⚠ DUPLICATE","")) -> #REF!
A25: 46113 | B25: MS SHS One Helix IS 4923 YSt 210 Black 50x50x2.20x6000 | C25: HYD-0326-04-G | D25: 213 | E25: =IF(C25="","",IFERROR(VLOOKUP(C25,'Coil to Slit'!$D:$H,3,FALSE),"")) -> 0 | F25: =IF(C25="","",IFERROR(VLOOKUP(C25,'Coil to Slit'!$D:$H,4,FALSE),"")) -> 197 | G25: =IF(C25="","",IFERROR(VLOOKUP(C25,'Coil to Slit'!$D:$H,2,FALSE),"")) -> 2.2 | H25: =IF(OR(C25="",D25=""),"",IFERROR(VLOOKUP(C25,'Coil to Slit'!$D:$H,5,FALSE),"")) -> 4.4817106 | I25: =IF(C25="","",IFERROR(VLOOKUP(LEFT(C25,LEN(C25)-2),'Coil Sheet at Plant'!$C:$J,8,FALSE),"")) -> 28.46 | J25: =IF(C25="","",SUMIF(C:C,C25,H:H)) -> 4.4817106 | K25: =IF(OR(I25="",J25=""),"",IF(J25>I25,"⚠ BUNDLES > BABY COIL","✔ OK")) -> ✔ OK | L25: =IF(#REF!="","",IF(COUNTIF(#REF!,#REF!)>1,"⚠ DUPLICATE","")) -> #REF!
A26: 46113 | B26: MS SHS One Helix IS 4923 YSt 210 Black 38x38x2.50x6000 | C26: HYD-0326-03-D | D26: 8 | E26: =IF(C26="","",IFERROR(VLOOKUP(C26,'Coil to Slit'!$D:$H,3,FALSE),"")) -> 0 | F26: =IF(C26="","",IFERROR(VLOOKUP(C26,'Coil to Slit'!$D:$H,4,FALSE),"")) -> 147 | G26: =IF(C26="","",IFERROR(VLOOKUP(C26,'Coil to Slit'!$D:$H,2,FALSE),"")) -> 2.5 | H26: =IF(OR(C26="",D26=""),"",IFERROR(VLOOKUP(C26,'Coil to Slit'!$D:$H,5,FALSE),"")) -> 2.8627859 | I26: =IF(C26="","",IFERROR(VLOOKUP(LEFT(C26,LEN(C26)-2),'Coil Sheet at Plant'!$C:$J,8,FALSE),"")) -> 29.29 | J26: =IF(C26="","",SUMIF(C:C,C26,H:H)) -> 5.7255718 | K26: =IF(OR(I26="",J26=""),"",IF(J26>I26,"⚠ BUNDLES > BABY COIL","✔ OK")) -> ✔ OK | L26: =IF(#REF!="","",IF(COUNTIF(#REF!,#REF!)>1,"⚠ DUPLICATE","")) -> #REF!
A27: 46113 | B27: MS SHS One Helix IS 4923 YSt 210 Black 38x38x2.20x6000 | C27: HYD-0326-04-A | D27: 219 | E27: =IF(C27="","",IFERROR(VLOOKUP(C27,'Coil to Slit'!$D:$H,3,FALSE),"")) -> 0 | F27: =IF(C27="","",IFERROR(VLOOKUP(C27,'Coil to Slit'!$D:$H,4,FALSE),"")) -> 148 | G27: =IF(C27="","",IFERROR(VLOOKUP(C27,'Coil to Slit'!$D:$H,2,FALSE),"")) -> 2.2 | H27: =IF(OR(C27="",D27=""),"",IFERROR(VLOOKUP(C27,'Coil to Slit'!$D:$H,5,FALSE),"")) -> 3.3669704 | I27: =IF(C27="","",IFERROR(VLOOKUP(LEFT(C27,LEN(C27)-2),'Coil Sheet at Plant'!$C:$J,8,FALSE),"")) -> 28.46 | J27: =IF(C27="","",SUMIF(C:C,C27,H:H)) -> 3.3669704 | K27: =IF(OR(I27="",J27=""),"",IF(J27>I27,"⚠ BUNDLES > BABY COIL","✔ OK")) -> ✔ OK | L27: =IF(#REF!="","",IF(COUNTIF(#REF!,#REF!)>1,"⚠ DUPLICATE","")) -> #REF!
A28: 46113 | B28: MS SHS One Helix IS 4923 YSt 210 Black 38x38x2.20x6000 | C28: HYD-0326-04-B | D28: 219 | E28: =IF(C28="","",IFERROR(VLOOKUP(C28,'Coil to Slit'!$D:$H,3,FALSE),"")) -> 0 | F28: =IF(C28="","",IFERROR(VLOOKUP(C28,'Coil to Slit'!$D:$H,4,FALSE),"")) -> 148 | G28: =IF(C28="","",IFERROR(VLOOKUP(C28,'Coil to Slit'!$D:$H,2,FALSE),"")) -> 2.2 | H28: =IF(OR(C28="",D28=""),"",IFERROR(VLOOKUP(C28,'Coil to Slit'!$D:$H,5,FALSE),"")) -> 3.3669704 | I28: =IF(C28="","",IFERROR(VLOOKUP(LEFT(C28,LEN(C28)-2),'Coil Sheet at Plant'!$C:$J,8,FALSE),"")) -> 28.46 | J28: =IF(C28="","",SUMIF(C:C,C28,H:H)) -> 3.3669704 | K28: =IF(OR(I28="",J28=""),"",IF(J28>I28,"⚠ BUNDLES > BABY COIL","✔ OK")) -> ✔ OK | L28: =IF(#REF!="","",IF(COUNTIF(#REF!,#REF!)>1,"⚠ DUPLICATE","")) -> #REF!
A29: 46113 | B29: MS SHS One Helix IS 4923 YSt 210 Black 38x38x2.20x6000 | C29: HYD-0326-04-C | D29: 219 | E29: =IF(C29="","",IFERROR(VLOOKUP(C29,'Coil to Slit'!$D:$H,3,FALSE),"")) -> 0 | F29: =IF(C29="","",IFERROR(VLOOKUP(C29,'Coil to Slit'!$D:$H,4,FALSE),"")) -> 148 | G29: =IF(C29="","",IFERROR(VLOOKUP(C29,'Coil to Slit'!$D:$H,2,FALSE),"")) -> 2.2 | H29: =IF(OR(C29="",D29=""),"",IFERROR(VLOOKUP(C29,'Coil to Slit'!$D:$H,5,FALSE),"")) -> 3.3669704 | I29: =IF(C29="","",IFERROR(VLOOKUP(LEFT(C29,LEN(C29)-2),'Coil Sheet at Plant'!$C:$J,8,FALSE),"")) -> 28.46 | J29: =IF(C29="","",SUMIF(C:C,C29,H:H)) -> 3.3669704 | K29: =IF(OR(I29="",J29=""),"",IF(J29>I29,"⚠ BUNDLES > BABY COIL","✔ OK")) -> ✔ OK | L29: =IF(#REF!="","",IF(COUNTIF(#REF!,#REF!)>1,"⚠ DUPLICATE","")) -> #REF!
A30: 46113 | B30: MS SHS One Helix IS 4923 YSt 210 Black 38x38x2.20x6000 | C30: HYD-0326-04-D | D30: 219 | E30: =IF(C30="","",IFERROR(VLOOKUP(C30,'Coil to Slit'!$D:$H,3,FALSE),"")) -> 0 | F30: =IF(C30="","",IFERROR(VLOOKUP(C30,'Coil to Slit'!$D:$H,4,FALSE),"")) -> 148 | G30: =IF(C30="","",IFERROR(VLOOKUP(C30,'Coil to Slit'!$D:$H,2,FALSE),"")) -> 2.2 | H30: =IF(OR(C30="",D30=""),"",IFERROR(VLOOKUP(C30,'Coil to Slit'!$D:$H,5,FALSE),"")) -> 3.3669704 | I30: =IF(C30="","",IFERROR(VLOOKUP(LEFT(C30,LEN(C30)-2),'Coil Sheet at Plant'!$C:$J,8,FALSE),"")) -> 28.46 | J30: =IF(C30="","",SUMIF(C:C,C30,H:H)) -> 3.3669704 | K30: =IF(OR(I30="",J30=""),"",IF(J30>I30,"⚠ BUNDLES > BABY COIL","✔ OK")) -> ✔ OK | L30: =IF(#REF!="","",IF(COUNTIF(#REF!,#REF!)>1,"⚠ DUPLICATE","")) -> #REF!
A31: 46113 | B31: MS SHS One Helix IS 4923 YSt 210 Black 38x38x2.20x6000 | C31: HYD-0326-04-E | D31: 218 | E31: =IF(C31="","",IFERROR(VLOOKUP(C31,'Coil to Slit'!$D:$H,3,FALSE),"")) -> 0 | F31: =IF(C31="","",IFERROR(VLOOKUP(C31,'Coil to Slit'!$D:$H,4,FALSE),"")) -> 148 | G31: =IF(C31="","",IFERROR(VLOOKUP(C31,'Coil to Slit'!$D:$H,2,FALSE),"")) -> 2.2 | H31: =IF(OR(C31="",D31=""),"",IFERROR(VLOOKUP(C31,'Coil to Slit'!$D:$H,5,FALSE),"")) -> 3.3669704 | I31: =IF(C31="","",IFERROR(VLOOKUP(LEFT(C31,LEN(C31)-2),'Coil Sheet at Plant'!$C:$J,8,FALSE),"")) -> 28.46 | J31: =IF(C31="","",SUMIF(C:C,C31,H:H)) -> 3.3669704 | K31: =IF(OR(I31="",J31=""),"",IF(J31>I31,"⚠ BUNDLES > BABY COIL","✔ OK")) -> ✔ OK | L31: =IF(#REF!="","",IF(COUNTIF(#REF!,#REF!)>1,"⚠ DUPLICATE","")) -> #REF!
A32: 46118 | B32: MS SHS One Helix IS 4923 YSt 210 Black 50x50x2x6000 | C32: HYD-0426-07-A | D32: 157 | E32: =IF(C32="","",IFERROR(VLOOKUP(C32,'Coil to Slit'!$D:$H,3,FALSE),"")) | F32: =IF(C32="","",IFERROR(VLOOKUP(C32,'Coil to Slit'!$D:$H,4,FALSE),"")) -> 197 | G32: =IF(C32="","",IFERROR(VLOOKUP(C32,'Coil to Slit'!$D:$H,2,FALSE),"")) -> 2 | H32: =IF(OR(C32="",D32=""),"",IFERROR(VLOOKUP(C32,'Coil to Slit'!$D:$H,5,FALSE),"")) -> 3.0084165 | I32: =IF(C32="","",IFERROR(VLOOKUP(LEFT(C32,LEN(C32)-2),'Coil Sheet at Plant'!$C:$J,8,FALSE),"")) -> 14.08 | J32: =IF(C32="","",SUMIF(C:C,C32,H:H)) -> 3.0084165 | K32: =IF(OR(I32="",J32=""),"",IF(J32>I32,"⚠ BUNDLES > BABY COIL","✔ OK")) -> ✔ OK | L32: =IF(#REF!="","",IF(COUNTIF(#REF!,#REF!)>1,"⚠ DUPLICATE","")) -> #REF!
A33: 46118 | B33: MS SHS One Helix IS 4923 YSt 210 Black 50x50x2x6000 | C33: HYD-0426-07-B | D33: 157 | E33: =IF(C33="","",IFERROR(VLOOKUP(C33,'Coil to Slit'!$D:$H,3,FALSE),"")) | F33: =IF(C33="","",IFERROR(VLOOKUP(C33,'Coil to Slit'!$D:$H,4,FALSE),"")) -> 197 | G33: =IF(C33="","",IFERROR(VLOOKUP(C33,'Coil to Slit'!$D:$H,2,FALSE),"")) -> 2 | H33: =IF(OR(C33="",D33=""),"",IFERROR(VLOOKUP(C33,'Coil to Slit'!$D:$H,5,FALSE),"")) -> 3.0084165 | I33: =IF(C33="","",IFERROR(VLOOKUP(LEFT(C33,LEN(C33)-2),'Coil Sheet at Plant'!$C:$J,8,FALSE),"")) -> 14.08 | J33: =IF(C33="","",SUMIF(C:C,C33,H:H)) -> 3.0084165 | K33: =IF(OR(I33="",J33=""),"",IF(J33>I33,"⚠ BUNDLES > BABY COIL","✔ OK")) -> ✔ OK | L33: =IF(#REF!="","",IF(COUNTIF(#REF!,#REF!)>1,"⚠ DUPLICATE","")) -> #REF!
A34: 46118 | B34: MS SHS One Helix IS 4923 YSt 210 Black 50x50x2x6000 | C34: HYD-0426-07-C | D34: 158 | E34: =IF(C34="","",IFERROR(VLOOKUP(C34,'Coil to Slit'!$D:$H,3,FALSE),"")) | F34: =IF(C34="","",IFERROR(VLOOKUP(C34,'Coil to Slit'!$D:$H,4,FALSE),"")) -> 197 | G34: =IF(C34="","",IFERROR(VLOOKUP(C34,'Coil to Slit'!$D:$H,2,FALSE),"")) -> 2 | H34: =IF(OR(C34="",D34=""),"",IFERROR(VLOOKUP(C34,'Coil to Slit'!$D:$H,5,FALSE),"")) -> 3.0084165 | I34: =IF(C34="","",IFERROR(VLOOKUP(LEFT(C34,LEN(C34)-2),'Coil Sheet at Plant'!$C:$J,8,FALSE),"")) -> 14.08 | J34: =IF(C34="","",SUMIF(C:C,C34,H:H)) -> 3.0084165 | K34: =IF(OR(I34="",J34=""),"",IF(J34>I34,"⚠ BUNDLES > BABY COIL","✔ OK")) -> ✔ OK | L34: =IF(#REF!="","",IF(COUNTIF(#REF!,#REF!)>1,"⚠ DUPLICATE","")) -> #REF!
A35: 46118 | B35: MS SHS One Helix IS 4923 YSt 210 Black 50x50x2x6000 | C35: HYD-0426-05-A | D35: 165 | E35: =IF(C35="","",IFERROR(VLOOKUP(C35,'Coil to Slit'!$D:$H,3,FALSE),"")) | F35: =IF(C35="","",IFERROR(VLOOKUP(C35,'Coil to Slit'!$D:$H,4,FALSE),"")) -> 197 | G35: =IF(C35="","",IFERROR(VLOOKUP(C35,'Coil to Slit'!$D:$H,2,FALSE),"")) -> 2 | H35: =IF(OR(C35="",D35=""),"",IFERROR(VLOOKUP(C35,'Coil to Slit'!$D:$H,5,FALSE),"")) -> 3.1005203 | I35: =IF(C35="","",IFERROR(VLOOKUP(LEFT(C35,LEN(C35)-2),'Coil Sheet at Plant'!$C:$J,8,FALSE),"")) -> 19.815 | J35: =IF(C35="","",SUMIF(C:C,C35,H:H)) -> 3.1005203 | K35: =IF(OR(I35="",J35=""),"",IF(J35>I35,"⚠ BUNDLES > BABY COIL","✔ OK")) -> ✔ OK | L35: =IF(#REF!="","",IF(COUNTIF(#REF!,#REF!)>1,"⚠ DUPLICATE","")) -> #REF!
... A38: 46118 | B38: MS SHS One Helix IS 4923 YSt 210 Black 50x50x2x6000 | C38: HYD-0426-05-D | D38: 95 | E38: =IF(C38="","",IFERROR(VLOOKUP(C38,'Coil to Slit'!$D:$H,3,FALSE),"")) | F38: =IF(C38="","",IFERROR(VLOOKUP(C38,'Coil to Slit'!$D:$H,4,FALSE),"")) -> 197 | G38: =IF(C38="","",IFERROR(VLOOKUP(C38,'Coil to Slit'!$D:$H,2,FALSE),"")) -> 2 | H38: =IF(OR(C38="",D38=""),"",IFERROR(VLOOKUP(C38,'Coil to Slit'!$D:$H,5,FALSE),"")) -> 3.1005203 | I38: =IF(C38="","",IFERROR(VLOOKUP(LEFT(C38,LEN(C38)-2),'Coil Sheet at Plant'!$C:$J,8,FALSE),"")) -> 19.815 | J38: =IF(C38="","",SUMIF(C:C,C38,H:H)) -> 4.4158925 | K38: =IF(OR(I38="",J38=""),"",IF(J38>I38,"⚠ BUNDLES > BABY COIL","✔ OK")) -> ✔ OK | L38: =IF(#REF!="","",IF(COUNTIF(#REF!,#REF!)>1,"⚠ DUPLICATE","")) -> #REF!
A39: 46119 | B39: MS SHS One Helix IS 4923 YSt 210 Black 50x50x2x6000 | C39: HYD-0426-05-D | D39: 70 | E39: =IF(C39="","",IFERROR(VLOOKUP(C39,'Coil to Slit'!$D:$F,3,FALSE),"")) | F39: =IF(C39="","",IFERROR(VLOOKUP(C39,'Coil to Slit'!$D:$G,4,FALSE),"")) -> 197 | G39: =IF(C39="","",IFERROR(VLOOKUP(C39,'Coil to Slit'!$D:$E,2,FALSE),"")) -> 2 | H39: =IF(OR(C39="",D39="",I39=""),"",I39*D39/SUMIF(C:C,C39,D:D)) -> 1.3153722 | I39: =IF(C39="","",IFERROR(VLOOKUP(C39,'Coil to Slit'!$D:$H,5,FALSE),"")) -> 3.1005203 | J39: =IF(C39="","",SUMIF(C:C,C39,H:H)) -> 4.4158925 | K39: =IF(OR(I39="",J39=""),"",IF(J39>I39,"⚠ BUNDLES > BABY COIL","✔ OK")) -> ⚠ BUNDLES > BABY COIL | L39: =IF(#REF!="","",IF(COUNTIF(#REF!,#REF!)>1,"⚠ DUPLICATE","")) -> #REF!
A40: 46119 | B40: MS SHS One Helix IS 4923 YSt 210 Black 50x50x2x6000 | C40: HYD-0426-05-E | D40: 166 | E40: =IF(C40="","",IFERROR(VLOOKUP(C40,'Coil to Slit'!$D:$F,3,FALSE),"")) | F40: =IF(C40="","",IFERROR(VLOOKUP(C40,'Coil to Slit'!$D:$G,4,FALSE),"")) -> 197 | G40: =IF(C40="","",IFERROR(VLOOKUP(C40,'Coil to Slit'!$D:$E,2,FALSE),"")) -> 2 | H40: =IF(OR(C40="",D40="",I40=""),"",I40*D40/SUMIF(C:C,C40,D:D)) -> 3.1005203 | I40: =IF(C40="","",IFERROR(VLOOKUP(C40,'Coil to Slit'!$D:$H,5,FALSE),"")) -> 3.1005203 | J40: =IF(C40="","",SUMIF(C:C,C40,H:H)) -> 3.1005203 | K40: =IF(OR(I40="",J40=""),"",IF(J40>I40,"⚠ BUNDLES > BABY COIL","✔ OK")) -> ✔ OK | L40: =IF(#REF!="","",IF(COUNTIF(#REF!,#REF!)>1,"⚠ DUPLICATE","")) -> #REF!
A41: 46119 | B41: MS SHS One Helix IS 4923 YSt 210 Black 50x50x2x6000 | C41: HYD-0426-05-F | D41: 166 | E41: =IF(C41="","",IFERROR(VLOOKUP(C41,'Coil to Slit'!$D:$F,3,FALSE),"")) | F41: =IF(C41="","",IFERROR(VLOOKUP(C41,'Coil to Slit'!$D:$G,4,FALSE),"")) -> 197 | G41: =IF(C41="","",IFERROR(VLOOKUP(C41,'Coil to Slit'!$D:$E,2,FALSE),"")) -> 2 | H41: =IF(OR(C41="",D41="",I41=""),"",I41*D41/SUMIF(C:C,C41,D:D)) -> 3.1005203 | I41: =IF(C41="","",IFERROR(VLOOKUP(C41,'Coil to Slit'!$D:$H,5,FALSE),"")) -> 3.1005203 | J41: =IF(C41="","",SUMIF(C:C,C41,H:H)) -> 3.1005203 | K41: =IF(OR(I41="",J41=""),"",IF(J41>I41,"⚠ BUNDLES > BABY COIL","✔ OK")) -> ✔ OK | L41: =IF(#REF!="","",IF(COUNTIF(#REF!,#REF!)>1,"⚠ DUPLICATE","")) -> #REF!
A42: 46119 | B42: MS SHS One Helix IS 4923 YSt 210 Black 50x50x2x6000 | C42: HYD-0426-06-A | D42: 185 | E42: =IF(C42="","",IFERROR(VLOOKUP(C42,'Coil to Slit'!$D:$F,3,FALSE),"")) | F42: =IF(C42="","",IFERROR(VLOOKUP(C42,'Coil to Slit'!$D:$G,4,FALSE),"")) -> 197 | G42: =IF(C42="","",IFERROR(VLOOKUP(C42,'Coil to Slit'!$D:$E,2,FALSE),"")) -> 2 | H42: =IF(OR(C42="",D42="",I42=""),"",I42*D42/SUMIF(C:C,C42,D:D)) -> 3.4627562 | I42: =IF(C42="","",IFERROR(VLOOKUP(C42,'Coil to Slit'!$D:$H,5,FALSE),"")) -> 3.4627562 | J42: =IF(C42="","",SUMIF(C:C,C42,H:H)) -> 3.4627562 | K42: =IF(OR(I42="",J42=""),"",IF(J42>I42,"⚠ BUNDLES > BABY COIL","✔ OK")) -> ✔ OK | L42: =IF(#REF!="","",IF(COUNTIF(#REF!,#REF!)>1,"⚠ DUPLICATE","")) -> #REF!
A43: 46119 | B43: MS SHS One Helix IS 4923 YSt 210 Black 50x50x2x6000 | C43: HYD-0426-06-B | D43: 185 | E43: =IF(C43="","",IFERROR(VLOOKUP(C43,'Coil to Slit'!$D:$F,3,FALSE),"")) | F43: =IF(C43="","",IFERROR(VLOOKUP(C43,'Coil to Slit'!$D:$G,4,FALSE),"")) -> 197 | G43: =IF(C43="","",IFERROR(VLOOKUP(C43,'Coil to Slit'!$D:$E,2,FALSE),"")) -> 2 | H43: =IF(OR(C43="",D43="",I43=""),"",I43*D43/SUMIF(C:C,C43,D:D)) -> 3.4627562 | I43: =IF(C43="","",IFERROR(VLOOKUP(C43,'Coil to Slit'!$D:$H,5,FALSE),"")) -> 3.4627562 | J43: =IF(C43="","",SUMIF(C:C,C43,H:H)) -> 3.4627562 | K43: =IF(OR(I43="",J43=""),"",IF(J43>I43,"⚠ BUNDLES > BABY COIL","✔ OK")) -> ✔ OK | L43: =IF(#REF!="","",IF(COUNTIF(#REF!,#REF!)>1,"⚠ DUPLICATE","")) -> #REF!
A44: 46119 | B44: MS SHS One Helix IS 4923 YSt 210 Black 50x50x2x6000 | C44: HYD-0426-06-C | D44: 185 | E44: =IF(C44="","",IFERROR(VLOOKUP(C44,'Coil to Slit'!$D:$F,3,FALSE),"")) | F44: =IF(C44="","",IFERROR(VLOOKUP(C44,'Coil to Slit'!$D:$G,4,FALSE),"")) -> 197 | G44: =IF(C44="","",IFERROR(VLOOKUP(C44,'Coil to Slit'!$D:$E,2,FALSE),"")) -> 2 | H44: =IF(OR(C44="",D44="",I44=""),"",I44*D44/SUMIF(C:C,C44,D:D)) -> 3.4627562 | I44: =IF(C44="","",IFERROR(VLOOKUP(C44,'Coil to Slit'!$D:$H,5,FALSE),"")) -> 3.4627562 | J44: =IF(C44="","",SUMIF(C:C,C44,H:H)) -> 3.4627562 | K44: =IF(OR(I44="",J44=""),"",IF(J44>I44,"⚠ BUNDLES > BABY COIL","✔ OK")) -> ✔ OK | L44: =IF(#REF!="","",IF(COUNTIF(#REF!,#REF!)>1,"⚠ DUPLICATE","")) -> #REF!
A45: 46119 | B45: MS SHS One Helix IS 4923 YSt 210 Black 50x50x2x6000 | C45: HYD-0426-06-D | D45: 185 | E45: =IF(C45="","",IFERROR(VLOOKUP(C45,'Coil to Slit'!$D:$F,3,FALSE),"")) | F45: =IF(C45="","",IFERROR(VLOOKUP(C45,'Coil to Slit'!$D:$G,4,FALSE),"")) -> 197 | G45: =IF(C45="","",IFERROR(VLOOKUP(C45,'Coil to Slit'!$D:$E,2,FALSE),"")) -> 2 | H45: =IF(OR(C45="",D45="",I45=""),"",I45*D45/SUMIF(C:C,C45,D:D)) -> 3.4627562 | I45: =IF(C45="","",IFERROR(VLOOKUP(C45,'Coil to Slit'!$D:$H,5,FALSE),"")) -> 3.4627562 | J45: =IF(C45="","",SUMIF(C:C,C45,H:H)) -> 3.4627562 | K45: =IF(OR(I45="",J45=""),"",IF(J45>I45,"⚠ BUNDLES > BABY COIL","✔ OK")) -> ✔ OK | L45: =IF(#REF!="","",IF(COUNTIF(#REF!,#REF!)>1,"⚠ DUPLICATE","")) -> #REF!
A46: 46119 | B46: MS SHS One Helix IS 4923 YSt 210 Black 50x50x2x6000 | C46: HYD-0426-06-E | D46: 185 | E46: =IF(C46="","",IFERROR(VLOOKUP(C46,'Coil to Slit'!$D:$F,3,FALSE),"")) | F46: =IF(C46="","",IFERROR(VLOOKUP(C46,'Coil to Slit'!$D:$G,4,FALSE),"")) -> 197 | G46: =IF(C46="","",IFERROR(VLOOKUP(C46,'Coil to Slit'!$D:$E,2,FALSE),"")) -> 2 | H46: =IF(OR(C46="",D46="",I46=""),"",I46*D46/SUMIF(C:C,C46,D:D)) -> 3.4627562 | I46: =IF(C46="","",IFERROR(VLOOKUP(C46,'Coil to Slit'!$D:$H,5,FALSE),"")) -> 3.4627562 | J46: =IF(C46="","",SUMIF(C:C,C46,H:H)) -> 3.4627562 | K46: =IF(OR(I46="",J46=""),"",IF(J46>I46,"⚠ BUNDLES > BABY COIL","✔ OK")) -> ✔ OK | L46: =IF(#REF!="","",IF(COUNTIF(#REF!,#REF!)>1,"⚠ DUPLICATE","")) -> #REF!
A47: 46119 | B47: MS SHS One Helix IS 4923 YSt 210 Black 50x50x2x6000 | C47: HYD-0426-06-F | D47: 185 | E47: =IF(C47="","",IFERROR(VLOOKUP(C47,'Coil to Slit'!$D:$F,3,FALSE),"")) | F47: =IF(C47="","",IFERROR(VLOOKUP(C47,'Coil to Slit'!$D:$G,4,FALSE),"")) -> 197 | G47: =IF(C47="","",IFERROR(VLOOKUP(C47,'Coil to Slit'!$D:$E,2,FALSE),"")) -> 2 | H47: =IF(OR(C47="",D47="",I47=""),"",I47*D47/SUMIF(C:C,C47,D:D)) -> 3.4627562 | I47: =IF(C47="","",IFERROR(VLOOKUP(C47,'Coil to Slit'!$D:$H,5,FALSE),"")) -> 3.4627562 | J47: =IF(C47="","",SUMIF(C:C,C47,H:H)) -> 3.4627562 | K47: =IF(OR(I47="",J47=""),"",IF(J47>I47,"⚠ BUNDLES > BABY COIL","✔ OK")) -> ✔ OK | L47: =IF(#REF!="","",IF(COUNTIF(#REF!,#REF!)>1,"⚠ DUPLICATE","")) -> #REF!
E48: =IF(C48="","",IFERROR(VLOOKUP(C48,'Coil to Slit'!$D:$F,3,FALSE),"")) | F48: =IF(C48="","",IFERROR(VLOOKUP(C48,'Coil to Slit'!$D:$G,4,FALSE),"")) | G48: =IF(C48="","",IFERROR(VLOOKUP(C48,'Coil to Slit'!$D:$E,2,FALSE),"")) | H48: =IF(OR(C48="",D48="",I48=""),"",I48*D48/SUMIF(C:C,C48,D:D)) | I48: =IF(C48="","",IFERROR(VLOOKUP(C48,'Coil to Slit'!$D:$H,5,FALSE),"")) | J48: =IF(C48="","",SUMIF(C:C,C48,H:H)) | K48: =IF(OR(I48="",J48=""),"",IF(J48>I48,"⚠ BUNDLES > BABY COIL","✔ OK")) | L48: =IF(#REF!="","",IF(COUNTIF(#REF!,#REF!)>1,"⚠ DUPLICATE","")) -> #REF!
E49: =IF(C49="","",IFERROR(VLOOKUP(C49,'Coil to Slit'!$D:$F,3,FALSE),"")) | F49: =IF(C49="","",IFERROR(VLOOKUP(C49,'Coil to Slit'!$D:$G,4,FALSE),"")) | G49: =IF(C49="","",IFERROR(VLOOKUP(C49,'Coil to Slit'!$D:$E,2,FALSE),"")) | H49: =IF(OR(C49="",D49="",I49=""),"",I49*D49/SUMIF(C:C,C49,D:D)) | I49: =IF(C49="","",IFERROR(VLOOKUP(C49,'Coil to Slit'!$D:$H,5,FALSE),"")) | J49: =IF(C49="","",SUMIF(C:C,C49,H:H)) | K49: =IF(OR(I49="",J49=""),"",IF(J49>I49,"⚠ BUNDLES > BABY COIL","✔ OK")) | L49: =IF(#REF!="","",IF(COUNTIF(#REF!,#REF!)>1,"⚠ DUPLICATE","")) -> #REF!
E50: =IF(C50="","",IFERROR(VLOOKUP(C50,'Coil to Slit'!$D:$F,3,FALSE),"")) | F50: =IF(C50="","",IFERROR(VLOOKUP(C50,'Coil to Slit'!$D:$G,4,FALSE),"")) | G50: =IF(C50="","",IFERROR(VLOOKUP(C50,'Coil to Slit'!$D:$E,2,FALSE),"")) | H50: =IF(OR(C50="",D50="",I50=""),"",I50*D50/SUMIF(C:C,C50,D:D)) | I50: =IF(C50="","",IFERROR(VLOOKUP(C50,'Coil to Slit'!$D:$H,5,FALSE),"")) | J50: =IF(C50="","",SUMIF(C:C,C50,H:H)) | K50: =IF(OR(I50="",J50=""),"",IF(J50>I50,"⚠ BUNDLES > BABY COIL","✔ OK")) | L50: =IF(#REF!="","",IF(COUNTIF(#REF!,#REF!)>1,"⚠ DUPLICATE","")) -> #REF!
E51: =IF(C51="","",IFERROR(VLOOKUP(C51,'Coil to Slit'!$D:$F,3,FALSE),"")) | F51: =IF(C51="","",IFERROR(VLOOKUP(C51,'Coil to Slit'!$D:$G,4,FALSE),"")) | G51: =IF(C51="","",IFERROR(VLOOKUP(C51,'Coil to Slit'!$D:$E,2,FALSE),"")) | H51: =IF(OR(C51="",D51="",I51=""),"",I51*D51/SUMIF(C:C,C51,D:D)) | I51: =IF(C51="","",IFERROR(VLOOKUP(C51,'Coil to Slit'!$D:$H,5,FALSE),"")) | J51: =IF(C51="","",SUMIF(C:C,C51,H:H)) | K51: =IF(OR(I51="",J51=""),"",IF(J51>I51,"⚠ BUNDLES > BABY COIL","✔ OK")) | L51: =IF(#REF!="","",IF(COUNTIF(#REF!,#REF!)>1,"⚠ DUPLICATE","")) -> #REF!
E52: =IF(C52="","",IFERROR(VLOOKUP(C52,'Coil to Slit'!$D:$F,3,FALSE),"")) | F52: =IF(C52="","",IFERROR(VLOOKUP(C52,'Coil to Slit'!$D:$G,4,FALSE),"")) | G52: =IF(C52="","",IFERROR(VLOOKUP(C52,'Coil to Slit'!$D:$E,2,FALSE),"")) | H52: =IF(OR(C52="",D52="",I52=""),"",I52*D52/SUMIF(C:C,C52,D:D)) | I52: =IF(C52="","",IFERROR(VLOOKUP(C52,'Coil to Slit'!$D:$H,5,FALSE),"")) | J52: =IF(C52="","",SUMIF(C:C,C52,H:H)) | K52: =IF(OR(I52="",J52=""),"",IF(J52>I52,"⚠ BUNDLES > BABY COIL","✔ OK")) | L52: =IF(#REF!="","",IF(COUNTIF(#REF!,#REF!)>1,"⚠ DUPLICATE","")) -> #REF!
E53: =IF(C53="","",IFERROR(VLOOKUP(C53,'Coil to Slit'!$D:$F,3,FALSE),"")) | F53: =IF(C53="","",IFERROR(VLOOKUP(C53,'Coil to Slit'!$D:$G,4,FALSE),"")) | G53: =IF(C53="","",IFERROR(VLOOKUP(C53,'Coil to Slit'!$D:$E,2,FALSE),"")) | H53: =IF(OR(C53="",D53="",I53=""),"",I53*D53/SUMIF(C:C,C53,D:D)) | I53: =IF(C53="","",IFERROR(VLOOKUP(C53,'Coil to Slit'!$D:$H,5,FALSE),"")) | J53: =IF(C53="","",SUMIF(C:C,C53,H:H)) | K53: =IF(OR(I53="",J53=""),"",IF(J53>I53,"⚠ BUNDLES > BABY COIL","✔ OK")) | L53: =IF(#REF!="","",IF(COUNTIF(#REF!,#REF!)>1,"⚠ DUPLICATE","")) -> #REF!
E54: =IF(C54="","",IFERROR(VLOOKUP(C54,'Coil to Slit'!$D:$F,3,FALSE),"")) | F54: =IF(C54="","",IFERROR(VLOOKUP(C54,'Coil to Slit'!$D:$G,4,FALSE),"")) | G54: =IF(C54="","",IFERROR(VLOOKUP(C54,'Coil to Slit'!$D:$E,2,FALSE),"")) | H54: =IF(OR(C54="",D54="",I54=""),"",I54*D54/SUMIF(C:C,C54,D:D)) | I54: =IF(C54="","",IFERROR(VLOOKUP(C54,'Coil to Slit'!$D:$H,5,FALSE),"")) | J54: =IF(C54="","",SUMIF(C:C,C54,H:H)) | K54: =IF(OR(I54="",J54=""),"",IF(J54>I54,"⚠ BUNDLES > BABY COIL","✔ OK")) | L54: =IF(#REF!="","",IF(COUNTIF(#REF!,#REF!)>1,"⚠ DUPLICATE","")) -> #REF!
E55: =IF(C55="","",IFERROR(VLOOKUP(C55,'Coil to Slit'!$D:$F,3,FALSE),"")) | F55: =IF(C55="","",IFERROR(VLOOKUP(C55,'Coil to Slit'!$D:$G,4,FALSE),"")) | G55: =IF(C55="","",IFERROR(VLOOKUP(C55,'Coil to Slit'!$D:$E,2,FALSE),"")) | H55: =IF(OR(C55="",D55="",I55=""),"",I55*D55/SUMIF(C:C,C55,D:D)) | I55: =IF(C55="","",IFERROR(VLOOKUP(C55,'Coil to Slit'!$D:$H,5,FALSE),"")) | J55: =IF(C55="","",SUMIF(C:C,C55,H:H)) | K55: =IF(OR(I55="",J55=""),"",IF(J55>I55,"⚠ BUNDLES > BABY COIL","✔ OK")) | L55: =IF(#REF!="","",IF(COUNTIF(#REF!,#REF!)>1,"⚠ DUPLICATE","")) -> #REF!
E56: =IF(C56="","",IFERROR(VLOOKUP(C56,'Coil to Slit'!$D:$F,3,FALSE),"")) | F56: =IF(C56="","",IFERROR(VLOOKUP(C56,'Coil to Slit'!$D:$G,4,FALSE),"")) | G56: =IF(C56="","",IFERROR(VLOOKUP(C56,'Coil to Slit'!$D:$E,2,FALSE),"")) | H56: =IF(OR(C56="",D56="",I56=""),"",I56*D56/SUMIF(C:C,C56,D:D)) | I56: =IF(C56="","",IFERROR(VLOOKUP(C56,'Coil to Slit'!$D:$H,5,FALSE),"")) | J56: =IF(C56="","",SUMIF(C:C,C56,H:H)) | K56: =IF(OR(I56="",J56=""),"",IF(J56>I56,"⚠ BUNDLES > BABY COIL","✔ OK")) | L56: =IF(#REF!="","",IF(COUNTIF(#REF!,#REF!)>1,"⚠ DUPLICATE","")) -> #REF!
E57: =IF(C57="","",IFERROR(VLOOKUP(C57,'Coil to Slit'!$D:$F,3,FALSE),"")) | F57: =IF(C57="","",IFERROR(VLOOKUP(C57,'Coil to Slit'!$D:$G,4,FALSE),"")) | G57: =IF(C57="","",IFERROR(VLOOKUP(C57,'Coil to Slit'!$D:$E,2,FALSE),"")) | H57: =IF(OR(C57="",D57="",I57=""),"",I57*D57/SUMIF(C:C,C57,D:D)) | I57: =IF(C57="","",IFERROR(VLOOKUP(C57,'Coil to Slit'!$D:$H,5,FALSE),"")) | J57: =IF(C57="","",SUMIF(C:C,C57,H:H)) | K57: =IF(OR(I57="",J57=""),"",IF(J57>I57,"⚠ BUNDLES > BABY COIL","✔ OK")) | L57: =IF(#REF!="","",IF(COUNTIF(#REF!,#REF!)>1,"⚠ DUPLICATE","")) -> #REF!
E58: =IF(C58="","",IFERROR(VLOOKUP(C58,'Coil to Slit'!$D:$F,3,FALSE),"")) | F58: =IF(C58="","",IFERROR(VLOOKUP(C58,'Coil to Slit'!$D:$G,4,FALSE),"")) | G58: =IF(C58="","",IFERROR(VLOOKUP(C58,'Coil to Slit'!$D:$E,2,FALSE),"")) | H58: =IF(OR(C58="",D58="",I58=""),"",I58*D58/SUMIF(C:C,C58,D:D)) | I58: =IF(C58="","",IFERROR(VLOOKUP(C58,'Coil to Slit'!$D:$H,5,FALSE),"")) | J58: =IF(C58="","",SUMIF(C:C,C58,H:H)) | K58: =IF(OR(I58="",J58=""),"",IF(J58>I58,"⚠ BUNDLES > BABY COIL","✔ OK")) | L58: =IF(#REF!="","",IF(COUNTIF(#REF!,#REF!)>1,"⚠ DUPLICATE","")) -> #REF!
E59: =IF(C59="","",IFERROR(VLOOKUP(C59,'Coil to Slit'!$D:$F,3,FALSE),"")) | F59: =IF(C59="","",IFERROR(VLOOKUP(C59,'Coil to Slit'!$D:$G,4,FALSE),"")) | G59: =IF(C59="","",IFERROR(VLOOKUP(C59,'Coil to Slit'!$D:$E,2,FALSE),"")) | H59: =IF(OR(C59="",D59="",I59=""),"",I59*D59/SUMIF(C:C,C59,D:D)) | I59: =IF(C59="","",IFERROR(VLOOKUP(C59,'Coil to Slit'!$D:$H,5,FALSE),"")) | J59: =IF(C59="","",SUMIF(C:C,C59,H:H)) | K59: =IF(OR(I59="",J59=""),"",IF(J59>I59,"⚠ BUNDLES > BABY COIL","✔ OK")) | L59: =IF(#REF!="","",IF(COUNTIF(#REF!,#REF!)>1,"⚠ DUPLICATE","")) -> #REF!
... E100: =IF(C100="","",IFERROR(VLOOKUP(C100,'Coil to Slit'!$D:$F,3,FALSE),"")) | F100: =IF(C100="","",IFERROR(VLOOKUP(C100,'Coil to Slit'!$D:$G,4,FALSE),"")) | G100: =IF(C100="","",IFERROR(VLOOKUP(C100,'Coil to Slit'!$D:$E,2,FALSE),"")) | H100: =IF(OR(C100="",D100="",I100=""),"",I100*D100/SUMIF(C:C,C100,D:D)) | I100: =IF(C100="","",IFERROR(VLOOKUP(C100,'Coil to Slit'!$D:$H,5,FALSE),"")) | J100: =IF(C100="","",SUMIF(C:C,C100,H:H)) | K100: =IF(OR(I100="",J100=""),"",IF(J100>I100,"⚠ BUNDLES > BABY COIL","✔ OK")) | L100: =IF(#REF!="","",IF(COUNTIF(#REF!,#REF!)>1,"⚠ DUPLICATE","")) -> #REF!

Sheet Bundle Formation
A1: 🔵 Manual Entry ↓ | K1: 🟡 Validation Helpers ↓
A2: Date of Entry | B2: Baby Coil ID | C2: SKU Code | D2: No. of tube pieces left | E2: No. of Tube Pieces | F2: Bundle No. | G2: Bundle ID | H2: Remaining Tube Pieces | I2: Weight per Piece (T) | J2: Total Bundle Weight (T) | K2: Baby Coil ID Validation | L2: Duplicate Row Check | M2: Pieces vs FG Conversion
A3: 46112 | B3: HYD-0326-01-A | C3: MS SHS One Helix IS 4923 YSt 210 Black 38x38x2.80x6000 | D3: =IF(OR(B3="",E3=""),"",IFERROR(INDEX('Slit to Tube Conversion'!$D:$D,MATCH(B3,'Slit to Tube Conversion'!$C:$C,0))-SUMIFS($E$3:E3,$B$3:B3,B3),"")) -> 14 | E3: 110 | F3: 1 | G3: =IF(F3="","","BND-"&F3) -> BND-1 | I3: =IF(OR(B3="",C3=""),"",IFERROR(INDEX('Slit to Tube Conversion'!$H:$H,MATCH(B3,'Slit to Tube Conversion'!$C:$C,0))/INDEX('Slit to Tube Conversion'!$D:$D,MATCH(B3,'Slit to Tube Conversion'!$C:$C,0)),"")) -> 0.019675408 | J3: =IF(OR(B3="",E3="",I3=""),"",I3*E3) -> 2.1642949 | K3: =IF(B3="","",IF(COUNTIF('Coil to Slit'!$D:$D,B3)>0,"✔ Valid","⚠ Not in Coil to Slit")) -> ✔ Valid | L3: =IF(OR(G3="",B3=""),"",IF(COUNTIFS($G$3:G3,G3,$B$3:B3,B3)>1,"⚠ DUPLICATE","")) | M3: =IF(OR(B3="",E3=""),"",IFERROR(IF(E3>INDEX('Slit to Tube Conversion'!$D:$D,MATCH(B3,'Slit to Tube Conversion'!$C:$C,0)),"⚠ EXCEEDS FG ("&INDEX('Slit to Tube Conversion'!$D:$D,MATCH(B3,'Slit to Tube Conversion'!$C:$C,0))&")","✔ OK"),"Not in FG Conversion")) -> ✔ OK
A4: 46112 | B4: HYD-0326-01-A | C4: MS SHS One Helix IS 4923 YSt 210 Black 38x38x2.80x6000 | D4: =IF(OR(B4="",E4=""),"",IFERROR(INDEX('Slit to Tube Conversion'!$D:$D,MATCH(B4,'Slit to Tube Conversion'!$C:$C,0))-SUMIFS($E$3:E4,$B$3:B4,B4),"")) -> 0 | E4: 14 | F4: =IF(B4="","",F3+1) -> 2 | G4: =IF(F4="","","BND-"&F4) -> BND-2 | I4: =IF(OR(B4="",C4=""),"",IFERROR(INDEX('Slit to Tube Conversion'!$H:$H,MATCH(B4,'Slit to Tube Conversion'!$C:$C,0))/INDEX('Slit to Tube Conversion'!$D:$D,MATCH(B4,'Slit to Tube Conversion'!$C:$C,0)),"")) -> 0.019675408 | J4: =IF(OR(B4="",E4="",I4=""),"",I4*E4) -> 0.27545571 | K4: =IF(B4="","",IF(COUNTIF('Coil to Slit'!$D:$D,B4)>0,"✔ Valid","⚠ Not in Coil to Slit")) -> ✔ Valid | L4: =IF(OR(G4="",B4=""),"",IF(COUNTIFS($G$3:G4,G4,$B$3:B4,B4)>1,"⚠ DUPLICATE","")) | M4: =IF(OR(B4="",E4=""),"",IFERROR(IF(E4>INDEX('Slit to Tube Conversion'!$D:$D,MATCH(B4,'Slit to Tube Conversion'!$C:$C,0)),"⚠ EXCEEDS FG ("&INDEX('Slit to Tube Conversion'!$D:$D,MATCH(B4,'Slit to Tube Conversion'!$C:$C,0))&")","✔ OK"),"Not in FG Conversion")) -> ✔ OK
A5: 46112 | B5: HYD-0326-01-B | C5: MS SHS One Helix IS 4923 YSt 210 Black 38x38x2.80x6000 | D5: =IF(OR(B5="",E5=""),"",IFERROR(INDEX('Slit to Tube Conversion'!$D:$D,MATCH(B5,'Slit to Tube Conversion'!$C:$C,0))-SUMIFS($E$3:E5,$B$3:B5,B5),"")) -> 28 | E5: 96 | F5: 2 | G5: =IF(F5="","","BND-"&F5) -> BND-2 | I5: =IF(OR(B5="",C5=""),"",IFERROR(INDEX('Slit to Tube Conversion'!$H:$H,MATCH(B5,'Slit to Tube Conversion'!$C:$C,0))/INDEX('Slit to Tube Conversion'!$D:$D,MATCH(B5,'Slit to Tube Conversion'!$C:$C,0)),"")) -> 0.019675408 | J5: =IF(OR(B5="",E5="",I5=""),"",I5*E5) -> 1.8888392 | K5: =IF(B5="","",IF(COUNTIF('Coil to Slit'!$D:$D,B5)>0,"✔ Valid","⚠ Not in Coil to Slit")) -> ✔ Valid | L5: =IF(OR(G5="",B5=""),"",IF(COUNTIFS($G$3:G5,G5,$B$3:B5,B5)>1,"⚠ DUPLICATE","")) | M5: =IF(OR(B5="",E5=""),"",IFERROR(IF(E5>INDEX('Slit to Tube Conversion'!$D:$D,MATCH(B5,'Slit to Tube Conversion'!$C:$C,0)),"⚠ EXCEEDS FG ("&INDEX('Slit to Tube Conversion'!$D:$D,MATCH(B5,'Slit to Tube Conversion'!$C:$C,0))&")","✔ OK"),"Not in FG Conversion")) -> ✔ OK
A6: 46112 | B6: HYD-0326-01-B | C6: MS SHS One Helix IS 4923 YSt 210 Black 38x38x2.80x6000 | D6: =IF(OR(B6="",E6=""),"",IFERROR(INDEX('Slit to Tube Conversion'!$D:$D,MATCH(B6,'Slit to Tube Conversion'!$C:$C,0))-SUMIFS($E$3:E6,$B$3:B6,B6),"")) -> 0 | E6: 28 | F6: 3 | G6: =IF(F6="","","BND-"&F6) -> BND-3 | I6: =IF(OR(B6="",C6=""),"",IFERROR(INDEX('Slit to Tube Conversion'!$H:$H,MATCH(B6,'Slit to Tube Conversion'!$C:$C,0))/INDEX('Slit to Tube Conversion'!$D:$D,MATCH(B6,'Slit to Tube Conversion'!$C:$C,0)),"")) -> 0.019675408 | J6: =IF(OR(B6="",E6="",I6=""),"",I6*E6) -> 0.55091143 | K6: =IF(B6="","",IF(COUNTIF('Coil to Slit'!$D:$D,B6)>0,"✔ Valid","⚠ Not in Coil to Slit")) -> ✔ Valid | L6: =IF(OR(G6="",B6=""),"",IF(COUNTIFS($G$3:G6,G6,$B$3:B6,B6)>1,"⚠ DUPLICATE","")) | M6: =IF(OR(B6="",E6=""),"",IFERROR(IF(E6>INDEX('Slit to Tube Conversion'!$D:$D,MATCH(B6,'Slit to Tube Conversion'!$C:$C,0)),"⚠ EXCEEDS FG ("&INDEX('Slit to Tube Conversion'!$D:$D,MATCH(B6,'Slit to Tube Conversion'!$C:$C,0))&")","✔ OK"),"Not in FG Conversion")) -> ✔ OK
A7: 46112 | B7: HYD-0326-01-C | C7: MS SHS One Helix IS 4923 YSt 210 Black 38x38x2.80x6000 | D7: =IF(OR(B7="",E7=""),"",IFERROR(INDEX('Slit to Tube Conversion'!$D:$D,MATCH(B7,'Slit to Tube Conversion'!$C:$C,0))-SUMIFS($E$3:E7,$B$3:B7,B7),"")) -> 44 | E7: 82 | F7: 3 | G7: =IF(F7="","","BND-"&F7) -> BND-3 | I7: =IF(OR(B7="",C7=""),"",IFERROR(INDEX('Slit to Tube Conversion'!$H:$H,MATCH(B7,'Slit to Tube Conversion'!$C:$C,0))/INDEX('Slit to Tube Conversion'!$D:$D,MATCH(B7,'Slit to Tube Conversion'!$C:$C,0)),"")) -> 0.0193631 | J7: =IF(OR(B7="",E7="",I7=""),"",I7*E7) -> 1.5877742 | K7: =IF(B7="","",IF(COUNTIF('Coil to Slit'!$D:$D,B7)>0,"✔ Valid","⚠ Not in Coil to Slit")) -> ✔ Valid | L7: =IF(OR(G7="",B7=""),"",IF(COUNTIFS($G$3:G7,G7,$B$3:B7,B7)>1,"⚠ DUPLICATE","")) | M7: =IF(OR(B7="",E7=""),"",IFERROR(IF(E7>INDEX('Slit to Tube Conversion'!$D:$D,MATCH(B7,'Slit to Tube Conversion'!$C:$C,0)),"⚠ EXCEEDS FG ("&INDEX('Slit to Tube Conversion'!$D:$D,MATCH(B7,'Slit to Tube Conversion'!$C:$C,0))&")","✔ OK"),"Not in FG Conversion")) -> ✔ OK
A8: 46112 | B8: HYD-0326-01-C | C8: MS SHS One Helix IS 4923 YSt 210 Black 38x38x2.80x6000 | D8: =IF(OR(B8="",E8=""),"",IFERROR(INDEX('Slit to Tube Conversion'!$D:$D,MATCH(B8,'Slit to Tube Conversion'!$C:$C,0))-SUMIFS($E$3:E8,$B$3:B8,B8),"")) -> 0 | E8: 44 | F8: =IF(B8="","",F7+1) -> 4 | G8: =IF(F8="","","BND-"&F8) -> BND-4 | I8: =IF(OR(B8="",C8=""),"",IFERROR(INDEX('Slit to Tube Conversion'!$H:$H,MATCH(B8,'Slit to Tube Conversion'!$C:$C,0))/INDEX('Slit to Tube Conversion'!$D:$D,MATCH(B8,'Slit to Tube Conversion'!$C:$C,0)),"")) -> 0.0193631 | J8: =IF(OR(B8="",E8="",I8=""),"",I8*E8) -> 0.8519764 | K8: =IF(B8="","",IF(COUNTIF('Coil to Slit'!$D:$D,B8)>0,"✔ Valid","⚠ Not in Coil to Slit")) -> ✔ Valid | L8: =IF(OR(G8="",B8=""),"",IF(COUNTIFS($G$3:G8,G8,$B$3:B8,B8)>1,"⚠ DUPLICATE","")) | M8: =IF(OR(B8="",E8=""),"",IFERROR(IF(E8>INDEX('Slit to Tube Conversion'!$D:$D,MATCH(B8,'Slit to Tube Conversion'!$C:$C,0)),"⚠ EXCEEDS FG ("&INDEX('Slit to Tube Conversion'!$D:$D,MATCH(B8,'Slit to Tube Conversion'!$C:$C,0))&")","✔ OK"),"Not in FG Conversion")) -> ✔ OK
A9: 46112 | B9: HYD-0326-01-D | C9: MS SHS One Helix IS 4923 YSt 210 Black 38x38x2.80x6000 | D9: =IF(OR(B9="",E9=""),"",IFERROR(INDEX('Slit to Tube Conversion'!$D:$D,MATCH(B9,'Slit to Tube Conversion'!$C:$C,0))-SUMIFS($E$3:E9,$B$3:B9,B9),"")) -> 60 | E9: 66 | F9: 4 | G9: =IF(F9="","","BND-"&F9) -> BND-4 | I9: =IF(OR(B9="",C9=""),"",IFERROR(INDEX('Slit to Tube Conversion'!$H:$H,MATCH(B9,'Slit to Tube Conversion'!$C:$C,0))/INDEX('Slit to Tube Conversion'!$D:$D,MATCH(B9,'Slit to Tube Conversion'!$C:$C,0)),"")) -> 0.0193631 | J9: =IF(OR(B9="",E9="",I9=""),"",I9*E9) -> 1.2779646 | K9: =IF(B9="","",IF(COUNTIF('Coil to Slit'!$D:$D,B9)>0,"✔ Valid","⚠ Not in Coil to Slit")) -> ✔ Valid | L9: =IF(OR(G9="",B9=""),"",IF(COUNTIFS($G$3:G9,G9,$B$3:B9,B9)>1,"⚠ DUPLICATE","")) | M9: =IF(OR(B9="",E9=""),"",IFERROR(IF(E9>INDEX('Slit to Tube Conversion'!$D:$D,MATCH(B9,'Slit to Tube Conversion'!$C:$C,0)),"⚠ EXCEEDS FG ("&INDEX('Slit to Tube Conversion'!$D:$D,MATCH(B9,'Slit to Tube Conversion'!$C:$C,0))&")","✔ OK"),"Not in FG Conversion")) -> ✔ OK
A10: 46112 | B10: HYD-0326-01-D | C10: MS SHS One Helix IS 4923 YSt 210 Black 38x38x2.80x6000 | D10: =IF(OR(B10="",E10=""),"",IFERROR(INDEX('Slit to Tube Conversion'!$D:$D,MATCH(B10,'Slit to Tube Conversion'!$C:$C,0))-SUMIFS($E$3:E10,$B$3:B10,B10),"")) -> 0 | E10: 60 | F10: 5 | G10: =IF(F10="","","BND-"&F10) -> BND-5 | I10: =IF(OR(B10="",C10=""),"",IFERROR(INDEX('Slit to Tube Conversion'!$H:$H,MATCH(B10,'Slit to Tube Conversion'!$C:$C,0))/INDEX('Slit to Tube Conversion'!$D:$D,MATCH(B10,'Slit to Tube Conversion'!$C:$C,0)),"")) -> 0.0193631 | J10: =IF(OR(B10="",E10="",I10=""),"",I10*E10) -> 1.161786 | K10: =IF(B10="","",IF(COUNTIF('Coil to Slit'!$D:$D,B10)>0,"✔ Valid","⚠ Not in Coil to Slit")) -> ✔ Valid | L10: =IF(OR(G10="",B10=""),"",IF(COUNTIFS($G$3:G10,G10,$B$3:B10,B10)>1,"⚠ DUPLICATE","")) | M10: =IF(OR(B10="",E10=""),"",IFERROR(IF(E10>INDEX('Slit to Tube Conversion'!$D:$D,MATCH(B10,'Slit to Tube Conversion'!$C:$C,0)),"⚠ EXCEEDS FG ("&INDEX('Slit to Tube Conversion'!$D:$D,MATCH(B10,'Slit to Tube Conversion'!$C:$C,0))&")","✔ OK"),"Not in FG Conversion")) -> ✔ OK
A11: 46112 | B11: HYD-0326-01-E | C11: MS SHS One Helix IS 4923 YSt 210 Black 38x38x2.80x6000 | D11: =IF(OR(B11="",E11=""),"",IFERROR(INDEX('Slit to Tube Conversion'!$D:$D,MATCH(B11,'Slit to Tube Conversion'!$C:$C,0))-SUMIFS($E$3:E11,$B$3:B11,B11),"")) -> 78 | E11: 50 | F11: 5 | G11: =IF(F11="","","BND-"&F11) -> BND-5 | I11: =IF(OR(B11="",C11=""),"",IFERROR(INDEX('Slit to Tube Conversion'!$H:$H,MATCH(B11,'Slit to Tube Conversion'!$C:$C,0))/INDEX('Slit to Tube Conversion'!$D:$D,MATCH(B11,'Slit to Tube Conversion'!$C:$C,0)),"")) -> 0.019060552 | J11: =IF(OR(B11="",E11="",I11=""),"",I11*E11) -> 0.95302758 | K11: =IF(B11="","",IF(COUNTIF('Coil to Slit'!$D:$D,B11)>0,"✔ Valid","⚠ Not in Coil to Slit")) -> ✔ Valid | L11: =IF(OR(G11="",B11=""),"",IF(COUNTIFS($G$3:G11,G11,$B$3:B11,B11)>1,"⚠ DUPLICATE","")) | M11: =IF(OR(B11="",E11=""),"",IFERROR(IF(E11>INDEX('Slit to Tube Conversion'!$D:$D,MATCH(B11,'Slit to Tube Conversion'!$C:$C,0)),"⚠ EXCEEDS FG ("&INDEX('Slit to Tube Conversion'!$D:$D,MATCH(B11,'Slit to Tube Conversion'!$C:$C,0))&")","✔ OK"),"Not in FG Conversion")) -> ✔ OK
A12: 46112 | B12: HYD-0326-01-E | C12: MS SHS One Helix IS 4923 YSt 210 Black 38x38x2.80x6000 | D12: =IF(OR(B12="",E12=""),"",IFERROR(INDEX('Slit to Tube Conversion'!$D:$D,MATCH(B12,'Slit to Tube Conversion'!$C:$C,0))-SUMIFS($E$3:E12,$B$3:B12,B12),"")) -> 0 | E12: 78 | F12: 6 | G12: =IF(F12="","","BND-"&F12) -> BND-6 | I12: =IF(OR(B12="",C12=""),"",IFERROR(INDEX('Slit to Tube Conversion'!$H:$H,MATCH(B12,'Slit to Tube Conversion'!$C:$C,0))/INDEX('Slit to Tube Conversion'!$D:$D,MATCH(B12,'Slit to Tube Conversion'!$C:$C,0)),"")) -> 0.019060552 | J12: =IF(OR(B12="",E12="",I12=""),"",I12*E12) -> 1.486723 | K12: =IF(B12="","",IF(COUNTIF('Coil to Slit'!$D:$D,B12)>0,"✔ Valid","⚠ Not in Coil to Slit")) -> ✔ Valid | L12: =IF(OR(G12="",B12=""),"",IF(COUNTIFS($G$3:G12,G12,$B$3:B12,B12)>1,"⚠ DUPLICATE","")) | M12: =IF(OR(B12="",E12=""),"",IFERROR(IF(E12>INDEX('Slit to Tube Conversion'!$D:$D,MATCH(B12,'Slit to Tube Conversion'!$C:$C,0)),"⚠ EXCEEDS FG ("&INDEX('Slit to Tube Conversion'!$D:$D,MATCH(B12,'Slit to Tube Conversion'!$C:$C,0))&")","✔ OK"),"Not in FG Conversion")) -> ✔ OK
A13: 46112 | B13: HYD-0326-02-A | C13: MS SHS One Helix IS 4923 YSt 210 Black 38x38x2.80x6000 | D13: =IF(OR(B13="",E13=""),"",IFERROR(INDEX('Slit to Tube Conversion'!$D:$D,MATCH(B13,'Slit to Tube Conversion'!$C:$C,0))-SUMIFS($E$3:E13,$B$3:B13,B13),"")) -> 95 | E13: 32 | F13: 6 | G13: =IF(F13="","","BND-"&F13) -> BND-6
A14: 46112 | B14: HYD-0326-02-A | C14: MS SHS One Helix IS 4923 YSt 210 Black 38x38x2.80x6000 | D14: =IF(OR(B14="",E14=""),"",IFERROR(INDEX('Slit to Tube Conversion'!$D:$D,MATCH(B14,'Slit to Tube Conversion'!$C:$C,0))-SUMIFS($E$3:E14,$B$3:B14,B14),"")) -> 0 | E14: 95 | F14: 7 | G14: =IF(F14="","","BND-"&F14) -> BND-7
A15: 46112 | B15: HYD-0326-02-B | C15: MS SHS One Helix IS 4923 YSt 210 Black 38x38x2.80x6000 | D15: =IF(OR(B15="",E15=""),"",IFERROR(INDEX('Slit to Tube Conversion'!$D:$D,MATCH(B15,'Slit to Tube Conversion'!$C:$C,0))-SUMIFS($E$3:E15,$B$3:B15,B15),"")) -> 112 | E15: 15 | F15: 7 | G15: =IF(F15="","","BND-"&F15) -> BND-7
A16: 46112 | B16: HYD-0326-02-B | C16: MS SHS One Helix IS 4923 YSt 210 Black 38x38x2.80x6000 | D16: =IF(OR(B16="",E16=""),"",IFERROR(INDEX('Slit to Tube Conversion'!$D:$D,MATCH(B16,'Slit to Tube Conversion'!$C:$C,0))-SUMIFS($E$3:E16,$B$3:B16,B16),"")) -> 2 | E16: 110 | F16: 8 | G16: =IF(F16="","","BND-"&F16) -> BND-8
A17: 46112 | B17: HYD-0326-02-B | C17: MS SHS One Helix IS 4923 YSt 210 Black 38x38x2.80x6000 | D17: =IF(OR(B17="",E17=""),"",IFERROR(INDEX('Slit to Tube Conversion'!$D:$D,MATCH(B17,'Slit to Tube Conversion'!$C:$C,0))-SUMIFS($E$3:E17,$B$3:B17,B17),"")) -> 0 | E17: 2 | F17: 9 | G17: =IF(F17="","","BND-"&F17) -> BND-9
A18: 46112 | B18: HYD-0326-02-C | C18: MS SHS One Helix IS 4923 YSt 210 Black 38x38x2.80x6000 | D18: =IF(OR(B18="",E18=""),"",IFERROR(INDEX('Slit to Tube Conversion'!$D:$D,MATCH(B18,'Slit to Tube Conversion'!$C:$C,0))-SUMIFS($E$3:E18,$B$3:B18,B18),"")) -> 19 | E18: 108 | F18: 9 | G18: =IF(F18="","","BND-"&F18) -> BND-9
A19: 46112 | B19: HYD-0326-02-C | C19: MS SHS One Helix IS 4923 YSt 210 Black 38x38x2.80x6000 | D19: =IF(OR(B19="",E19=""),"",IFERROR(INDEX('Slit to Tube Conversion'!$D:$D,MATCH(B19,'Slit to Tube Conversion'!$C:$C,0))-SUMIFS($E$3:E19,$B$3:B19,B19),"")) -> 0 | E19: 19 | F19: 10 | G19: =IF(F19="","","BND-"&F19) -> BND-10
A20: 46112 | B20: HYD-0326-02-D | C20: MS SHS One Helix IS 4923 YSt 210 Black 38x38x2.80x6000 | D20: =IF(OR(B20="",E20=""),"",IFERROR(INDEX('Slit to Tube Conversion'!$D:$D,MATCH(B20,'Slit to Tube Conversion'!$C:$C,0))-SUMIFS($E$3:E20,$B$3:B20,B20),"")) -> 34 | E20: 93 | F20: 10 | G20: =IF(F20="","","BND-"&F20) -> BND-10
A21: 46112 | B21: HYD-0326-02-D | C21: MS SHS One Helix IS 4923 YSt 210 Black 38x38x2.80x6000 | D21: =IF(OR(B21="",E21=""),"",IFERROR(INDEX('Slit to Tube Conversion'!$D:$D,MATCH(B21,'Slit to Tube Conversion'!$C:$C,0))-SUMIFS($E$3:E21,$B$3:B21,B21),"")) -> 0 | E21: 34 | F21: 11 | G21: =IF(F21="","","BND-"&F21) -> BND-11
A22: 46112 | B22: HYD-0326-02-E | C22: MS SHS One Helix IS 4923 YSt 210 Black 38x38x2.80x6000 | D22: =IF(OR(B22="",E22=""),"",IFERROR(INDEX('Slit to Tube Conversion'!$D:$D,MATCH(B22,'Slit to Tube Conversion'!$C:$C,0))-SUMIFS($E$3:E22,$B$3:B22,B22),"")) -> 4 | E22: 126 | F22: 11 | G22: =IF(F22="","","BND-"&F22) -> BND-11
A23: 46112 | B23: HYD-0326-02-E | D23: =IF(OR(B23="",E23=""),"",IFERROR(INDEX('Slit to Tube Conversion'!$D:$D,MATCH(B23,'Slit to Tube Conversion'!$C:$C,0))-SUMIFS($E$3:E23,$B$3:B23,B23),""))
A24: 46112 | B24: HYD-0326-01-F | C24: MS SHS One Helix IS 4923 YSt 210 Black 50x50x2.80x6000 | D24: =IF(OR(B24="",E24=""),"",IFERROR(INDEX('Slit to Tube Conversion'!$D:$D,MATCH(B24,'Slit to Tube Conversion'!$C:$C,0))-SUMIFS($E$3:E24,$B$3:B24,B24),"")) -> 45 | E24: 80 | F24: 12 | G24: =IF(F24="","","BND-"&F24) -> BND-12 | I24: =IF(OR(B24="",C24=""),"",IFERROR(INDEX('Slit to Tube Conversion'!$H:$H,MATCH(B24,'Slit to Tube Conversion'!$C:$C,0))/INDEX('Slit to Tube Conversion'!$D:$D,MATCH(B24,'Slit to Tube Conversion'!$C:$C,0)),"")) -> 0.026024006 | J24: =IF(OR(B24="",E24="",I24=""),"",I24*E24) -> 2.0819205 | K24: =IF(B24="","",IF(COUNTIF('Coil to Slit'!$D:$D,B24)>0,"✔ Valid","⚠ Not in Coil to Slit")) -> ✔ Valid | L24: =IF(OR(G24="",B24=""),"",IF(COUNTIFS($G$3:G24,G24,$B$3:B24,B24)>1,"⚠ DUPLICATE","")) | M24: =IF(OR(B24="",E24=""),"",IFERROR(IF(E24>INDEX('Slit to Tube Conversion'!$D:$D,MATCH(B24,'Slit to Tube Conversion'!$C:$C,0)),"⚠ EXCEEDS FG ("&INDEX('Slit to Tube Conversion'!$D:$D,MATCH(B24,'Slit to Tube Conversion'!$C:$C,0))&")","✔ OK"),"Not in FG Conversion")) -> ✔ OK
A25: 46112 | B25: HYD-0326-01-F | C25: MS SHS One Helix IS 4923 YSt 210 Black 50x50x2.80x6000 | D25: =IF(OR(B25="",E25=""),"",IFERROR(INDEX('Slit to Tube Conversion'!$D:$D,MATCH(B25,'Slit to Tube Conversion'!$C:$C,0))-SUMIFS($E$3:E25,$B$3:B25,B25),"")) -> 0 | E25: 45 | F25: =IF(B25="","",F24+1) -> 13 | G25: =IF(F25="","","BND-"&F25) -> BND-13 | I25: =IF(OR(B25="",C25=""),"",IFERROR(INDEX('Slit to Tube Conversion'!$H:$H,MATCH(B25,'Slit to Tube Conversion'!$C:$C,0))/INDEX('Slit to Tube Conversion'!$D:$D,MATCH(B25,'Slit to Tube Conversion'!$C:$C,0)),"")) -> 0.026024006 | J25: =IF(OR(B25="",E25="",I25=""),"",I25*E25) -> 1.1710803 | K25: =IF(B25="","",IF(COUNTIF('Coil to Slit'!$D:$D,B25)>0,"✔ Valid","⚠ Not in Coil to Slit")) -> ✔ Valid | L25: =IF(OR(G25="",B25=""),"",IF(COUNTIFS($G$3:G25,G25,$B$3:B25,B25)>1,"⚠ DUPLICATE","")) | M25: =IF(OR(B25="",E25=""),"",IFERROR(IF(E25>INDEX('Slit to Tube Conversion'!$D:$D,MATCH(B25,'Slit to Tube Conversion'!$C:$C,0)),"⚠ EXCEEDS FG ("&INDEX('Slit to Tube Conversion'!$D:$D,MATCH(B25,'Slit to Tube Conversion'!$C:$C,0))&")","✔ OK"),"Not in FG Conversion")) -> ✔ OK
A26: 46112 | B26: HYD-0326-01-G | C26: MS SHS One Helix IS 4923 YSt 210 Black 50x50x2.80x6000 | D26: =IF(OR(B26="",E26=""),"",IFERROR(INDEX('Slit to Tube Conversion'!$D:$D,MATCH(B26,'Slit to Tube Conversion'!$C:$C,0))-SUMIFS($E$3:E26,$B$3:B26,B26),"")) -> 90 | E26: 35 | F26: 13 | G26: =IF(F26="","","BND-"&F26) -> BND-13 | I26: =IF(OR(B26="",C26=""),"",IFERROR(INDEX('Slit to Tube Conversion'!$H:$H,MATCH(B26,'Slit to Tube Conversion'!$C:$C,0))/INDEX('Slit to Tube Conversion'!$D:$D,MATCH(B26,'Slit to Tube Conversion'!$C:$C,0)),"")) -> 0.026024006 | J26: =IF(OR(B26="",E26="",I26=""),"",I26*E26) -> 0.91084023 | K26: =IF(B26="","",IF(COUNTIF('Coil to Slit'!$D:$D,B26)>0,"✔ Valid","⚠ Not in Coil to Slit")) -> ✔ Valid | L26: =IF(OR(G26="",B26=""),"",IF(COUNTIFS($G$3:G26,G26,$B$3:B26,B26)>1,"⚠ DUPLICATE","")) | M26: =IF(OR(B26="",E26=""),"",IFERROR(IF(E26>INDEX('Slit to Tube Conversion'!$D:$D,MATCH(B26,'Slit to Tube Conversion'!$C:$C,0)),"⚠ EXCEEDS FG ("&INDEX('Slit to Tube Conversion'!$D:$D,MATCH(B26,'Slit to Tube Conversion'!$C:$C,0))&")","✔ OK"),"Not in FG Conversion")) -> ✔ OK
A27: 46112 | B27: HYD-0326-01-G | C27: MS SHS One Helix IS 4923 YSt 210 Black 50x50x2.80x6000 | D27: =IF(OR(B27="",E27=""),"",IFERROR(INDEX('Slit to Tube Conversion'!$D:$D,MATCH(B27,'Slit to Tube Conversion'!$C:$C,0))-SUMIFS($E$3:E27,$B$3:B27,B27),"")) -> 10 | E27: 80 | F27: 14 | G27: =IF(F27="","","BND-"&F27) -> BND-14 | I27: =IF(OR(B27="",C27=""),"",IFERROR(INDEX('Slit to Tube Conversion'!$H:$H,MATCH(B27,'Slit to Tube Conversion'!$C:$C,0))/INDEX('Slit to Tube Conversion'!$D:$D,MATCH(B27,'Slit to Tube Conversion'!$C:$C,0)),"")) -> 0.026024006 | J27: =IF(OR(B27="",E27="",I27=""),"",I27*E27) -> 2.0819205 | K27: =IF(B27="","",IF(COUNTIF('Coil to Slit'!$D:$D,B27)>0,"✔ Valid","⚠ Not in Coil to Slit")) -> ✔ Valid | L27: =IF(OR(G27="",B27=""),"",IF(COUNTIFS($G$3:G27,G27,$B$3:B27,B27)>1,"⚠ DUPLICATE","")) | M27: =IF(OR(B27="",E27=""),"",IFERROR(IF(E27>INDEX('Slit to Tube Conversion'!$D:$D,MATCH(B27,'Slit to Tube Conversion'!$C:$C,0)),"⚠ EXCEEDS FG ("&INDEX('Slit to Tube Conversion'!$D:$D,MATCH(B27,'Slit to Tube Conversion'!$C:$C,0))&")","✔ OK"),"Not in FG Conversion")) -> ✔ OK
A28: 46112 | B28: HYD-0326-01-G | C28: MS SHS One Helix IS 4923 YSt 210 Black 50x50x2.80x6000 | D28: =IF(OR(B28="",E28=""),"",IFERROR(INDEX('Slit to Tube Conversion'!$D:$D,MATCH(B28,'Slit to Tube Conversion'!$C:$C,0))-SUMIFS($E$3:E28,$B$3:B28,B28),"")) -> 0 | E28: 10 | F28: 15 | G28: =IF(F28="","","BND-"&F28) -> BND-15 | I28: =IF(OR(B28="",C28=""),"",IFERROR(INDEX('Slit to Tube Conversion'!$H:$H,MATCH(B28,'Slit to Tube Conversion'!$C:$C,0))/INDEX('Slit to Tube Conversion'!$D:$D,MATCH(B28,'Slit to Tube Conversion'!$C:$C,0)),"")) -> 0.026024006 | J28: =IF(OR(B28="",E28="",I28=""),"",I28*E28) -> 0.26024006 | K28: =IF(B28="","",IF(COUNTIF('Coil to Slit'!$D:$D,B28)>0,"✔ Valid","⚠ Not in Coil to Slit")) -> ✔ Valid | L28: =IF(OR(G28="",B28=""),"",IF(COUNTIFS($G$3:G28,G28,$B$3:B28,B28)>1,"⚠ DUPLICATE","")) | M28: =IF(OR(B28="",E28=""),"",IFERROR(IF(E28>INDEX('Slit to Tube Conversion'!$D:$D,MATCH(B28,'Slit to Tube Conversion'!$C:$C,0)),"⚠ EXCEEDS FG ("&INDEX('Slit to Tube Conversion'!$D:$D,MATCH(B28,'Slit to Tube Conversion'!$C:$C,0))&")","✔ OK"),"Not in FG Conversion")) -> ✔ OK
A29: 46112 | B29: HYD-0326-02-F | C29: MS SHS One Helix IS 4923 YSt 210 Black 50x50x2.80x6000 | D29: =IF(OR(B29="",E29=""),"",IFERROR(INDEX('Slit to Tube Conversion'!$D:$D,MATCH(B29,'Slit to Tube Conversion'!$C:$C,0))-SUMIFS($E$3:E29,$B$3:B29,B29),"")) -> 55 | E29: 70 | F29: 15 | G29: =IF(F29="","","BND-"&F29) -> BND-15
A30: 46112 | B30: HYD-0326-02-F | C30: MS SHS One Helix IS 4923 YSt 210 Black 50x50x2.80x6000 | D30: =IF(OR(B30="",E30=""),"",IFERROR(INDEX('Slit to Tube Conversion'!$D:$D,MATCH(B30,'Slit to Tube Conversion'!$C:$C,0))-SUMIFS($E$3:E30,$B$3:B30,B30),"")) -> 0 | E30: 55 | F30: 16 | G30: =IF(F30="","","BND-"&F30) -> BND-16
A31: 46112 | B31: HYD-0326-02-G | C31: MS SHS One Helix IS 4923 YSt 210 Black 50x50x2.80x6000 | D31: =IF(OR(B31="",E31=""),"",IFERROR(INDEX('Slit to Tube Conversion'!$D:$D,MATCH(B31,'Slit to Tube Conversion'!$C:$C,0))-SUMIFS($E$3:E31,$B$3:B31,B31),"")) -> 100 | E31: 25 | F31: 16 | G31: =IF(F31="","","BND-"&F31) -> BND-16
A32: 46112 | B32: HYD-0326-02-G | C32: MS SHS One Helix IS 4923 YSt 210 Black 50x50x2.80x6000 | D32: =IF(OR(B32="",E32=""),"",IFERROR(INDEX('Slit to Tube Conversion'!$D:$D,MATCH(B32,'Slit to Tube Conversion'!$C:$C,0))-SUMIFS($E$3:E32,$B$3:B32,B32),"")) -> 20 | E32: 80 | F32: 17 | G32: =IF(F32="","","BND-"&F32) -> BND-17 | I32: =IF(OR(B32="",C32=""),"",IFERROR(INDEX('Slit to Tube Conversion'!$H:$H,MATCH(B32,'Slit to Tube Conversion'!$C:$C,0))/INDEX('Slit to Tube Conversion'!$D:$D,MATCH(B32,'Slit to Tube Conversion'!$C:$C,0)),"")) -> 0.026402446 | J32: =IF(OR(B32="",E32="",I32=""),"",I32*E32) -> 2.1121957 | K32: =IF(B32="","",IF(COUNTIF('Coil to Slit'!$D:$D,B32)>0,"✔ Valid","⚠ Not in Coil to Slit")) -> ✔ Valid | L32: =IF(OR(G32="",B32=""),"",IF(COUNTIFS($G$3:G32,G32,$B$3:B32,B32)>1,"⚠ DUPLICATE","")) | M32: =IF(OR(B32="",E32=""),"",IFERROR(IF(E32>INDEX('Slit to Tube Conversion'!$D:$D,MATCH(B32,'Slit to Tube Conversion'!$C:$C,0)),"⚠ EXCEEDS FG ("&INDEX('Slit to Tube Conversion'!$D:$D,MATCH(B32,'Slit to Tube Conversion'!$C:$C,0))&")","✔ OK"),"Not in FG Conversion")) -> ✔ OK
A33: 46112 | B33: HYD-0326-03-A | C33: MS SHS One Helix IS 4923 YSt 210 Black 38x38x2.50x6000 | D33: =IF(OR(B33="",E33=""),"",IFERROR(INDEX('Slit to Tube Conversion'!$D:$D,MATCH(B33,'Slit to Tube Conversion'!$C:$C,0))-SUMIFS($E$3:E33,$B$3:B33,B33),"")) -> 29 | E33: 132 | F33: =IF(B33="","",F32+1) -> 18 | G33: =IF(F33="","","BND-"&F33) -> BND-18 | I33: =IF(OR(B33="",C33=""),"",IFERROR(INDEX('Slit to Tube Conversion'!$H:$H,MATCH(B33,'Slit to Tube Conversion'!$C:$C,0))/INDEX('Slit to Tube Conversion'!$D:$D,MATCH(B33,'Slit to Tube Conversion'!$C:$C,0)),"")) -> 0.017781279 | J33: =IF(OR(B33="",E33="",I33=""),"",I33*E33) -> 2.3471288 | K33: =IF(B33="","",IF(COUNTIF('Coil to Slit'!$D:$D,B33)>0,"✔ Valid","⚠ Not in Coil to Slit")) -> ✔ Valid | L33: =IF(OR(G33="",B33=""),"",IF(COUNTIFS($G$3:G33,G33,$B$3:B33,B33)>1,"⚠ DUPLICATE","")) | M33: =IF(OR(B33="",E33=""),"",IFERROR(IF(E33>INDEX('Slit to Tube Conversion'!$D:$D,MATCH(B33,'Slit to Tube Conversion'!$C:$C,0)),"⚠ EXCEEDS FG ("&INDEX('Slit to Tube Conversion'!$D:$D,MATCH(B33,'Slit to Tube Conversion'!$C:$C,0))&")","✔ OK"),"Not in FG Conversion")) -> ✔ OK
A34: 46112 | B34: HYD-0326-03-A | C34: MS SHS One Helix IS 4923 YSt 210 Black 38x38x2.50x6000 | D34: =IF(OR(B34="",E34=""),"",IFERROR(INDEX('Slit to Tube Conversion'!$D:$D,MATCH(B34,'Slit to Tube Conversion'!$C:$C,0))-SUMIFS($E$3:E34,$B$3:B34,B34),"")) -> 0 | E34: 29 | F34: =IF(B34="","",F33+1) -> 19 | G34: =IF(F34="","","BND-"&F34) -> BND-19 | I34: =IF(OR(B34="",C34=""),"",IFERROR(INDEX('Slit to Tube Conversion'!$H:$H,MATCH(B34,'Slit to Tube Conversion'!$C:$C,0))/INDEX('Slit to Tube Conversion'!$D:$D,MATCH(B34,'Slit to Tube Conversion'!$C:$C,0)),"")) -> 0.017781279 | J34: =IF(OR(B34="",E34="",I34=""),"",I34*E34) -> 0.51565709 | K34: =IF(B34="","",IF(COUNTIF('Coil to Slit'!$D:$D,B34)>0,"✔ Valid","⚠ Not in Coil to Slit")) -> ✔ Valid | L34: =IF(OR(G34="",B34=""),"",IF(COUNTIFS($G$3:G34,G34,$B$3:B34,B34)>1,"⚠ DUPLICATE","")) | M34: =IF(OR(B34="",E34=""),"",IFERROR(IF(E34>INDEX('Slit to Tube Conversion'!$D:$D,MATCH(B34,'Slit to Tube Conversion'!$C:$C,0)),"⚠ EXCEEDS FG ("&INDEX('Slit to Tube Conversion'!$D:$D,MATCH(B34,'Slit to Tube Conversion'!$C:$C,0))&")","✔ OK"),"Not in FG Conversion")) -> ✔ OK
A35: 46112 | B35: HYD-0326-03-B | C35: MS SHS One Helix IS 4923 YSt 210 Black 38x38x2.50x6000 | D35: =IF(OR(B35="",E35=""),"",IFERROR(INDEX('Slit to Tube Conversion'!$D:$D,MATCH(B35,'Slit to Tube Conversion'!$C:$C,0))-SUMIFS($E$3:E35,$B$3:B35,B35),"")) -> 70 | E35: 91 | F35: 19 | G35: =IF(F35="","","BND-"&F35) -> BND-19 | I35: =IF(OR(B35="",C35=""),"",IFERROR(INDEX('Slit to Tube Conversion'!$H:$H,MATCH(B35,'Slit to Tube Conversion'!$C:$C,0))/INDEX('Slit to Tube Conversion'!$D:$D,MATCH(B35,'Slit to Tube Conversion'!$C:$C,0)),"")) -> 0.017781279 | J35: =IF(OR(B35="",E35="",I35=""),"",I35*E35) -> 1.6180964 | K35: =IF(B35="","",IF(COUNTIF('Coil to Slit'!$D:$D,B35)>0,"✔ Valid","⚠ Not in Coil to Slit")) -> ✔ Valid | L35: =IF(OR(G35="",B35=""),"",IF(COUNTIFS($G$3:G35,G35,$B$3:B35,B35)>1,"⚠ DUPLICATE","")) | M35: =IF(OR(B35="",E35=""),"",IFERROR(IF(E35>INDEX('Slit to Tube Conversion'!$D:$D,MATCH(B35,'Slit to Tube Conversion'!$C:$C,0)),"⚠ EXCEEDS FG ("&INDEX('Slit to Tube Conversion'!$D:$D,MATCH(B35,'Slit to Tube Conversion'!$C:$C,0))&")","✔ OK"),"Not in FG Conversion")) -> ✔ OK
A36: 46112 | B36: HYD-0326-03-B | C36: MS SHS One Helix IS 4923 YSt 210 Black 38x38x2.50x6000 | D36: =IF(OR(B36="",E36=""),"",IFERROR(INDEX('Slit to Tube Conversion'!$D:$D,MATCH(B36,'Slit to Tube Conversion'!$C:$C,0))-SUMIFS($E$3:E36,$B$3:B36,B36),"")) -> 0 | E36: 70 | F36: =IF(B36="","",F35+1) -> 20 | G36: =IF(F36="","","BND-"&F36) -> BND-20 | I36: =IF(OR(B36="",C36=""),"",IFERROR(INDEX('Slit to Tube Conversion'!$H:$H,MATCH(B36,'Slit to Tube Conversion'!$C:$C,0))/INDEX('Slit to Tube Conversion'!$D:$D,MATCH(B36,'Slit to Tube Conversion'!$C:$C,0)),"")) -> 0.017781279 | J36: =IF(OR(B36="",E36="",I36=""),"",I36*E36) -> 1.2446895 | K36: =IF(B36="","",IF(COUNTIF('Coil to Slit'!$D:$D,B36)>0,"✔ Valid","⚠ Not in Coil to Slit")) -> ✔ Valid | L36: =IF(OR(G36="",B36=""),"",IF(COUNTIFS($G$3:G36,G36,$B$3:B36,B36)>1,"⚠ DUPLICATE","")) | M36: =IF(OR(B36="",E36=""),"",IFERROR(IF(E36>INDEX('Slit to Tube Conversion'!$D:$D,MATCH(B36,'Slit to Tube Conversion'!$C:$C,0)),"⚠ EXCEEDS FG ("&INDEX('Slit to Tube Conversion'!$D:$D,MATCH(B36,'Slit to Tube Conversion'!$C:$C,0))&")","✔ OK"),"Not in FG Conversion")) -> ✔ OK
A37: 46112 | B37: HYD-0326-03-C | C37: MS SHS One Helix IS 4923 YSt 210 Black 38x38x2.50x6000 | D37: =IF(OR(B37="",E37=""),"",IFERROR(INDEX('Slit to Tube Conversion'!$D:$D,MATCH(B37,'Slit to Tube Conversion'!$C:$C,0))-SUMIFS($E$3:E37,$B$3:B37,B37),"")) -> 111 | E37: 50 | F37: 20 | G37: =IF(F37="","","BND-"&F37) -> BND-20
A38: 46112 | B38: HYD-0326-03-C | C38: MS SHS One Helix IS 4923 YSt 210 Black 38x38x2.50x6000 | D38: =IF(OR(B38="",E38=""),"",IFERROR(INDEX('Slit to Tube Conversion'!$D:$D,MATCH(B38,'Slit to Tube Conversion'!$C:$C,0))-SUMIFS($E$3:E38,$B$3:B38,B38),"")) -> 0 | E38: 111 | F38: 21 | G38: =IF(F38="","","BND-"&F38) -> BND-21
A39: 46112 | B39: HYD-0326-03-D | C39: MS SHS One Helix IS 4923 YSt 210 Black 38x38x2.50x6000 | D39: =IF(OR(B39="",E39=""),"",IFERROR(INDEX('Slit to Tube Conversion'!$D:$D,MATCH(B39,'Slit to Tube Conversion'!$C:$C,0))-SUMIFS($E$3:E39,$B$3:B39,B39),"")) -> 154 | E39: 9 | F39: 21 | G39: =IF(F39="","","BND-"&F39) -> BND-21
A40: 46112 | B40: HYD-0326-03-D | C40: MS SHS One Helix IS 4923 YSt 210 Black 38x38x2.50x6000 | D40: =IF(OR(B40="",E40=""),"",IFERROR(INDEX('Slit to Tube Conversion'!$D:$D,MATCH(B40,'Slit to Tube Conversion'!$C:$C,0))-SUMIFS($E$3:E40,$B$3:B40,B40),"")) -> 34 | E40: 120 | F40: 22 | G40: =IF(F40="","","BND-"&F40) -> BND-22 | I40: =IF(OR(B40="",C40=""),"",IFERROR(INDEX('Slit to Tube Conversion'!$H:$H,MATCH(B40,'Slit to Tube Conversion'!$C:$C,0))/INDEX('Slit to Tube Conversion'!$D:$D,MATCH(B40,'Slit to Tube Conversion'!$C:$C,0)),"")) -> 0.017563104 | J40: =IF(OR(B40="",E40="",I40=""),"",I40*E40) -> 2.1075724 | K40: =IF(B40="","",IF(COUNTIF('Coil to Slit'!$D:$D,B40)>0,"✔ Valid","⚠ Not in Coil to Slit")) -> ✔ Valid | L40: =IF(OR(G40="",B40=""),"",IF(COUNTIFS($G$3:G40,G40,$B$3:B40,B40)>1,"⚠ DUPLICATE","")) | M40: =IF(OR(B40="",E40=""),"",IFERROR(IF(E40>INDEX('Slit to Tube Conversion'!$D:$D,MATCH(B40,'Slit to Tube Conversion'!$C:$C,0)),"⚠ EXCEEDS FG ("&INDEX('Slit to Tube Conversion'!$D:$D,MATCH(B40,'Slit to Tube Conversion'!$C:$C,0))&")","✔ OK"),"Not in FG Conversion")) -> ✔ OK
A41: 46112 | B41: HYD-0326-03-E | C41: MS SHS One Helix IS 4923 YSt 210 Black 50x50x2.50x6000 | D41: =IF(OR(B41="",E41=""),"",IFERROR(INDEX('Slit to Tube Conversion'!$D:$D,MATCH(B41,'Slit to Tube Conversion'!$C:$C,0))-SUMIFS($E$3:E41,$B$3:B41,B41),"")) -> 70 | E41: 90 | F41: =IF(B41="","",F40+1) -> 23 | G41: =IF(F41="","","BND-"&F41) -> BND-23 | I41: =IF(OR(B41="",C41=""),"",IFERROR(INDEX('Slit to Tube Conversion'!$H:$H,MATCH(B41,'Slit to Tube Conversion'!$C:$C,0))/INDEX('Slit to Tube Conversion'!$D:$D,MATCH(B41,'Slit to Tube Conversion'!$C:$C,0)),"")) -> 0.023856549 | J41: =IF(OR(B41="",E41="",I41=""),"",I41*E41) -> 2.1470894 | K41: =IF(B41="","",IF(COUNTIF('Coil to Slit'!$D:$D,B41)>0,"✔ Valid","⚠ Not in Coil to Slit")) -> ✔ Valid | L41: =IF(OR(G41="",B41=""),"",IF(COUNTIFS($G$3:G41,G41,$B$3:B41,B41)>1,"⚠ DUPLICATE","")) | M41: =IF(OR(B41="",E41=""),"",IFERROR(IF(E41>INDEX('Slit to Tube Conversion'!$D:$D,MATCH(B41,'Slit to Tube Conversion'!$C:$C,0)),"⚠ EXCEEDS FG ("&INDEX('Slit to Tube Conversion'!$D:$D,MATCH(B41,'Slit to Tube Conversion'!$C:$C,0))&")","✔ OK"),"Not in FG Conversion")) -> ✔ OK
A42: 46112 | B42: HYD-0326-03-E | C42: MS SHS One Helix IS 4923 YSt 210 Black 50x50x2.50x6000 | D42: =IF(OR(B42="",E42=""),"",IFERROR(INDEX('Slit to Tube Conversion'!$D:$D,MATCH(B42,'Slit to Tube Conversion'!$C:$C,0))-SUMIFS($E$3:E42,$B$3:B42,B42),"")) -> 0 | E42: 70 | F42: =IF(B42="","",F41+1) -> 24 | G42: =IF(F42="","","BND-"&F42) -> BND-24 | I42: =IF(OR(B42="",C42=""),"",IFERROR(INDEX('Slit to Tube Conversion'!$H:$H,MATCH(B42,'Slit to Tube Conversion'!$C:$C,0))/INDEX('Slit to Tube Conversion'!$D:$D,MATCH(B42,'Slit to Tube Conversion'!$C:$C,0)),"")) -> 0.023856549 | J42: =IF(OR(B42="",E42="",I42=""),"",I42*E42) -> 1.6699584 | K42: =IF(B42="","",IF(COUNTIF('Coil to Slit'!$D:$D,B42)>0,"✔ Valid","⚠ Not in Coil to Slit")) -> ✔ Valid | L42: =IF(OR(G42="",B42=""),"",IF(COUNTIFS($G$3:G42,G42,$B$3:B42,B42)>1,"⚠ DUPLICATE","")) | M42: =IF(OR(B42="",E42=""),"",IFERROR(IF(E42>INDEX('Slit to Tube Conversion'!$D:$D,MATCH(B42,'Slit to Tube Conversion'!$C:$C,0)),"⚠ EXCEEDS FG ("&INDEX('Slit to Tube Conversion'!$D:$D,MATCH(B42,'Slit to Tube Conversion'!$C:$C,0))&")","✔ OK"),"Not in FG Conversion")) -> ✔ OK
A43: 46112 | B43: HYD-0326-03-F | C43: MS SHS One Helix IS 4923 YSt 210 Black 50x50x2.50x6000 | D43: =IF(OR(B43="",E43=""),"",IFERROR(INDEX('Slit to Tube Conversion'!$D:$D,MATCH(B43,'Slit to Tube Conversion'!$C:$C,0))-SUMIFS($E$3:E43,$B$3:B43,B43),"")) -> 140 | E43: 20 | F43: 24 | G43: =IF(F43="","","BND-"&F43) -> BND-24 | I43: =IF(OR(B43="",C43=""),"",IFERROR(INDEX('Slit to Tube Conversion'!$H:$H,MATCH(B43,'Slit to Tube Conversion'!$C:$C,0))/INDEX('Slit to Tube Conversion'!$D:$D,MATCH(B43,'Slit to Tube Conversion'!$C:$C,0)),"")) -> 0.023856549 | J43: =IF(OR(B43="",E43="",I43=""),"",I43*E43) -> 0.47713098 | K43: =IF(B43="","",IF(COUNTIF('Coil to Slit'!$D:$D,B43)>0,"✔ Valid","⚠ Not in Coil to Slit")) -> ✔ Valid | L43: =IF(OR(G43="",B43=""),"",IF(COUNTIFS($G$3:G43,G43,$B$3:B43,B43)>1,"⚠ DUPLICATE","")) | M43: =IF(OR(B43="",E43=""),"",IFERROR(IF(E43>INDEX('Slit to Tube Conversion'!$D:$D,MATCH(B43,'Slit to Tube Conversion'!$C:$C,0)),"⚠ EXCEEDS FG ("&INDEX('Slit to Tube Conversion'!$D:$D,MATCH(B43,'Slit to Tube Conversion'!$C:$C,0))&")","✔ OK"),"Not in FG Conversion")) -> ✔ OK
A44: 46112 | B44: HYD-0326-03-F | C44: MS SHS One Helix IS 4923 YSt 210 Black 50x50x2.50x6000 | D44: =IF(OR(B44="",E44=""),"",IFERROR(INDEX('Slit to Tube Conversion'!$D:$D,MATCH(B44,'Slit to Tube Conversion'!$C:$C,0))-SUMIFS($E$3:E44,$B$3:B44,B44),"")) -> 50 | E44: 90 | F44: =IF(B44="","",F43+1) -> 25 | G44: =IF(F44="","","BND-"&F44) -> BND-25 | I44: =IF(OR(B44="",C44=""),"",IFERROR(INDEX('Slit to Tube Conversion'!$H:$H,MATCH(B44,'Slit to Tube Conversion'!$C:$C,0))/INDEX('Slit to Tube Conversion'!$D:$D,MATCH(B44,'Slit to Tube Conversion'!$C:$C,0)),"")) -> 0.023856549 | J44: =IF(OR(B44="",E44="",I44=""),"",I44*E44) -> 2.1470894 | K44: =IF(B44="","",IF(COUNTIF('Coil to Slit'!$D:$D,B44)>0,"✔ Valid","⚠ Not in Coil to Slit")) -> ✔ Valid | L44: =IF(OR(G44="",B44=""),"",IF(COUNTIFS($G$3:G44,G44,$B$3:B44,B44)>1,"⚠ DUPLICATE","")) | M44: =IF(OR(B44="",E44=""),"",IFERROR(IF(E44>INDEX('Slit to Tube Conversion'!$D:$D,MATCH(B44,'Slit to Tube Conversion'!$C:$C,0)),"⚠ EXCEEDS FG ("&INDEX('Slit to Tube Conversion'!$D:$D,MATCH(B44,'Slit to Tube Conversion'!$C:$C,0))&")","✔ OK"),"Not in FG Conversion")) -> ✔ OK
A45: 46112 | B45: HYD-0326-03-F | C45: MS SHS One Helix IS 4923 YSt 210 Black 50x50x2.50x6000 | D45: =IF(OR(B45="",E45=""),"",IFERROR(INDEX('Slit to Tube Conversion'!$D:$D,MATCH(B45,'Slit to Tube Conversion'!$C:$C,0))-SUMIFS($E$3:E45,$B$3:B45,B45),"")) -> 0 | E45: 50 | F45: =IF(B45="","",F44+1) -> 26 | G45: =IF(F45="","","BND-"&F45) -> BND-26 | I45: =IF(OR(B45="",C45=""),"",IFERROR(INDEX('Slit to Tube Conversion'!$H:$H,MATCH(B45,'Slit to Tube Conversion'!$C:$C,0))/INDEX('Slit to Tube Conversion'!$D:$D,MATCH(B45,'Slit to Tube Conversion'!$C:$C,0)),"")) -> 0.023856549 | J45: =IF(OR(B45="",E45="",I45=""),"",I45*E45) -> 1.1928275 | K45: =IF(B45="","",IF(COUNTIF('Coil to Slit'!$D:$D,B45)>0,"✔ Valid","⚠ Not in Coil to Slit")) -> ✔ Valid | L45: =IF(OR(G45="",B45=""),"",IF(COUNTIFS($G$3:G45,G45,$B$3:B45,B45)>1,"⚠ DUPLICATE","")) | M45: =IF(OR(B45="",E45=""),"",IFERROR(IF(E45>INDEX('Slit to Tube Conversion'!$D:$D,MATCH(B45,'Slit to Tube Conversion'!$C:$C,0)),"⚠ EXCEEDS FG ("&INDEX('Slit to Tube Conversion'!$D:$D,MATCH(B45,'Slit to Tube Conversion'!$C:$C,0))&")","✔ OK"),"Not in FG Conversion")) -> ✔ OK
A46: 46112 | B46: HYD-0326-03-G | C46: MS SHS One Helix IS 4923 YSt 210 Black 50x50x2.50x6000 | D46: =IF(OR(B46="",E46=""),"",IFERROR(INDEX('Slit to Tube Conversion'!$D:$D,MATCH(B46,'Slit to Tube Conversion'!$C:$C,0))-SUMIFS($E$3:E46,$B$3:B46,B46),"")) -> 122 | E46: 40 | F46: 26 | G46: =IF(F46="","","BND-"&F46) -> BND-26 | I46: =IF(OR(B46="",C46=""),"",IFERROR(INDEX('Slit to Tube Conversion'!$H:$H,MATCH(B46,'Slit to Tube Conversion'!$C:$C,0))/INDEX('Slit to Tube Conversion'!$D:$D,MATCH(B46,'Slit to Tube Conversion'!$C:$C,0)),"")) -> 0.023562024 | J46: =IF(OR(B46="",E46="",I46=""),"",I46*E46) -> 0.94248096 | K46: =IF(B46="","",IF(COUNTIF('Coil to Slit'!$D:$D,B46)>0,"✔ Valid","⚠ Not in Coil to Slit")) -> ✔ Valid | L46: =IF(OR(G46="",B46=""),"",IF(COUNTIFS($G$3:G46,G46,$B$3:B46,B46)>1,"⚠ DUPLICATE","")) | M46: =IF(OR(B46="",E46=""),"",IFERROR(IF(E46>INDEX('Slit to Tube Conversion'!$D:$D,MATCH(B46,'Slit to Tube Conversion'!$C:$C,0)),"⚠ EXCEEDS FG ("&INDEX('Slit to Tube Conversion'!$D:$D,MATCH(B46,'Slit to Tube Conversion'!$C:$C,0))&")","✔ OK"),"Not in FG Conversion")) -> ✔ OK
A47: 46112 | B47: HYD-0326-03-G | C47: MS SHS One Helix IS 4923 YSt 210 Black 50x50x2.50x6000 | D47: =IF(OR(B47="",E47=""),"",IFERROR(INDEX('Slit to Tube Conversion'!$D:$D,MATCH(B47,'Slit to Tube Conversion'!$C:$C,0))-SUMIFS($E$3:E47,$B$3:B47,B47),"")) -> 32 | E47: 90 | F47: =IF(B47="","",F46+1) -> 27 | G47: =IF(F47="","","BND-"&F47) -> BND-27 | I47: =IF(OR(B47="",C47=""),"",IFERROR(INDEX('Slit to Tube Conversion'!$H:$H,MATCH(B47,'Slit to Tube Conversion'!$C:$C,0))/INDEX('Slit to Tube Conversion'!$D:$D,MATCH(B47,'Slit to Tube Conversion'!$C:$C,0)),"")) -> 0.023562024 | J47: =IF(OR(B47="",E47="",I47=""),"",I47*E47) -> 2.1205822 | K47: =IF(B47="","",IF(COUNTIF('Coil to Slit'!$D:$D,B47)>0,"✔ Valid","⚠ Not in Coil to Slit")) -> ✔ Valid | L47: =IF(OR(G47="",B47=""),"",IF(COUNTIFS($G$3:G47,G47,$B$3:B47,B47)>1,"⚠ DUPLICATE","")) | M47: =IF(OR(B47="",E47=""),"",IFERROR(IF(E47>INDEX('Slit to Tube Conversion'!$D:$D,MATCH(B47,'Slit to Tube Conversion'!$C:$C,0)),"⚠ EXCEEDS FG ("&INDEX('Slit to Tube Conversion'!$D:$D,MATCH(B47,'Slit to Tube Conversion'!$C:$C,0))&")","✔ OK"),"Not in FG Conversion")) -> ✔ OK
A48: 46113 | B48: HYD-0326-04-A | C48: MS SHS One Helix IS 4923 YSt 210 Black 38x38x2.20x6000 | D48: =IF(OR(B48="",E48=""),"",IFERROR(INDEX('Slit to Tube Conversion'!$D:$D,MATCH(B48,'Slit to Tube Conversion'!$C:$C,0))-SUMIFS($E$3:E48,$B$3:B48,B48),"")) -> 75 | E48: 144 | F48: =IF(B48="","",F47+1) -> 28 | G48: =IF(F48="","","BND-"&F48) -> BND-28 | I48: =IF(OR(B48="",C48=""),"",IFERROR(INDEX('Slit to Tube Conversion'!$H:$H,MATCH(B48,'Slit to Tube Conversion'!$C:$C,0))/INDEX('Slit to Tube Conversion'!$D:$D,MATCH(B48,'Slit to Tube Conversion'!$C:$C,0)),"")) -> 0.015374294 | J48: =IF(OR(B48="",E48="",I48=""),"",I48*E48) -> 2.2138984 | K48: =IF(B48="","",IF(COUNTIF('Coil to Slit'!$D:$D,B48)>0,"✔ Valid","⚠ Not in Coil to Slit")) -> ✔ Valid | L48: =IF(OR(G48="",B48=""),"",IF(COUNTIFS($G$3:G48,G48,$B$3:B48,B48)>1,"⚠ DUPLICATE","")) | M48: =IF(OR(B48="",E48=""),"",IFERROR(IF(E48>INDEX('Slit to Tube Conversion'!$D:$D,MATCH(B48,'Slit to Tube Conversion'!$C:$C,0)),"⚠ EXCEEDS FG ("&INDEX('Slit to Tube Conversion'!$D:$D,MATCH(B48,'Slit to Tube Conversion'!$C:$C,0))&")","✔ OK"),"Not in FG Conversion")) -> ✔ OK
A49: 46113 | B49: HYD-0326-04-A | C49: MS SHS One Helix IS 4923 YSt 210 Black 38x38x2.20x6000 | D49: =IF(OR(B49="",E49=""),"",IFERROR(INDEX('Slit to Tube Conversion'!$D:$D,MATCH(B49,'Slit to Tube Conversion'!$C:$C,0))-SUMIFS($E$3:E49,$B$3:B49,B49),"")) -> 0 | E49: 75 | F49: =IF(B49="","",F48+1) -> 29 | G49: =IF(F49="","","BND-"&F49) -> BND-29 | I49: =IF(OR(B49="",C49=""),"",IFERROR(INDEX('Slit to Tube Conversion'!$H:$H,MATCH(B49,'Slit to Tube Conversion'!$C:$C,0))/INDEX('Slit to Tube Conversion'!$D:$D,MATCH(B49,'Slit to Tube Conversion'!$C:$C,0)),"")) -> 0.015374294 | J49: =IF(OR(B49="",E49="",I49=""),"",I49*E49) -> 1.1530721 | K49: =IF(B49="","",IF(COUNTIF('Coil to Slit'!$D:$D,B49)>0,"✔ Valid","⚠ Not in Coil to Slit")) -> ✔ Valid | L49: =IF(OR(G49="",B49=""),"",IF(COUNTIFS($G$3:G49,G49,$B$3:B49,B49)>1,"⚠ DUPLICATE","")) | M49: =IF(OR(B49="",E49=""),"",IFERROR(IF(E49>INDEX('Slit to Tube Conversion'!$D:$D,MATCH(B49,'Slit to Tube Conversion'!$C:$C,0)),"⚠ EXCEEDS FG ("&INDEX('Slit to Tube Conversion'!$D:$D,MATCH(B49,'Slit to Tube Conversion'!$C:$C,0))&")","✔ OK"),"Not in FG Conversion")) -> ✔ OK
A50: 46113 | B50: HYD-0326-04-B | C50: MS SHS One Helix IS 4923 YSt 210 Black 38x38x2.20x6000 | D50: =IF(OR(B50="",E50=""),"",IFERROR(INDEX('Slit to Tube Conversion'!$D:$D,MATCH(B50,'Slit to Tube Conversion'!$C:$C,0))-SUMIFS($E$3:E50,$B$3:B50,B50),"")) -> 150 | E50: 69 | F50: 29 | G50: =IF(F50="","","BND-"&F50) -> BND-29 | I50: =IF(OR(B50="",C50=""),"",IFERROR(INDEX('Slit to Tube Conversion'!$H:$H,MATCH(B50,'Slit to Tube Conversion'!$C:$C,0))/INDEX('Slit to Tube Conversion'!$D:$D,MATCH(B50,'Slit to Tube Conversion'!$C:$C,0)),"")) -> 0.015374294 | J50: =IF(OR(B50="",E50="",I50=""),"",I50*E50) -> 1.0608263 | K50: =IF(B50="","",IF(COUNTIF('Coil to Slit'!$D:$D,B50)>0,"✔ Valid","⚠ Not in Coil to Slit")) -> ✔ Valid | L50: =IF(OR(G50="",B50=""),"",IF(COUNTIFS($G$3:G50,G50,$B$3:B50,B50)>1,"⚠ DUPLICATE","")) | M50: =IF(OR(B50="",E50=""),"",IFERROR(IF(E50>INDEX('Slit to Tube Conversion'!$D:$D,MATCH(B50,'Slit to Tube Conversion'!$C:$C,0)),"⚠ EXCEEDS FG ("&INDEX('Slit to Tube Conversion'!$D:$D,MATCH(B50,'Slit to Tube Conversion'!$C:$C,0))&")","✔ OK"),"Not in FG Conversion")) -> ✔ OK
A51: 46113 | B51: HYD-0326-04-B | C51: MS SHS One Helix IS 4923 YSt 210 Black 38x38x2.20x6000 | D51: =IF(OR(B51="",E51=""),"",IFERROR(INDEX('Slit to Tube Conversion'!$D:$D,MATCH(B51,'Slit to Tube Conversion'!$C:$C,0))-SUMIFS($E$3:E51,$B$3:B51,B51),"")) -> 6 | E51: 144 | F51: =IF(B51="","",F50+1) -> 30 | G51: =IF(F51="","","BND-"&F51) -> BND-30 | I51: =IF(OR(B51="",C51=""),"",IFERROR(INDEX('Slit to Tube Conversion'!$H:$H,MATCH(B51,'Slit to Tube Conversion'!$C:$C,0))/INDEX('Slit to Tube Conversion'!$D:$D,MATCH(B51,'Slit to Tube Conversion'!$C:$C,0)),"")) -> 0.015374294 | J51: =IF(OR(B51="",E51="",I51=""),"",I51*E51) -> 2.2138984 | K51: =IF(B51="","",IF(COUNTIF('Coil to Slit'!$D:$D,B51)>0,"✔ Valid","⚠ Not in Coil to Slit")) -> ✔ Valid | L51: =IF(OR(G51="",B51=""),"",IF(COUNTIFS($G$3:G51,G51,$B$3:B51,B51)>1,"⚠ DUPLICATE","")) | M51: =IF(OR(B51="",E51=""),"",IFERROR(IF(E51>INDEX('Slit to Tube Conversion'!$D:$D,MATCH(B51,'Slit to Tube Conversion'!$C:$C,0)),"⚠ EXCEEDS FG ("&INDEX('Slit to Tube Conversion'!$D:$D,MATCH(B51,'Slit to Tube Conversion'!$C:$C,0))&")","✔ OK"),"Not in FG Conversion")) -> ✔ OK
A52: 46113 | B52: HYD-0326-04-B | C52: MS SHS One Helix IS 4923 YSt 210 Black 38x38x2.20x6000 | D52: =IF(OR(B52="",E52=""),"",IFERROR(INDEX('Slit to Tube Conversion'!$D:$D,MATCH(B52,'Slit to Tube Conversion'!$C:$C,0))-SUMIFS($E$3:E52,$B$3:B52,B52),"")) -> 0 | E52: 6 | F52: 31 | G52: =IF(F52="","","BND-"&F52) -> BND-31 | I52: =IF(OR(B52="",C52=""),"",IFERROR(INDEX('Slit to Tube Conversion'!$H:$H,MATCH(B52,'Slit to Tube Conversion'!$C:$C,0))/INDEX('Slit to Tube Conversion'!$D:$D,MATCH(B52,'Slit to Tube Conversion'!$C:$C,0)),"")) -> 0.015374294 | J52: =IF(OR(B52="",E52="",I52=""),"",I52*E52) -> 0.092245765 | K52: =IF(B52="","",IF(COUNTIF('Coil to Slit'!$D:$D,B52)>0,"✔ Valid","⚠ Not in Coil to Slit")) -> ✔ Valid | L52: =IF(OR(G52="",B52=""),"",IF(COUNTIFS($G$3:G52,G52,$B$3:B52,B52)>1,"⚠ DUPLICATE","")) | M52: =IF(OR(B52="",E52=""),"",IFERROR(IF(E52>INDEX('Slit to Tube Conversion'!$D:$D,MATCH(B52,'Slit to Tube Conversion'!$C:$C,0)),"⚠ EXCEEDS FG ("&INDEX('Slit to Tube Conversion'!$D:$D,MATCH(B52,'Slit to Tube Conversion'!$C:$C,0))&")","✔ OK"),"Not in FG Conversion")) -> ✔ OK
A53: 46113 | B53: HYD-0326-04-C | C53: MS SHS One Helix IS 4923 YSt 210 Black 38x38x2.20x6000 | D53: =IF(OR(B53="",E53=""),"",IFERROR(INDEX('Slit to Tube Conversion'!$D:$D,MATCH(B53,'Slit to Tube Conversion'!$C:$C,0))-SUMIFS($E$3:E53,$B$3:B53,B53),"")) -> 173 | E53: 46 | F53: 31 | G53: =IF(F53="","","BND-"&F53) -> BND-31 | I53: =IF(OR(B53="",C53=""),"",IFERROR(INDEX('Slit to Tube Conversion'!$H:$H,MATCH(B53,'Slit to Tube Conversion'!$C:$C,0))/INDEX('Slit to Tube Conversion'!$D:$D,MATCH(B53,'Slit to Tube Conversion'!$C:$C,0)),"")) -> 0.015374294 | J53: =IF(OR(B53="",E53="",I53=""),"",I53*E53) -> 0.70721753 | K53: =IF(B53="","",IF(COUNTIF('Coil to Slit'!$D:$D,B53)>0,"✔ Valid","⚠ Not in Coil to Slit")) -> ✔ Valid | L53: =IF(OR(G53="",B53=""),"",IF(COUNTIFS($G$3:G53,G53,$B$3:B53,B53)>1,"⚠ DUPLICATE","")) | M53: =IF(OR(B53="",E53=""),"",IFERROR(IF(E53>INDEX('Slit to Tube Conversion'!$D:$D,MATCH(B53,'Slit to Tube Conversion'!$C:$C,0)),"⚠ EXCEEDS FG ("&INDEX('Slit to Tube Conversion'!$D:$D,MATCH(B53,'Slit to Tube Conversion'!$C:$C,0))&")","✔ OK"),"Not in FG Conversion")) -> ✔ OK
A54: 46113 | B54: HYD-0326-04-C | C54: MS SHS One Helix IS 4923 YSt 210 Black 38x38x2.20x6000 | D54: =IF(OR(B54="",E54=""),"",IFERROR(INDEX('Slit to Tube Conversion'!$D:$D,MATCH(B54,'Slit to Tube Conversion'!$C:$C,0))-SUMIFS($E$3:E54,$B$3:B54,B54),"")) -> 29 | E54: 144 | F54: 32 | G54: =IF(F54="","","BND-"&F54) -> BND-32 | I54: =IF(OR(B54="",C54=""),"",IFERROR(INDEX('Slit to Tube Conversion'!$H:$H,MATCH(B54,'Slit to Tube Conversion'!$C:$C,0))/INDEX('Slit to Tube Conversion'!$D:$D,MATCH(B54,'Slit to Tube Conversion'!$C:$C,0)),"")) -> 0.015374294 | J54: =IF(OR(B54="",E54="",I54=""),"",I54*E54) -> 2.2138984 | K54: =IF(B54="","",IF(COUNTIF('Coil to Slit'!$D:$D,B54)>0,"✔ Valid","⚠ Not in Coil to Slit")) -> ✔ Valid | L54: =IF(OR(G54="",B54=""),"",IF(COUNTIFS($G$3:G54,G54,$B$3:B54,B54)>1,"⚠ DUPLICATE","")) | M54: =IF(OR(B54="",E54=""),"",IFERROR(IF(E54>INDEX('Slit to Tube Conversion'!$D:$D,MATCH(B54,'Slit to Tube Conversion'!$C:$C,0)),"⚠ EXCEEDS FG ("&INDEX('Slit to Tube Conversion'!$D:$D,MATCH(B54,'Slit to Tube Conversion'!$C:$C,0))&")","✔ OK"),"Not in FG Conversion")) -> ✔ OK
A55: 46113 | B55: HYD-0326-04-C | C55: MS SHS One Helix IS 4923 YSt 210 Black 38x38x2.20x6000 | D55: =IF(OR(B55="",E55=""),"",IFERROR(INDEX('Slit to Tube Conversion'!$D:$D,MATCH(B55,'Slit to Tube Conversion'!$C:$C,0))-SUMIFS($E$3:E55,$B$3:B55,B55),"")) -> 0 | E55: 29 | F55: =IF(B55="","",F54+1) -> 33 | G55: =IF(F55="","","BND-"&F55) -> BND-33 | I55: =IF(OR(B55="",C55=""),"",IFERROR(INDEX('Slit to Tube Conversion'!$H:$H,MATCH(B55,'Slit to Tube Conversion'!$C:$C,0))/INDEX('Slit to Tube Conversion'!$D:$D,MATCH(B55,'Slit to Tube Conversion'!$C:$C,0)),"")) -> 0.015374294 | J55: =IF(OR(B55="",E55="",I55=""),"",I55*E55) -> 0.44585453 | K55: =IF(B55="","",IF(COUNTIF('Coil to Slit'!$D:$D,B55)>0,"✔ Valid","⚠ Not in Coil to Slit")) -> ✔ Valid | L55: =IF(OR(G55="",B55=""),"",IF(COUNTIFS($G$3:G55,G55,$B$3:B55,B55)>1,"⚠ DUPLICATE","")) | M55: =IF(OR(B55="",E55=""),"",IFERROR(IF(E55>INDEX('Slit to Tube Conversion'!$D:$D,MATCH(B55,'Slit to Tube Conversion'!$C:$C,0)),"⚠ EXCEEDS FG ("&INDEX('Slit to Tube Conversion'!$D:$D,MATCH(B55,'Slit to Tube Conversion'!$C:$C,0))&")","✔ OK"),"Not in FG Conversion")) -> ✔ OK
A56: 46113 | B56: HYD-0326-04-D | C56: MS SHS One Helix IS 4923 YSt 210 Black 38x38x2.20x6000 | D56: =IF(OR(B56="",E56=""),"",IFERROR(INDEX('Slit to Tube Conversion'!$D:$D,MATCH(B56,'Slit to Tube Conversion'!$C:$C,0))-SUMIFS($E$3:E56,$B$3:B56,B56),"")) -> 104 | E56: 115 | F56: 33 | G56: =IF(F56="","","BND-"&F56) -> BND-33 | I56: =IF(OR(B56="",C56=""),"",IFERROR(INDEX('Slit to Tube Conversion'!$H:$H,MATCH(B56,'Slit to Tube Conversion'!$C:$C,0))/INDEX('Slit to Tube Conversion'!$D:$D,MATCH(B56,'Slit to Tube Conversion'!$C:$C,0)),"")) -> 0.015374294 | J56: =IF(OR(B56="",E56="",I56=""),"",I56*E56) -> 1.7680438 | K56: =IF(B56="","",IF(COUNTIF('Coil to Slit'!$D:$D,B56)>0,"✔ Valid","⚠ Not in Coil to Slit")) -> ✔ Valid | L56: =IF(OR(G56="",B56=""),"",IF(COUNTIFS($G$3:G56,G56,$B$3:B56,B56)>1,"⚠ DUPLICATE","")) | M56: =IF(OR(B56="",E56=""),"",IFERROR(IF(E56>INDEX('Slit to Tube Conversion'!$D:$D,MATCH(B56,'Slit to Tube Conversion'!$C:$C,0)),"⚠ EXCEEDS FG ("&INDEX('Slit to Tube Conversion'!$D:$D,MATCH(B56,'Slit to Tube Conversion'!$C:$C,0))&")","✔ OK"),"Not in FG Conversion")) -> ✔ OK
A57: 46113 | B57: HYD-0326-04-D | C57: MS SHS One Helix IS 4923 YSt 210 Black 38x38x2.20x6000 | D57: =IF(OR(B57="",E57=""),"",IFERROR(INDEX('Slit to Tube Conversion'!$D:$D,MATCH(B57,'Slit to Tube Conversion'!$C:$C,0))-SUMIFS($E$3:E57,$B$3:B57,B57),"")) -> 0 | E57: 104 | F57: =IF(B57="","",F56+1) -> 34 | G57: =IF(F57="","","BND-"&F57) -> BND-34 | I57: =IF(OR(B57="",C57=""),"",IFERROR(INDEX('Slit to Tube Conversion'!$H:$H,MATCH(B57,'Slit to Tube Conversion'!$C:$C,0))/INDEX('Slit to Tube Conversion'!$D:$D,MATCH(B57,'Slit to Tube Conversion'!$C:$C,0)),"")) -> 0.015374294 | J57: =IF(OR(B57="",E57="",I57=""),"",I57*E57) -> 1.5989266 | K57: =IF(B57="","",IF(COUNTIF('Coil to Slit'!$D:$D,B57)>0,"✔ Valid","⚠ Not in Coil to Slit")) -> ✔ Valid | L57: =IF(OR(G57="",B57=""),"",IF(COUNTIFS($G$3:G57,G57,$B$3:B57,B57)>1,"⚠ DUPLICATE","")) | M57: =IF(OR(B57="",E57=""),"",IFERROR(IF(E57>INDEX('Slit to Tube Conversion'!$D:$D,MATCH(B57,'Slit to Tube Conversion'!$C:$C,0)),"⚠ EXCEEDS FG ("&INDEX('Slit to Tube Conversion'!$D:$D,MATCH(B57,'Slit to Tube Conversion'!$C:$C,0))&")","✔ OK"),"Not in FG Conversion")) -> ✔ OK
A58: 46113 | B58: HYD-0326-04-E | C58: MS SHS One Helix IS 4923 YSt 210 Black 38x38x2.20x6000 | D58: =IF(OR(B58="",E58=""),"",IFERROR(INDEX('Slit to Tube Conversion'!$D:$D,MATCH(B58,'Slit to Tube Conversion'!$C:$C,0))-SUMIFS($E$3:E58,$B$3:B58,B58),"")) -> 178 | E58: 40 | F58: 34 | G58: =IF(F58="","","BND-"&F58) -> BND-34 | I58: =IF(OR(B58="",C58=""),"",IFERROR(INDEX('Slit to Tube Conversion'!$H:$H,MATCH(B58,'Slit to Tube Conversion'!$C:$C,0))/INDEX('Slit to Tube Conversion'!$D:$D,MATCH(B58,'Slit to Tube Conversion'!$C:$C,0)),"")) -> 0.015444818 | J58: =IF(OR(B58="",E58="",I58=""),"",I58*E58) -> 0.61779274 | K58: =IF(B58="","",IF(COUNTIF('Coil to Slit'!$D:$D,B58)>0,"✔ Valid","⚠ Not in Coil to Slit")) -> ✔ Valid | L58: =IF(OR(G58="",B58=""),"",IF(COUNTIFS($G$3:G58,G58,$B$3:B58,B58)>1,"⚠ DUPLICATE","")) | M58: =IF(OR(B58="",E58=""),"",IFERROR(IF(E58>INDEX('Slit to Tube Conversion'!$D:$D,MATCH(B58,'Slit to Tube Conversion'!$C:$C,0)),"⚠ EXCEEDS FG ("&INDEX('Slit to Tube Conversion'!$D:$D,MATCH(B58,'Slit to Tube Conversion'!$C:$C,0))&")","✔ OK"),"Not in FG Conversion")) -> ✔ OK
A59: 46113 | B59: HYD-0326-04-E | C59: MS SHS One Helix IS 4923 YSt 210 Black 38x38x2.20x6000 | D59: =IF(OR(B59="",E59=""),"",IFERROR(INDEX('Slit to Tube Conversion'!$D:$D,MATCH(B59,'Slit to Tube Conversion'!$C:$C,0))-SUMIFS($E$3:E59,$B$3:B59,B59),"")) -> 34 | E59: 144 | F59: =IF(B59="","",F58+1) -> 35 | G59: =IF(F59="","","BND-"&F59) -> BND-35 | I59: =IF(OR(B59="",C59=""),"",IFERROR(INDEX('Slit to Tube Conversion'!$H:$H,MATCH(B59,'Slit to Tube Conversion'!$C:$C,0))/INDEX('Slit to Tube Conversion'!$D:$D,MATCH(B59,'Slit to Tube Conversion'!$C:$C,0)),"")) -> 0.015444818 | J59: =IF(OR(B59="",E59="",I59=""),"",I59*E59) -> 2.2240539 | K59: =IF(B59="","",IF(COUNTIF('Coil to Slit'!$D:$D,B59)>0,"✔ Valid","⚠ Not in Coil to Slit")) -> ✔ Valid | L59: =IF(OR(G59="",B59=""),"",IF(COUNTIFS($G$3:G59,G59,$B$3:B59,B59)>1,"⚠ DUPLICATE","")) | M59: =IF(OR(B59="",E59=""),"",IFERROR(IF(E59>INDEX('Slit to Tube Conversion'!$D:$D,MATCH(B59,'Slit to Tube Conversion'!$C:$C,0)),"⚠ EXCEEDS FG ("&INDEX('Slit to Tube Conversion'!$D:$D,MATCH(B59,'Slit to Tube Conversion'!$C:$C,0))&")","✔ OK"),"Not in FG Conversion")) -> ✔ OK
A60: 46113 | B60: HYD-0326-04-F | C60: MS SHS One Helix IS 4923 YSt 210 Black 50x50x2.20x6000 | D60: =IF(OR(B60="",E60=""),"",IFERROR(INDEX('Slit to Tube Conversion'!$D:$D,MATCH(B60,'Slit to Tube Conversion'!$C:$C,0))-SUMIFS($E$3:E60,$B$3:B60,B60),"")) -> 103 | E60: 110 | F60: =IF(B60="","",F59+1) -> 36 | G60: =IF(F60="","","BND-"&F60) -> BND-36 | I60: =IF(OR(B60="",C60=""),"",IFERROR(INDEX('Slit to Tube Conversion'!$H:$H,MATCH(B60,'Slit to Tube Conversion'!$C:$C,0))/INDEX('Slit to Tube Conversion'!$D:$D,MATCH(B60,'Slit to Tube Conversion'!$C:$C,0)),"")) -> 0.021040895 | J60: =IF(OR(B60="",E60="",I60=""),"",I60*E60) -> 2.3144984 | K60: =IF(B60="","",IF(COUNTIF('Coil to Slit'!$D:$D,B60)>0,"✔ Valid","⚠ Not in Coil to Slit")) -> ✔ Valid | L60: =IF(OR(G60="",B60=""),"",IF(COUNTIFS($G$3:G60,G60,$B$3:B60,B60)>1,"⚠ DUPLICATE","")) | M60: =IF(OR(B60="",E60=""),"",IFERROR(IF(E60>INDEX('Slit to Tube Conversion'!$D:$D,MATCH(B60,'Slit to Tube Conversion'!$C:$C,0)),"⚠ EXCEEDS FG ("&INDEX('Slit to Tube Conversion'!$D:$D,MATCH(B60,'Slit to Tube Conversion'!$C:$C,0))&")","✔ OK"),"Not in FG Conversion")) -> ✔ OK
A61: 46113 | B61: HYD-0326-04-F | C61: MS SHS One Helix IS 4923 YSt 210 Black 50x50x2.20x6000 | D61: =IF(OR(B61="",E61=""),"",IFERROR(INDEX('Slit to Tube Conversion'!$D:$D,MATCH(B61,'Slit to Tube Conversion'!$C:$C,0))-SUMIFS($E$3:E61,$B$3:B61,B61),"")) -> 0 | E61: 103 | F61: =IF(B61="","",F60+1) -> 37 | G61: =IF(F61="","","BND-"&F61) -> BND-37 | I61: =IF(OR(B61="",C61=""),"",IFERROR(INDEX('Slit to Tube Conversion'!$H:$H,MATCH(B61,'Slit to Tube Conversion'!$C:$C,0))/INDEX('Slit to Tube Conversion'!$D:$D,MATCH(B61,'Slit to Tube Conversion'!$C:$C,0)),"")) -> 0.021040895 | J61: =IF(OR(B61="",E61="",I61=""),"",I61*E61) -> 2.1672122 | K61: =IF(B61="","",IF(COUNTIF('Coil to Slit'!$D:$D,B61)>0,"✔ Valid","⚠ Not in Coil to Slit")) -> ✔ Valid | L61: =IF(OR(G61="",B61=""),"",IF(COUNTIFS($G$3:G61,G61,$B$3:B61,B61)>1,"⚠ DUPLICATE","")) | M61: =IF(OR(B61="",E61=""),"",IFERROR(IF(E61>INDEX('Slit to Tube Conversion'!$D:$D,MATCH(B61,'Slit to Tube Conversion'!$C:$C,0)),"⚠ EXCEEDS FG ("&INDEX('Slit to Tube Conversion'!$D:$D,MATCH(B61,'Slit to Tube Conversion'!$C:$C,0))&")","✔ OK"),"Not in FG Conversion")) -> ✔ OK
A62: 46113 | B62: HYD-0326-04-G | C62: MS SHS One Helix IS 4923 YSt 210 Black 50x50x2.20x6000 | D62: =IF(OR(B62="",E62=""),"",IFERROR(INDEX('Slit to Tube Conversion'!$D:$D,MATCH(B62,'Slit to Tube Conversion'!$C:$C,0))-SUMIFS($E$3:E62,$B$3:B62,B62),"")) -> 206 | E62: 7 | F62: 37 | G62: =IF(F62="","","BND-"&F62) -> BND-37 | I62: =IF(OR(B62="",C62=""),"",IFERROR(INDEX('Slit to Tube Conversion'!$H:$H,MATCH(B62,'Slit to Tube Conversion'!$C:$C,0))/INDEX('Slit to Tube Conversion'!$D:$D,MATCH(B62,'Slit to Tube Conversion'!$C:$C,0)),"")) -> 0.021040895 | J62: =IF(OR(B62="",E62="",I62=""),"",I62*E62) -> 0.14728626 | K62: =IF(B62="","",IF(COUNTIF('Coil to Slit'!$D:$D,B62)>0,"✔ Valid","⚠ Not in Coil to Slit")) -> ✔ Valid | L62: =IF(OR(G62="",B62=""),"",IF(COUNTIFS($G$3:G62,G62,$B$3:B62,B62)>1,"⚠ DUPLICATE","")) | M62: =IF(OR(B62="",E62=""),"",IFERROR(IF(E62>INDEX('Slit to Tube Conversion'!$D:$D,MATCH(B62,'Slit to Tube Conversion'!$C:$C,0)),"⚠ EXCEEDS FG ("&INDEX('Slit to Tube Conversion'!$D:$D,MATCH(B62,'Slit to Tube Conversion'!$C:$C,0))&")","✔ OK"),"Not in FG Conversion")) -> ✔ OK
A63: 46113 | B63: HYD-0326-04-G | C63: MS SHS One Helix IS 4923 YSt 210 Black 50x50x2.20x6000 | D63: =IF(OR(B63="",E63=""),"",IFERROR(INDEX('Slit to Tube Conversion'!$D:$D,MATCH(B63,'Slit to Tube Conversion'!$C:$C,0))-SUMIFS($E$3:E63,$B$3:B63,B63),"")) -> 96 | E63: 110 | F63: =IF(B63="","",F62+1) -> 38 | G63: =IF(F63="","","BND-"&F63) -> BND-38 | I63: =IF(OR(B63="",C63=""),"",IFERROR(INDEX('Slit to Tube Conversion'!$H:$H,MATCH(B63,'Slit to Tube Conversion'!$C:$C,0))/INDEX('Slit to Tube Conversion'!$D:$D,MATCH(B63,'Slit to Tube Conversion'!$C:$C,0)),"")) -> 0.021040895 | J63: =IF(OR(B63="",E63="",I63=""),"",I63*E63) -> 2.3144984 | K63: =IF(B63="","",IF(COUNTIF('Coil to Slit'!$D:$D,B63)>0,"✔ Valid","⚠ Not in Coil to Slit")) -> ✔ Valid | L63: =IF(OR(G63="",B63=""),"",IF(COUNTIFS($G$3:G63,G63,$B$3:B63,B63)>1,"⚠ DUPLICATE","")) | M63: =IF(OR(B63="",E63=""),"",IFERROR(IF(E63>INDEX('Slit to Tube Conversion'!$D:$D,MATCH(B63,'Slit to Tube Conversion'!$C:$C,0)),"⚠ EXCEEDS FG ("&INDEX('Slit to Tube Conversion'!$D:$D,MATCH(B63,'Slit to Tube Conversion'!$C:$C,0))&")","✔ OK"),"Not in FG Conversion")) -> ✔ OK
A64: 46113 | D64: =IF(OR(B64="",E64=""),"",IFERROR(INDEX('Slit to Tube Conversion'!$D:$D,MATCH(B64,'Slit to Tube Conversion'!$C:$C,0))-SUMIFS($E$3:E64,$B$3:B64,B64),"")) | F64: =IF(B64="","",F63+1) | G64: =IF(F64="","","BND-"&F64) | I64: =IF(OR(B64="",C64=""),"",IFERROR(INDEX('Slit to Tube Conversion'!$H:$H,MATCH(B64,'Slit to Tube Conversion'!$C:$C,0))/INDEX('Slit to Tube Conversion'!$D:$D,MATCH(B64,'Slit to Tube Conversion'!$C:$C,0)),"")) | J64: =IF(OR(B64="",E64="",I64=""),"",I64*E64) | K64: =IF(B64="","",IF(COUNTIF('Coil to Slit'!$D:$D,B64)>0,"✔ Valid","⚠ Not in Coil to Slit")) | L64: =IF(OR(G64="",B64=""),"",IF(COUNTIFS($G$3:G64,G64,$B$3:B64,B64)>1,"⚠ DUPLICATE","")) | M64: =IF(OR(B64="",E64=""),"",IFERROR(IF(E64>INDEX('Slit to Tube Conversion'!$D:$D,MATCH(B64,'Slit to Tube Conversion'!$C:$C,0)),"⚠ EXCEEDS FG ("&INDEX('Slit to Tube Conversion'!$D:$D,MATCH(B64,'Slit to Tube Conversion'!$C:$C,0))&")","✔ OK"),"Not in FG Conversion"))
D65: =IF(OR(B65="",E65=""),"",IFERROR(INDEX('Slit to Tube Conversion'!$D:$D,MATCH(B65,'Slit to Tube Conversion'!$C:$C,0))-SUMIFS($E$3:E65,$B$3:B65,B65),"")) | F65: =IF(B65="","",F64+1) | G65: =IF(F65="","","BND-"&F65) | I65: =IF(OR(B65="",C65=""),"",IFERROR(INDEX('Slit to Tube Conversion'!$H:$H,MATCH(B65,'Slit to Tube Conversion'!$C:$C,0))/INDEX('Slit to Tube Conversion'!$D:$D,MATCH(B65,'Slit to Tube Conversion'!$C:$C,0)),"")) | J65: =IF(OR(B65="",E65="",I65=""),"",I65*E65) | K65: =IF(B65="","",IF(COUNTIF('Coil to Slit'!$D:$D,B65)>0,"✔ Valid","⚠ Not in Coil to Slit")) | L65: =IF(OR(G65="",B65=""),"",IF(COUNTIFS($G$3:G65,G65,$B$3:B65,B65)>1,"⚠ DUPLICATE","")) | M65: =IF(OR(B65="",E65=""),"",IFERROR(IF(E65>INDEX('Slit to Tube Conversion'!$D:$D,MATCH(B65,'Slit to Tube Conversion'!$C:$C,0)),"⚠ EXCEEDS FG ("&INDEX('Slit to Tube Conversion'!$D:$D,MATCH(B65,'Slit to Tube Conversion'!$C:$C,0))&")","✔ OK"),"Not in FG Conversion"))
D66: =IF(OR(B66="",E66=""),"",IFERROR(INDEX('Slit to Tube Conversion'!$D:$D,MATCH(B66,'Slit to Tube Conversion'!$C:$C,0))-SUMIFS($E$3:E66,$B$3:B66,B66),"")) | F66: =IF(B66="","",F65+1) | G66: =IF(F66="","","BND-"&F66) | I66: =IF(OR(B66="",C66=""),"",IFERROR(INDEX('Slit to Tube Conversion'!$H:$H,MATCH(B66,'Slit to Tube Conversion'!$C:$C,0))/INDEX('Slit to Tube Conversion'!$D:$D,MATCH(B66,'Slit to Tube Conversion'!$C:$C,0)),"")) | J66: =IF(OR(B66="",E66="",I66=""),"",I66*E66) | K66: =IF(B66="","",IF(COUNTIF('Coil to Slit'!$D:$D,B66)>0,"✔ Valid","⚠ Not in Coil to Slit")) | L66: =IF(OR(G66="",B66=""),"",IF(COUNTIFS($G$3:G66,G66,$B$3:B66,B66)>1,"⚠ DUPLICATE","")) | M66: =IF(OR(B66="",E66=""),"",IFERROR(IF(E66>INDEX('Slit to Tube Conversion'!$D:$D,MATCH(B66,'Slit to Tube Conversion'!$C:$C,0)),"⚠ EXCEEDS FG ("&INDEX('Slit to Tube Conversion'!$D:$D,MATCH(B66,'Slit to Tube Conversion'!$C:$C,0))&")","✔ OK"),"Not in FG Conversion"))
D67: =IF(OR(B67="",E67=""),"",IFERROR(INDEX('Slit to Tube Conversion'!$D:$D,MATCH(B67,'Slit to Tube Conversion'!$C:$C,0))-SUMIFS($E$3:E67,$B$3:B67,B67),"")) | F67: =IF(B67="","",F66+1) | G67: =IF(F67="","","BND-"&F67) | I67: =IF(OR(B67="",C67=""),"",IFERROR(INDEX('Slit to Tube Conversion'!$H:$H,MATCH(B67,'Slit to Tube Conversion'!$C:$C,0))/INDEX('Slit to Tube Conversion'!$D:$D,MATCH(B67,'Slit to Tube Conversion'!$C:$C,0)),"")) | J67: =IF(OR(B67="",E67="",I67=""),"",I67*E67) | K67: =IF(B67="","",IF(COUNTIF('Coil to Slit'!$D:$D,B67)>0,"✔ Valid","⚠ Not in Coil to Slit")) | L67: =IF(OR(G67="",B67=""),"",IF(COUNTIFS($G$3:G67,G67,$B$3:B67,B67)>1,"⚠ DUPLICATE","")) | M67: =IF(OR(B67="",E67=""),"",IFERROR(IF(E67>INDEX('Slit to Tube Conversion'!$D:$D,MATCH(B67,'Slit to Tube Conversion'!$C:$C,0)),"⚠ EXCEEDS FG ("&INDEX('Slit to Tube Conversion'!$D:$D,MATCH(B67,'Slit to Tube Conversion'!$C:$C,0))&")","✔ OK"),"Not in FG Conversion"))
D68: =IF(OR(B68="",E68=""),"",IFERROR(INDEX('Slit to Tube Conversion'!$D:$D,MATCH(B68,'Slit to Tube Conversion'!$C:$C,0))-SUMIFS($E$3:E68,$B$3:B68,B68),"")) | F68: =IF(B68="","",F67+1) | G68: =IF(F68="","","BND-"&F68) | I68: =IF(OR(B68="",C68=""),"",IFERROR(INDEX('Slit to Tube Conversion'!$H:$H,MATCH(B68,'Slit to Tube Conversion'!$C:$C,0))/INDEX('Slit to Tube Conversion'!$D:$D,MATCH(B68,'Slit to Tube Conversion'!$C:$C,0)),"")) | J68: =IF(OR(B68="",E68="",I68=""),"",I68*E68) | K68: =IF(B68="","",IF(COUNTIF('Coil to Slit'!$D:$D,B68)>0,"✔ Valid","⚠ Not in Coil to Slit")) | L68: =IF(OR(G68="",B68=""),"",IF(COUNTIFS($G$3:G68,G68,$B$3:B68,B68)>1,"⚠ DUPLICATE","")) | M68: =IF(OR(B68="",E68=""),"",IFERROR(IF(E68>INDEX('Slit to Tube Conversion'!$D:$D,MATCH(B68,'Slit to Tube Conversion'!$C:$C,0)),"⚠ EXCEEDS FG ("&INDEX('Slit to Tube Conversion'!$D:$D,MATCH(B68,'Slit to Tube Conversion'!$C:$C,0))&")","✔ OK"),"Not in FG Conversion"))
D69: =IF(OR(B69="",E69=""),"",IFERROR(INDEX('Slit to Tube Conversion'!$D:$D,MATCH(B69,'Slit to Tube Conversion'!$C:$C,0))-SUMIFS($E$3:E69,$B$3:B69,B69),"")) | F69: =IF(B69="","",F68+1) | G69: =IF(F69="","","BND-"&F69) | I69: =IF(OR(B69="",C69=""),"",IFERROR(INDEX('Slit to Tube Conversion'!$H:$H,MATCH(B69,'Slit to Tube Conversion'!$C:$C,0))/INDEX('Slit to Tube Conversion'!$D:$D,MATCH(B69,'Slit to Tube Conversion'!$C:$C,0)),"")) | J69: =IF(OR(B69="",E69="",I69=""),"",I69*E69) | K69: =IF(B69="","",IF(COUNTIF('Coil to Slit'!$D:$D,B69)>0,"✔ Valid","⚠ Not in Coil to Slit")) | L69: =IF(OR(G69="",B69=""),"",IF(COUNTIFS($G$3:G69,G69,$B$3:B69,B69)>1,"⚠ DUPLICATE","")) | M69: =IF(OR(B69="",E69=""),"",IFERROR(IF(E69>INDEX('Slit to Tube Conversion'!$D:$D,MATCH(B69,'Slit to Tube Conversion'!$C:$C,0)),"⚠ EXCEEDS FG ("&INDEX('Slit to Tube Conversion'!$D:$D,MATCH(B69,'Slit to Tube Conversion'!$C:$C,0))&")","✔ OK"),"Not in FG Conversion"))
D70: =IF(OR(B70="",E70=""),"",IFERROR(INDEX('Slit to Tube Conversion'!$D:$D,MATCH(B70,'Slit to Tube Conversion'!$C:$C,0))-SUMIFS($E$3:E70,$B$3:B70,B70),"")) | F70: =IF(B70="","",F69+1) | G70: =IF(F70="","","BND-"&F70) | I70: =IF(OR(B70="",C70=""),"",IFERROR(INDEX('Slit to Tube Conversion'!$H:$H,MATCH(B70,'Slit to Tube Conversion'!$C:$C,0))/INDEX('Slit to Tube Conversion'!$D:$D,MATCH(B70,'Slit to Tube Conversion'!$C:$C,0)),"")) | J70: =IF(OR(B70="",E70="",I70=""),"",I70*E70) | K70: =IF(B70="","",IF(COUNTIF('Coil to Slit'!$D:$D,B70)>0,"✔ Valid","⚠ Not in Coil to Slit")) | L70: =IF(OR(G70="",B70=""),"",IF(COUNTIFS($G$3:G70,G70,$B$3:B70,B70)>1,"⚠ DUPLICATE","")) | M70: =IF(OR(B70="",E70=""),"",IFERROR(IF(E70>INDEX('Slit to Tube Conversion'!$D:$D,MATCH(B70,'Slit to Tube Conversion'!$C:$C,0)),"⚠ EXCEEDS FG ("&INDEX('Slit to Tube Conversion'!$D:$D,MATCH(B70,'Slit to Tube Conversion'!$C:$C,0))&")","✔ OK"),"Not in FG Conversion"))
D71: =IF(OR(B71="",E71=""),"",IFERROR(INDEX('Slit to Tube Conversion'!$D:$D,MATCH(B71,'Slit to Tube Conversion'!$C:$C,0))-SUMIFS($E$3:E71,$B$3:B71,B71),"")) | F71: =IF(B71="","",F70+1) | G71: =IF(F71="","","BND-"&F71) | I71: =IF(OR(B71="",C71=""),"",IFERROR(INDEX('Slit to Tube Conversion'!$H:$H,MATCH(B71,'Slit to Tube Conversion'!$C:$C,0))/INDEX('Slit to Tube Conversion'!$D:$D,MATCH(B71,'Slit to Tube Conversion'!$C:$C,0)),"")) | J71: =IF(OR(B71="",E71="",I71=""),"",I71*E71) | K71: =IF(B71="","",IF(COUNTIF('Coil to Slit'!$D:$D,B71)>0,"✔ Valid","⚠ Not in Coil to Slit")) | L71: =IF(OR(G71="",B71=""),"",IF(COUNTIFS($G$3:G71,G71,$B$3:B71,B71)>1,"⚠ DUPLICATE","")) | M71: =IF(OR(B71="",E71=""),"",IFERROR(IF(E71>INDEX('Slit to Tube Conversion'!$D:$D,MATCH(B71,'Slit to Tube Conversion'!$C:$C,0)),"⚠ EXCEEDS FG ("&INDEX('Slit to Tube Conversion'!$D:$D,MATCH(B71,'Slit to Tube Conversion'!$C:$C,0))&")","✔ OK"),"Not in FG Conversion"))
D72: =IF(OR(B72="",E72=""),"",IFERROR(INDEX('Slit to Tube Conversion'!$D:$D,MATCH(B72,'Slit to Tube Conversion'!$C:$C,0))-SUMIFS($E$3:E72,$B$3:B72,B72),"")) | F72: =IF(B72="","",F71+1) | G72: =IF(F72="","","BND-"&F72) | I72: =IF(OR(B72="",C72=""),"",IFERROR(INDEX('Slit to Tube Conversion'!$H:$H,MATCH(B72,'Slit to Tube Conversion'!$C:$C,0))/INDEX('Slit to Tube Conversion'!$D:$D,MATCH(B72,'Slit to Tube Conversion'!$C:$C,0)),"")) | J72: =IF(OR(B72="",E72="",I72=""),"",I72*E72) | K72: =IF(B72="","",IF(COUNTIF('Coil to Slit'!$D:$D,B72)>0,"✔ Valid","⚠ Not in Coil to Slit")) | L72: =IF(OR(G72="",B72=""),"",IF(COUNTIFS($G$3:G72,G72,$B$3:B72,B72)>1,"⚠ DUPLICATE","")) | M72: =IF(OR(B72="",E72=""),"",IFERROR(IF(E72>INDEX('Slit to Tube Conversion'!$D:$D,MATCH(B72,'Slit to Tube Conversion'!$C:$C,0)),"⚠ EXCEEDS FG ("&INDEX('Slit to Tube Conversion'!$D:$D,MATCH(B72,'Slit to Tube Conversion'!$C:$C,0))&")","✔ OK"),"Not in FG Conversion"))
D73: =IF(OR(B73="",E73=""),"",IFERROR(INDEX('Slit to Tube Conversion'!$D:$D,MATCH(B73,'Slit to Tube Conversion'!$C:$C,0))-SUMIFS($E$3:E73,$B$3:B73,B73),"")) | F73: =IF(B73="","",F72+1) | G73: =IF(F73="","","BND-"&F73) | I73: =IF(OR(B73="",C73=""),"",IFERROR(INDEX('Slit to Tube Conversion'!$H:$H,MATCH(B73,'Slit to Tube Conversion'!$C:$C,0))/INDEX('Slit to Tube Conversion'!$D:$D,MATCH(B73,'Slit to Tube Conversion'!$C:$C,0)),"")) | J73: =IF(OR(B73="",E73="",I73=""),"",I73*E73) | K73: =IF(B73="","",IF(COUNTIF('Coil to Slit'!$D:$D,B73)>0,"✔ Valid","⚠ Not in Coil to Slit")) | L73: =IF(OR(G73="",B73=""),"",IF(COUNTIFS($G$3:G73,G73,$B$3:B73,B73)>1,"⚠ DUPLICATE","")) | M73: =IF(OR(B73="",E73=""),"",IFERROR(IF(E73>INDEX('Slit to Tube Conversion'!$D:$D,MATCH(B73,'Slit to Tube Conversion'!$C:$C,0)),"⚠ EXCEEDS FG ("&INDEX('Slit to Tube Conversion'!$D:$D,MATCH(B73,'Slit to Tube Conversion'!$C:$C,0))&")","✔ OK"),"Not in FG Conversion"))
D74: =IF(OR(B74="",E74=""),"",IFERROR(INDEX('Slit to Tube Conversion'!$D:$D,MATCH(B74,'Slit to Tube Conversion'!$C:$C,0))-SUMIFS($E$3:E74,$B$3:B74,B74),"")) | F74: =IF(B74="","",F73+1) | G74: =IF(F74="","","BND-"&F74) | I74: =IF(OR(B74="",C74=""),"",IFERROR(INDEX('Slit to Tube Conversion'!$H:$H,MATCH(B74,'Slit to Tube Conversion'!$C:$C,0))/INDEX('Slit to Tube Conversion'!$D:$D,MATCH(B74,'Slit to Tube Conversion'!$C:$C,0)),"")) | J74: =IF(OR(B74="",E74="",I74=""),"",I74*E74) | K74: =IF(B74="","",IF(COUNTIF('Coil to Slit'!$D:$D,B74)>0,"✔ Valid","⚠ Not in Coil to Slit")) | L74: =IF(OR(G74="",B74=""),"",IF(COUNTIFS($G$3:G74,G74,$B$3:B74,B74)>1,"⚠ DUPLICATE","")) | M74: =IF(OR(B74="",E74=""),"",IFERROR(IF(E74>INDEX('Slit to Tube Conversion'!$D:$D,MATCH(B74,'Slit to Tube Conversion'!$C:$C,0)),"⚠ EXCEEDS FG ("&INDEX('Slit to Tube Conversion'!$D:$D,MATCH(B74,'Slit to Tube Conversion'!$C:$C,0))&")","✔ OK"),"Not in FG Conversion"))
D75: =IF(OR(B75="",E75=""),"",IFERROR(INDEX('Slit to Tube Conversion'!$D:$D,MATCH(B75,'Slit to Tube Conversion'!$C:$C,0))-SUMIFS($E$3:E75,$B$3:B75,B75),"")) | F75: =IF(B75="","",F74+1) | G75: =IF(F75="","","BND-"&F75) | I75: =IF(OR(B75="",C75=""),"",IFERROR(INDEX('Slit to Tube Conversion'!$H:$H,MATCH(B75,'Slit to Tube Conversion'!$C:$C,0))/INDEX('Slit to Tube Conversion'!$D:$D,MATCH(B75,'Slit to Tube Conversion'!$C:$C,0)),"")) | J75: =IF(OR(B75="",E75="",I75=""),"",I75*E75) | K75: =IF(B75="","",IF(COUNTIF('Coil to Slit'!$D:$D,B75)>0,"✔ Valid","⚠ Not in Coil to Slit")) | L75: =IF(OR(G75="",B75=""),"",IF(COUNTIFS($G$3:G75,G75,$B$3:B75,B75)>1,"⚠ DUPLICATE","")) | M75: =IF(OR(B75="",E75=""),"",IFERROR(IF(E75>INDEX('Slit to Tube Conversion'!$D:$D,MATCH(B75,'Slit to Tube Conversion'!$C:$C,0)),"⚠ EXCEEDS FG ("&INDEX('Slit to Tube Conversion'!$D:$D,MATCH(B75,'Slit to Tube Conversion'!$C:$C,0))&")","✔ OK"),"Not in FG Conversion"))
D76: =IF(OR(B76="",E76=""),"",IFERROR(INDEX('Slit to Tube Conversion'!$D:$D,MATCH(B76,'Slit to Tube Conversion'!$C:$C,0))-SUMIFS($E$3:E76,$B$3:B76,B76),"")) | F76: =IF(B76="","",F75+1) | G76: =IF(F76="","","BND-"&F76) | I76: =IF(OR(B76="",C76=""),"",IFERROR(INDEX('Slit to Tube Conversion'!$H:$H,MATCH(B76,'Slit to Tube Conversion'!$C:$C,0))/INDEX('Slit to Tube Conversion'!$D:$D,MATCH(B76,'Slit to Tube Conversion'!$C:$C,0)),"")) | J76: =IF(OR(B76="",E76="",I76=""),"",I76*E76) | K76: =IF(B76="","",IF(COUNTIF('Coil to Slit'!$D:$D,B76)>0,"✔ Valid","⚠ Not in Coil to Slit")) | L76: =IF(OR(G76="",B76=""),"",IF(COUNTIFS($G$3:G76,G76,$B$3:B76,B76)>1,"⚠ DUPLICATE","")) | M76: =IF(OR(B76="",E76=""),"",IFERROR(IF(E76>INDEX('Slit to Tube Conversion'!$D:$D,MATCH(B76,'Slit to Tube Conversion'!$C:$C,0)),"⚠ EXCEEDS FG ("&INDEX('Slit to Tube Conversion'!$D:$D,MATCH(B76,'Slit to Tube Conversion'!$C:$C,0))&")","✔ OK"),"Not in FG Conversion"))
... D117: =IF(OR(B117="",E117=""),"",IFERROR(INDEX('Slit to Tube Conversion'!$D:$D,MATCH(B117,'Slit to Tube Conversion'!$C:$C,0))-SUMIFS($E$3:E117,$B$3:B117,B117),"")) | F117: =IF(B117="","",F116+1) | G117: =IF(F117="","","BND-"&F117) | I117: =IF(OR(B117="",C117=""),"",IFERROR(INDEX('Slit to Tube Conversion'!$H:$H,MATCH(B117,'Slit to Tube Conversion'!$C:$C,0))/INDEX('Slit to Tube Conversion'!$D:$D,MATCH(B117,'Slit to Tube Conversion'!$C:$C,0)),"")) | J117: =IF(OR(B117="",E117="",I117=""),"",I117*E117) | K117: =IF(B117="","",IF(COUNTIF('Coil to Slit'!$D:$D,B117)>0,"✔ Valid","⚠ Not in Coil to Slit")) | L117: =IF(OR(G117="",B117=""),"",IF(COUNTIFS($G$3:G117,G117,$B$3:B117,B117)>1,"⚠ DUPLICATE","")) | M117: =IF(OR(B117="",E117=""),"",IFERROR(IF(E117>INDEX('Slit to Tube Conversion'!$D:$D,MATCH(B117,'Slit to Tube Conversion'!$C:$C,0)),"⚠ EXCEEDS FG ("&INDEX('Slit to Tube Conversion'!$D:$D,MATCH(B117,'Slit to Tube Conversion'!$C:$C,0))&")","✔ OK"),"Not in FG Conversion"))

Sheet Dispatch Sheet
A1: 🔵 Manual Entry | G1: 🟢 Auto-Calculated | M1: 🟡 Validation Helpers
A2: Date of Dispatch | B2: Vehicle No. | C2: Invoice No. | D2: Vehicle Weight (T) | E2: SKU Code | F2: Bundle ID | G2: No.of Pieces | H2: Theoretical Weight (T) | I2: Variance (T) | J2: Length (mm) | K2: Width (mm) | L2: Thickness (mm) | M2: Yield Flag | N2: Duplicate Bundle Check
A3: 46112 | B3: TS08UJ6444 | D3: 7.04 | E3: =IF(F3="","",IFERROR(INDEX('Bundle Formation'!$C:$C,MATCH(F3,'Bundle Formation'!$G:$G,0)),"")) -> MS SHS One Helix IS 4923 YSt 210 Black 38x38x2.80x6000 | F3: BND-1 | G3: =IF(F3="","",SUMIF('Bundle Formation'!$G$3:$G$75,F3,'Bundle Formation'!$E$3:$E$75)) -> 110 | H3: =IF(F3="","",SUMIF('Bundle Formation'!$G$3:$G$117,F3,'Bundle Formation'!$J$3:$J$117)) -> 2.1642949 | I3: =IF(OR(D3="",H3=""),"",D3-H3) -> 4.8757051 | J3: =IF(F3="","",IFERROR(INDEX('Slit to Tube Conversion'!$E:$E,MATCH(INDEX('Bundle Formation'!$B$3:$B$117,MATCH(F3,'Bundle Formation'!$G$3:$G$117,0)),'Slit to Tube Conversion'!$C:$C,0)),"")) -> 0 | K3: =IF(F3="","",IFERROR(INDEX('Slit to Tube Conversion'!$F:$F,MATCH(INDEX('Bundle Formation'!$B$3:$B$117,MATCH(F3,'Bundle Formation'!$G$3:$G$117,0)),'Slit to Tube Conversion'!$C:$C,0)),"")) -> 147 | L3: =IF(F3="","",IFERROR(INDEX('Slit to Tube Conversion'!$G:$G,MATCH(INDEX('Bundle Formation'!$B$3:$B$117,MATCH(F3,'Bundle Formation'!$G$3:$G$117,0)),'Slit to Tube Conversion'!$C:$C,0)),"")) -> 2.8 | M3: =IF(OR(F3="",D3="",H3=""),"",IF(H3=0,"",IF(D3/H3<0.85,"🔴 CRITICAL",IF(D3/H3<0.9,"🟠 INVESTIGATE",IF(D3/H3<0.95,"🟡 OPTIMIZE","🟢 GOOD"))))) -> 🟢 GOOD | N3: =IF(F3="","",IF(COUNTIF(F$3:F3,F3)>1,"⚠ DUPLICATE DISPATCH",""))
A4: 46112 | B4: TS08UJ6444 | D4: 7.04 | E4: =IF(F4="","",IFERROR(INDEX('Bundle Formation'!$C:$C,MATCH(F4,'Bundle Formation'!$G:$G,0)),"")) -> MS SHS One Helix IS 4923 YSt 210 Black 38x38x2.80x6000 | F4: BND-2 | G4: =IF(F4="","",SUMIF('Bundle Formation'!$G$3:$G$75,F4,'Bundle Formation'!$E$3:$E$75)) -> 110 | H4: =IF(F4="","",SUMIF('Bundle Formation'!$G$3:$G$117,F4,'Bundle Formation'!$J$3:$J$117)) -> 2.1642949 | I4: =IF(OR(D4="",H4=""),"",D4-H4) -> 4.8757051 | J4: =IF(F4="","",IFERROR(INDEX('Slit to Tube Conversion'!$E:$E,MATCH(INDEX('Bundle Formation'!$B$3:$B$117,MATCH(F4,'Bundle Formation'!$G$3:$G$117,0)),'Slit to Tube Conversion'!$C:$C,0)),"")) -> 0 | K4: =IF(F4="","",IFERROR(INDEX('Slit to Tube Conversion'!$F:$F,MATCH(INDEX('Bundle Formation'!$B$3:$B$117,MATCH(F4,'Bundle Formation'!$G$3:$G$117,0)),'Slit to Tube Conversion'!$C:$C,0)),"")) -> 147 | L4: =IF(F4="","",IFERROR(INDEX('Slit to Tube Conversion'!$G:$G,MATCH(INDEX('Bundle Formation'!$B$3:$B$117,MATCH(F4,'Bundle Formation'!$G$3:$G$117,0)),'Slit to Tube Conversion'!$C:$C,0)),"")) -> 2.8 | M4: =IF(OR(F4="",D4="",H4=""),"",IF(H4=0,"",IF(D4/H4<0.85,"🔴 CRITICAL",IF(D4/H4<0.9,"🟠 INVESTIGATE",IF(D4/H4<0.95,"🟡 OPTIMIZE","🟢 GOOD"))))) -> 🟢 GOOD | N4: =IF(F4="","",IF(COUNTIF(F$3:F4,F4)>1,"⚠ DUPLICATE DISPATCH",""))
A5: 46112 | B5: TS08UJ6444 | D5: 7.04 | F5: BND-11 | G5: =IF(F5="","",SUMIF('Bundle Formation'!$G$3:$G$75,F5,'Bundle Formation'!$E$3:$E$75)) -> 160 | H5: =IF(F5="","",SUMIF('Bundle Formation'!$G$3:$G$117,F5,'Bundle Formation'!$J$3:$J$117)) -> 0 | I5: =IF(OR(D5="",H5=""),"",D5-H5) -> 7.04 | J5: =IF(F5="","",IFERROR(INDEX('Slit to Tube Conversion'!$E:$E,MATCH(INDEX('Bundle Formation'!$B$3:$B$117,MATCH(F5,'Bundle Formation'!$G$3:$G$117,0)),'Slit to Tube Conversion'!$C:$C,0)),"")) -> 0 | K5: =IF(F5="","",IFERROR(INDEX('Slit to Tube Conversion'!$F:$F,MATCH(INDEX('Bundle Formation'!$B$3:$B$117,MATCH(F5,'Bundle Formation'!$G$3:$G$117,0)),'Slit to Tube Conversion'!$C:$C,0)),"")) -> 147 | L5: =IF(F5="","",IFERROR(INDEX('Slit to Tube Conversion'!$G:$G,MATCH(INDEX('Bundle Formation'!$B$3:$B$117,MATCH(F5,'Bundle Formation'!$G$3:$G$117,0)),'Slit to Tube Conversion'!$C:$C,0)),"")) -> 2.8 | M5: =IF(OR(F5="",D5="",H5=""),"",IF(H5=0,"",IF(D5/H5<0.85,"🔴 CRITICAL",IF(D5/H5<0.9,"🟠 INVESTIGATE",IF(D5/H5<0.95,"🟡 OPTIMIZE","🟢 GOOD"))))) | N5: =IF(F5="","",IF(COUNTIF(F$3:F5,F5)>1,"⚠ DUPLICATE DISPATCH",""))
A6: 46112 | B6: TS08UJ6444 | D6: 7.04 | E6: =IF(F6="","",IFERROR(INDEX('Bundle Formation'!$C:$C,MATCH(F6,'Bundle Formation'!$G:$G,0)),"")) -> MS SHS One Helix IS 4923 YSt 210 Black 50x50x2.80x6000 | F6: BND-13 | G6: =IF(F6="","",SUMIF('Bundle Formation'!$G$3:$G$75,F6,'Bundle Formation'!$E$3:$E$75)) -> 80 | H6: =IF(F6="","",SUMIF('Bundle Formation'!$G$3:$G$117,F6,'Bundle Formation'!$J$3:$J$117)) -> 2.0819205 | I6: =IF(OR(D6="",H6=""),"",D6-H6) -> 4.9580795 | J6: =IF(F6="","",IFERROR(INDEX('Slit to Tube Conversion'!$E:$E,MATCH(INDEX('Bundle Formation'!$B$3:$B$117,MATCH(F6,'Bundle Formation'!$G$3:$G$117,0)),'Slit to Tube Conversion'!$C:$C,0)),"")) -> 0 | K6: =IF(F6="","",IFERROR(INDEX('Slit to Tube Conversion'!$F:$F,MATCH(INDEX('Bundle Formation'!$B$3:$B$117,MATCH(F6,'Bundle Formation'!$G$3:$G$117,0)),'Slit to Tube Conversion'!$C:$C,0)),"")) -> 196 | L6: =IF(F6="","",IFERROR(INDEX('Slit to Tube Conversion'!$G:$G,MATCH(INDEX('Bundle Formation'!$B$3:$B$117,MATCH(F6,'Bundle Formation'!$G$3:$G$117,0)),'Slit to Tube Conversion'!$C:$C,0)),"")) -> 2.8 | M6: =IF(OR(F6="",D6="",H6=""),"",IF(H6=0,"",IF(D6/H6<0.85,"🔴 CRITICAL",IF(D6/H6<0.9,"🟠 INVESTIGATE",IF(D6/H6<0.95,"🟡 OPTIMIZE","🟢 GOOD"))))) -> 🟢 GOOD | N6: =IF(F6="","",IF(COUNTIF(F$3:F6,F6)>1,"⚠ DUPLICATE DISPATCH",""))
A7: 46112 | B7: TS08UJ6444 | D7: 7.04 | E7: =IF(F7="","",IFERROR(INDEX('Bundle Formation'!$C:$C,MATCH(F7,'Bundle Formation'!$G:$G,0)),"")) -> MS SHS One Helix IS 4923 YSt 210 Black 38x38x2.20x6000 | F7: BND-29 | G7: =IF(F7="","",SUMIF('Bundle Formation'!$G$3:$G$75,F7,'Bundle Formation'!$E$3:$E$75)) -> 144 | H7: =IF(F7="","",SUMIF('Bundle Formation'!$G$3:$G$117,F7,'Bundle Formation'!$J$3:$J$117)) -> 2.2138984 | I7: =IF(OR(D7="",H7=""),"",D7-H7) -> 4.8261016 | J7: =IF(F7="","",IFERROR(INDEX('Slit to Tube Conversion'!$E:$E,MATCH(INDEX('Bundle Formation'!$B$3:$B$117,MATCH(F7,'Bundle Formation'!$G$3:$G$117,0)),'Slit to Tube Conversion'!$C:$C,0)),"")) -> 0 | K7: =IF(F7="","",IFERROR(INDEX('Slit to Tube Conversion'!$F:$F,MATCH(INDEX('Bundle Formation'!$B$3:$B$117,MATCH(F7,'Bundle Formation'!$G$3:$G$117,0)),'Slit to Tube Conversion'!$C:$C,0)),"")) -> 148 | L7: =IF(F7="","",IFERROR(INDEX('Slit to Tube Conversion'!$G:$G,MATCH(INDEX('Bundle Formation'!$B$3:$B$117,MATCH(F7,'Bundle Formation'!$G$3:$G$117,0)),'Slit to Tube Conversion'!$C:$C,0)),"")) -> 2.2 | M7: =IF(OR(F7="",D7="",H7=""),"",IF(H7=0,"",IF(D7/H7<0.85,"🔴 CRITICAL",IF(D7/H7<0.9,"🟠 INVESTIGATE",IF(D7/H7<0.95,"🟡 OPTIMIZE","🟢 GOOD"))))) -> 🟢 GOOD | N7: =IF(F7="","",IF(COUNTIF(F$3:F7,F7)>1,"⚠ DUPLICATE DISPATCH",""))
A8: 46112 | B8: TS08UJ6444 | D8: 7.04 | E8: =IF(F8="","",IFERROR(INDEX('Bundle Formation'!$C:$C,MATCH(F8,'Bundle Formation'!$G:$G,0)),"")) -> MS SHS One Helix IS 4923 YSt 210 Black 38x38x2.20x6000 | F8: BND-31 | G8: =IF(F8="","",SUMIF('Bundle Formation'!$G$3:$G$75,F8,'Bundle Formation'!$E$3:$E$75)) -> 52 | H8: =IF(F8="","",SUMIF('Bundle Formation'!$G$3:$G$117,F8,'Bundle Formation'!$J$3:$J$117)) -> 0.7994633 | I8: =IF(OR(D8="",H8=""),"",D8-H8) -> 6.2405367 | J8: =IF(F8="","",IFERROR(INDEX('Slit to Tube Conversion'!$E:$E,MATCH(INDEX('Bundle Formation'!$B$3:$B$117,MATCH(F8,'Bundle Formation'!$G$3:$G$117,0)),'Slit to Tube Conversion'!$C:$C,0)),"")) -> 0 | K8: =IF(F8="","",IFERROR(INDEX('Slit to Tube Conversion'!$F:$F,MATCH(INDEX('Bundle Formation'!$B$3:$B$117,MATCH(F8,'Bundle Formation'!$G$3:$G$117,0)),'Slit to Tube Conversion'!$C:$C,0)),"")) -> 148 | L8: =IF(F8="","",IFERROR(INDEX('Slit to Tube Conversion'!$G:$G,MATCH(INDEX('Bundle Formation'!$B$3:$B$117,MATCH(F8,'Bundle Formation'!$G$3:$G$117,0)),'Slit to Tube Conversion'!$C:$C,0)),"")) -> 2.2 | M8: =IF(OR(F8="",D8="",H8=""),"",IF(H8=0,"",IF(D8/H8<0.85,"🔴 CRITICAL",IF(D8/H8<0.9,"🟠 INVESTIGATE",IF(D8/H8<0.95,"🟡 OPTIMIZE","🟢 GOOD"))))) -> 🟢 GOOD | N8: =IF(F8="","",IF(COUNTIF(F$3:F8,F8)>1,"⚠ DUPLICATE DISPATCH",""))
A9: 46112 | B9: TS08UJ6444 | D9: 7.04 | E9: =IF(F9="","",IFERROR(INDEX('Bundle Formation'!$C:$C,MATCH(F9,'Bundle Formation'!$G:$G,0)),"")) -> MS SHS One Helix IS 4923 YSt 210 Black 50x50x2.20x6000 | F9: BND-37 | G9: =IF(F9="","",SUMIF('Bundle Formation'!$G$3:$G$75,F9,'Bundle Formation'!$E$3:$E$75)) -> 110 | H9: =IF(F9="","",SUMIF('Bundle Formation'!$G$3:$G$117,F9,'Bundle Formation'!$J$3:$J$117)) -> 2.3144984 | I9: =IF(OR(D9="",H9=""),"",D9-H9) -> 4.7255016 | J9: =IF(F9="","",IFERROR(INDEX('Slit to Tube Conversion'!$E:$E,MATCH(INDEX('Bundle Formation'!$B$3:$B$117,MATCH(F9,'Bundle Formation'!$G$3:$G$117,0)),'Slit to Tube Conversion'!$C:$C,0)),"")) -> 0 | K9: =IF(F9="","",IFERROR(INDEX('Slit to Tube Conversion'!$F:$F,MATCH(INDEX('Bundle Formation'!$B$3:$B$117,MATCH(F9,'Bundle Formation'!$G$3:$G$117,0)),'Slit to Tube Conversion'!$C:$C,0)),"")) -> 197 | L9: =IF(F9="","",IFERROR(INDEX('Slit to Tube Conversion'!$G:$G,MATCH(INDEX('Bundle Formation'!$B$3:$B$117,MATCH(F9,'Bundle Formation'!$G$3:$G$117,0)),'Slit to Tube Conversion'!$C:$C,0)),"")) -> 2.2 | M9: =IF(OR(F9="",D9="",H9=""),"",IF(H9=0,"",IF(D9/H9<0.85,"🔴 CRITICAL",IF(D9/H9<0.9,"🟠 INVESTIGATE",IF(D9/H9<0.95,"🟡 OPTIMIZE","🟢 GOOD"))))) -> 🟢 GOOD | N9: =IF(F9="","",IF(COUNTIF(F$3:F9,F9)>1,"⚠ DUPLICATE DISPATCH",""))
A10: 46112 | B10: TS08UJ6444 | D10: 7.04 | E10: =IF(F10="","",IFERROR(INDEX('Bundle Formation'!$C:$C,MATCH(F10,'Bundle Formation'!$G:$G,0)),"")) | F10: BND-39 | G10: =IF(F10="","",SUMIF('Bundle Formation'!$G$3:$G$75,F10,'Bundle Formation'!$E$3:$E$75)) -> 0 | H10: =IF(F10="","",SUMIF('Bundle Formation'!$G$3:$G$117,F10,'Bundle Formation'!$J$3:$J$117)) -> 0 | I10: =IF(OR(D10="",H10=""),"",D10-H10) -> 7.04 | J10: =IF(F10="","",IFERROR(INDEX('Slit to Tube Conversion'!$E:$E,MATCH(INDEX('Bundle Formation'!$B$3:$B$117,MATCH(F10,'Bundle Formation'!$G$3:$G$117,0)),'Slit to Tube Conversion'!$C:$C,0)),"")) | K10: =IF(F10="","",IFERROR(INDEX('Slit to Tube Conversion'!$F:$F,MATCH(INDEX('Bundle Formation'!$B$3:$B$117,MATCH(F10,'Bundle Formation'!$G$3:$G$117,0)),'Slit to Tube Conversion'!$C:$C,0)),"")) | L10: =IF(F10="","",IFERROR(INDEX('Slit to Tube Conversion'!$G:$G,MATCH(INDEX('Bundle Formation'!$B$3:$B$117,MATCH(F10,'Bundle Formation'!$G$3:$G$117,0)),'Slit to Tube Conversion'!$C:$C,0)),"")) | M10: =IF(OR(F10="",D10="",H10=""),"",IF(H10=0,"",IF(D10/H10<0.85,"🔴 CRITICAL",IF(D10/H10<0.9,"🟠 INVESTIGATE",IF(D10/H10<0.95,"🟡 OPTIMIZE","🟢 GOOD"))))) | N10: =IF(F10="","",IF(COUNTIF(F$3:F10,F10)>1,"⚠ DUPLICATE DISPATCH",""))
A11: 46115 | B11: KA37B3630 | D11: 13.72 | E11: =IF(F11="","",IFERROR(INDEX('Bundle Formation'!$C:$C,MATCH(F11,'Bundle Formation'!$G:$G,0)),"")) -> MS SHS One Helix IS 4923 YSt 210 Black 38x38x2.20x6000 | F11: BND-33 | G11: =IF(F11="","",SUMIF('Bundle Formation'!$G$3:$G$75,F11,'Bundle Formation'!$E$3:$E$75)) -> 144 | H11: =IF(F11="","",SUMIF('Bundle Formation'!$G$3:$G$117,F11,'Bundle Formation'!$J$3:$J$117)) -> 2.2138984 | I11: =IF(OR(D11="",H11=""),"",D11-H11) -> 11.506102 | J11: =IF(F11="","",IFERROR(INDEX('Slit to Tube Conversion'!$E:$E,MATCH(INDEX('Bundle Formation'!$B$3:$B$117,MATCH(F11,'Bundle Formation'!$G$3:$G$117,0)),'Slit to Tube Conversion'!$C:$C,0)),"")) -> 0 | K11: =IF(F11="","",IFERROR(INDEX('Slit to Tube Conversion'!$F:$F,MATCH(INDEX('Bundle Formation'!$B$3:$B$117,MATCH(F11,'Bundle Formation'!$G$3:$G$117,0)),'Slit to Tube Conversion'!$C:$C,0)),"")) -> 148 | L11: =IF(F11="","",IFERROR(INDEX('Slit to Tube Conversion'!$G:$G,MATCH(INDEX('Bundle Formation'!$B$3:$B$117,MATCH(F11,'Bundle Formation'!$G$3:$G$117,0)),'Slit to Tube Conversion'!$C:$C,0)),"")) -> 2.2 | M11: =IF(OR(F11="",D11="",H11=""),"",IF(H11=0,"",IF(D11/H11<0.85,"🔴 CRITICAL",IF(D11/H11<0.9,"🟠 INVESTIGATE",IF(D11/H11<0.95,"🟡 OPTIMIZE","🟢 GOOD"))))) -> 🟢 GOOD | N11: =IF(F11="","",IF(COUNTIF(F$3:F11,F11)>1,"⚠ DUPLICATE DISPATCH",""))
A12: 46115 | B12: KA37B3630 | D12: 13.72 | E12: =IF(F12="","",IFERROR(INDEX('Bundle Formation'!$C:$C,MATCH(F12,'Bundle Formation'!$G:$G,0)),"")) -> MS SHS One Helix IS 4923 YSt 210 Black 38x38x2.20x6000 | F12: BND-35 | G12: =IF(F12="","",SUMIF('Bundle Formation'!$G$3:$G$75,F12,'Bundle Formation'!$E$3:$E$75)) -> 144 | H12: =IF(F12="","",SUMIF('Bundle Formation'!$G$3:$G$117,F12,'Bundle Formation'!$J$3:$J$117)) -> 2.2240539 | I12: =IF(OR(D12="",H12=""),"",D12-H12) -> 11.495946 | J12: =IF(F12="","",IFERROR(INDEX('Slit to Tube Conversion'!$E:$E,MATCH(INDEX('Bundle Formation'!$B$3:$B$117,MATCH(F12,'Bundle Formation'!$G$3:$G$117,0)),'Slit to Tube Conversion'!$C:$C,0)),"")) -> 0 | K12: =IF(F12="","",IFERROR(INDEX('Slit to Tube Conversion'!$F:$F,MATCH(INDEX('Bundle Formation'!$B$3:$B$117,MATCH(F12,'Bundle Formation'!$G$3:$G$117,0)),'Slit to Tube Conversion'!$C:$C,0)),"")) -> 148 | L12: =IF(F12="","",IFERROR(INDEX('Slit to Tube Conversion'!$G:$G,MATCH(INDEX('Bundle Formation'!$B$3:$B$117,MATCH(F12,'Bundle Formation'!$G$3:$G$117,0)),'Slit to Tube Conversion'!$C:$C,0)),"")) -> 2.2 | M12: =IF(OR(F12="",D12="",H12=""),"",IF(H12=0,"",IF(D12/H12<0.85,"🔴 CRITICAL",IF(D12/H12<0.9,"🟠 INVESTIGATE",IF(D12/H12<0.95,"🟡 OPTIMIZE","🟢 GOOD"))))) -> 🟢 GOOD | N12: =IF(F12="","",IF(COUNTIF(F$3:F12,F12)>1,"⚠ DUPLICATE DISPATCH",""))
A13: 46115 | B13: KA37B3630 | D13: 13.72 | E13: =IF(F13="","",IFERROR(INDEX('Bundle Formation'!$C:$C,MATCH(F13,'Bundle Formation'!$G:$G,0)),"")) -> MS SHS One Helix IS 4923 YSt 210 Black 50x50x2.20x6000 | F13: BND-36 | G13: =IF(F13="","",SUMIF('Bundle Formation'!$G$3:$G$75,F13,'Bundle Formation'!$E$3:$E$75)) -> 110 | H13: =IF(F13="","",SUMIF('Bundle Formation'!$G$3:$G$117,F13,'Bundle Formation'!$J$3:$J$117)) -> 2.3144984 | I13: =IF(OR(D13="",H13=""),"",D13-H13) -> 11.405502 | J13: =IF(F13="","",IFERROR(INDEX('Slit to Tube Conversion'!$E:$E,MATCH(INDEX('Bundle Formation'!$B$3:$B$117,MATCH(F13,'Bundle Formation'!$G$3:$G$117,0)),'Slit to Tube Conversion'!$C:$C,0)),"")) -> 0 | K13: =IF(F13="","",IFERROR(INDEX('Slit to Tube Conversion'!$F:$F,MATCH(INDEX('Bundle Formation'!$B$3:$B$117,MATCH(F13,'Bundle Formation'!$G$3:$G$117,0)),'Slit to Tube Conversion'!$C:$C,0)),"")) -> 197 | L13: =IF(F13="","",IFERROR(INDEX('Slit to Tube Conversion'!$G:$G,MATCH(INDEX('Bundle Formation'!$B$3:$B$117,MATCH(F13,'Bundle Formation'!$G$3:$G$117,0)),'Slit to Tube Conversion'!$C:$C,0)),"")) -> 2.2 | M13: =IF(OR(F13="",D13="",H13=""),"",IF(H13=0,"",IF(D13/H13<0.85,"🔴 CRITICAL",IF(D13/H13<0.9,"🟠 INVESTIGATE",IF(D13/H13<0.95,"🟡 OPTIMIZE","🟢 GOOD"))))) -> 🟢 GOOD | N13: =IF(F13="","",IF(COUNTIF(F$3:F13,F13)>1,"⚠ DUPLICATE DISPATCH",""))
A14: 46115 | B14: KA37B3630 | D14: 13.72 | E14: =IF(F14="","",IFERROR(INDEX('Bundle Formation'!$C:$C,MATCH(F14,'Bundle Formation'!$G:$G,0)),"")) -> MS SHS One Helix IS 4923 YSt 210 Black 38x38x2.20x6000 | F14: BND-34 | G14: =IF(F14="","",SUMIF('Bundle Formation'!$G$3:$G$75,F14,'Bundle Formation'!$E$3:$E$75)) -> 144 | H14: =IF(F14="","",SUMIF('Bundle Formation'!$G$3:$G$117,F14,'Bundle Formation'!$J$3:$J$117)) -> 2.2167193 | I14: =IF(OR(D14="",H14=""),"",D14-H14) -> 11.503281 | J14: =IF(F14="","",IFERROR(INDEX('Slit to Tube Conversion'!$E:$E,MATCH(INDEX('Bundle Formation'!$B$3:$B$117,MATCH(F14,'Bundle Formation'!$G$3:$G$117,0)),'Slit to Tube Conversion'!$C:$C,0)),"")) -> 0 | K14: =IF(F14="","",IFERROR(INDEX('Slit to Tube Conversion'!$F:$F,MATCH(INDEX('Bundle Formation'!$B$3:$B$117,MATCH(F14,'Bundle Formation'!$G$3:$G$117,0)),'Slit to Tube Conversion'!$C:$C,0)),"")) -> 148 | L14: =IF(F14="","",IFERROR(INDEX('Slit to Tube Conversion'!$G:$G,MATCH(INDEX('Bundle Formation'!$B$3:$B$117,MATCH(F14,'Bundle Formation'!$G$3:$G$117,0)),'Slit to Tube Conversion'!$C:$C,0)),"")) -> 2.2 | M14: =IF(OR(F14="",D14="",H14=""),"",IF(H14=0,"",IF(D14/H14<0.85,"🔴 CRITICAL",IF(D14/H14<0.9,"🟠 INVESTIGATE",IF(D14/H14<0.95,"🟡 OPTIMIZE","🟢 GOOD"))))) -> 🟢 GOOD | N14: =IF(F14="","",IF(COUNTIF(F$3:F14,F14)>1,"⚠ DUPLICATE DISPATCH",""))
A15: 46115 | B15: KA37B3630 | D15: 13.72 | E15: =IF(F15="","",IFERROR(INDEX('Bundle Formation'!$C:$C,MATCH(F15,'Bundle Formation'!$G:$G,0)),"")) -> MS SHS One Helix IS 4923 YSt 210 Black 38x38x2.20x6000 | F15: BND-32 | G15: =IF(F15="","",SUMIF('Bundle Formation'!$G$3:$G$75,F15,'Bundle Formation'!$E$3:$E$75)) -> 144 | H15: =IF(F15="","",SUMIF('Bundle Formation'!$G$3:$G$117,F15,'Bundle Formation'!$J$3:$J$117)) -> 2.2138984 | I15: =IF(OR(D15="",H15=""),"",D15-H15) -> 11.506102 | J15: =IF(F15="","",IFERROR(INDEX('Slit to Tube Conversion'!$E:$E,MATCH(INDEX('Bundle Formation'!$B$3:$B$117,MATCH(F15,'Bundle Formation'!$G$3:$G$117,0)),'Slit to Tube Conversion'!$C:$C,0)),"")) -> 0 | K15: =IF(F15="","",IFERROR(INDEX('Slit to Tube Conversion'!$F:$F,MATCH(INDEX('Bundle Formation'!$B$3:$B$117,MATCH(F15,'Bundle Formation'!$G$3:$G$117,0)),'Slit to Tube Conversion'!$C:$C,0)),"")) -> 148 | L15: =IF(F15="","",IFERROR(INDEX('Slit to Tube Conversion'!$G:$G,MATCH(INDEX('Bundle Formation'!$B$3:$B$117,MATCH(F15,'Bundle Formation'!$G$3:$G$117,0)),'Slit to Tube Conversion'!$C:$C,0)),"")) -> 2.2 | M15: =IF(OR(F15="",D15="",H15=""),"",IF(H15=0,"",IF(D15/H15<0.85,"🔴 CRITICAL",IF(D15/H15<0.9,"🟠 INVESTIGATE",IF(D15/H15<0.95,"🟡 OPTIMIZE","🟢 GOOD"))))) -> 🟢 GOOD | N15: =IF(F15="","",IF(COUNTIF(F$3:F15,F15)>1,"⚠ DUPLICATE DISPATCH",""))
A16: 46115 | B16: KA37B3630 | D16: 13.72 | E16: =IF(F16="","",IFERROR(INDEX('Bundle Formation'!$C:$C,MATCH(F16,'Bundle Formation'!$G:$G,0)),"")) | F16: BND-41 | G16: =IF(F16="","",SUMIF('Bundle Formation'!$G$3:$G$75,F16,'Bundle Formation'!$E$3:$E$75)) -> 0 | H16: =IF(F16="","",SUMIF('Bundle Formation'!$G$3:$G$117,F16,'Bundle Formation'!$J$3:$J$117)) -> 0 | I16: =IF(OR(D16="",H16=""),"",D16-H16) -> 13.72 | J16: =IF(F16="","",IFERROR(INDEX('Slit to Tube Conversion'!$E:$E,MATCH(INDEX('Bundle Formation'!$B$3:$B$117,MATCH(F16,'Bundle Formation'!$G$3:$G$117,0)),'Slit to Tube Conversion'!$C:$C,0)),"")) | K16: =IF(F16="","",IFERROR(INDEX('Slit to Tube Conversion'!$F:$F,MATCH(INDEX('Bundle Formation'!$B$3:$B$117,MATCH(F16,'Bundle Formation'!$G$3:$G$117,0)),'Slit to Tube Conversion'!$C:$C,0)),"")) | L16: =IF(F16="","",IFERROR(INDEX('Slit to Tube Conversion'!$G:$G,MATCH(INDEX('Bundle Formation'!$B$3:$B$117,MATCH(F16,'Bundle Formation'!$G$3:$G$117,0)),'Slit to Tube Conversion'!$C:$C,0)),"")) | M16: =IF(OR(F16="",D16="",H16=""),"",IF(H16=0,"",IF(D16/H16<0.85,"🔴 CRITICAL",IF(D16/H16<0.9,"🟠 INVESTIGATE",IF(D16/H16<0.95,"🟡 OPTIMIZE","🟢 GOOD"))))) | N16: =IF(F16="","",IF(COUNTIF(F$3:F16,F16)>1,"⚠ DUPLICATE DISPATCH",""))
A17: 46115 | B17: KA37B3630 | D17: 13.72 | E17: =IF(F17="","",IFERROR(INDEX('Bundle Formation'!$C:$C,MATCH(F17,'Bundle Formation'!$G:$G,0)),"")) -> MS SHS One Helix IS 4923 YSt 210 Black 50x50x2.50x6000 | F17: BND-25 | G17: =IF(F17="","",SUMIF('Bundle Formation'!$G$3:$G$75,F17,'Bundle Formation'!$E$3:$E$75)) -> 90 | H17: =IF(F17="","",SUMIF('Bundle Formation'!$G$3:$G$117,F17,'Bundle Formation'!$J$3:$J$117)) -> 2.1470894 | I17: =IF(OR(D17="",H17=""),"",D17-H17) -> 11.572911 | J17: =IF(F17="","",IFERROR(INDEX('Slit to Tube Conversion'!$E:$E,MATCH(INDEX('Bundle Formation'!$B$3:$B$117,MATCH(F17,'Bundle Formation'!$G$3:$G$117,0)),'Slit to Tube Conversion'!$C:$C,0)),"")) -> 0 | K17: =IF(F17="","",IFERROR(INDEX('Slit to Tube Conversion'!$F:$F,MATCH(INDEX('Bundle Formation'!$B$3:$B$117,MATCH(F17,'Bundle Formation'!$G$3:$G$117,0)),'Slit to Tube Conversion'!$C:$C,0)),"")) -> 196 | L17: =IF(F17="","",IFERROR(INDEX('Slit to Tube Conversion'!$G:$G,MATCH(INDEX('Bundle Formation'!$B$3:$B$117,MATCH(F17,'Bundle Formation'!$G$3:$G$117,0)),'Slit to Tube Conversion'!$C:$C,0)),"")) -> 2.5 | M17: =IF(OR(F17="",D17="",H17=""),"",IF(H17=0,"",IF(D17/H17<0.85,"🔴 CRITICAL",IF(D17/H17<0.9,"🟠 INVESTIGATE",IF(D17/H17<0.95,"🟡 OPTIMIZE","🟢 GOOD"))))) -> 🟢 GOOD | N17: =IF(F17="","",IF(COUNTIF(F$3:F17,F17)>1,"⚠ DUPLICATE DISPATCH",""))
... A40: 46115 | B40: KA37B3630 | D40: 13.72 | E40: =IF(F40="","",IFERROR(INDEX('Bundle Formation'!$C:$C,MATCH(F40,'Bundle Formation'!$G:$G,0)),"")) -> MS SHS One Helix IS 4923 YSt 210 Black 50x50x2.50x6000 | F40: BND-24 | G40: =IF(F40="","",SUMIF('Bundle Formation'!$G$3:$G$75,F40,'Bundle Formation'!$E$3:$E$75)) -> 90 | H40: =IF(F40="","",SUMIF('Bundle Formation'!$G$3:$G$117,F40,'Bundle Formation'!$J$3:$J$117)) -> 2.1470894 | I40: =IF(OR(D40="",H40=""),"",D40-H40) -> 11.572911 | J40: =IF(F40="","",IFERROR(INDEX('Slit to Tube Conversion'!$E:$E,MATCH(INDEX('Bundle Formation'!$B$3:$B$117,MATCH(F40,'Bundle Formation'!$G$3:$G$117,0)),'Slit to Tube Conversion'!$C:$C,0)),"")) -> 0 | K40: =IF(F40="","",IFERROR(INDEX('Slit to Tube Conversion'!$F:$F,MATCH(INDEX('Bundle Formation'!$B$3:$B$117,MATCH(F40,'Bundle Formation'!$G$3:$G$117,0)),'Slit to Tube Conversion'!$C:$C,0)),"")) -> 196 | L40: =IF(F40="","",IFERROR(INDEX('Slit to Tube Conversion'!$G:$G,MATCH(INDEX('Bundle Formation'!$B$3:$B$117,MATCH(F40,'Bundle Formation'!$G$3:$G$117,0)),'Slit to Tube Conversion'!$C:$C,0)),"")) -> 2.5 | M40: =IF(OR(F40="",D40="",H40=""),"",IF(H40=0,"",IF(D40/H40<0.85,"🔴 CRITICAL",IF(D40/H40<0.9,"🟠 INVESTIGATE",IF(D40/H40<0.95,"🟡 OPTIMIZE","🟢 GOOD"))))) -> 🟢 GOOD | N40: =IF(F40="","",IF(COUNTIF(F$3:F40,F40)>1,"⚠ DUPLICATE DISPATCH",""))
E41: =IF(F41="","",IFERROR(INDEX('Bundle Formation'!$C:$C,MATCH(F41,'Bundle Formation'!$G:$G,0)),"")) | G41: =IF(F41="","",SUMIF('Bundle Formation'!$G$3:$G$75,F41,'Bundle Formation'!$E$3:$E$75)) | H41: =IF(F41="","",SUMIF('Bundle Formation'!$G$3:$G$117,F41,'Bundle Formation'!$J$3:$J$117)) | I41: =IF(OR(D41="",H41=""),"",D41-H41) | J41: =IF(F41="","",IFERROR(INDEX('Slit to Tube Conversion'!$E:$E,MATCH(INDEX('Bundle Formation'!$B$3:$B$117,MATCH(F41,'Bundle Formation'!$G$3:$G$117,0)),'Slit to Tube Conversion'!$C:$C,0)),"")) | K41: =IF(F41="","",IFERROR(INDEX('Slit to Tube Conversion'!$F:$F,MATCH(INDEX('Bundle Formation'!$B$3:$B$117,MATCH(F41,'Bundle Formation'!$G$3:$G$117,0)),'Slit to Tube Conversion'!$C:$C,0)),"")) | L41: =IF(F41="","",IFERROR(INDEX('Slit to Tube Conversion'!$G:$G,MATCH(INDEX('Bundle Formation'!$B$3:$B$117,MATCH(F41,'Bundle Formation'!$G$3:$G$117,0)),'Slit to Tube Conversion'!$C:$C,0)),"")) | M41: =IF(OR(F41="",D41="",H41=""),"",IF(H41=0,"",IF(D41/H41<0.85,"🔴 CRITICAL",IF(D41/H41<0.9,"🟠 INVESTIGATE",IF(D41/H41<0.95,"🟡 OPTIMIZE","🟢 GOOD"))))) | N41: =IF(F41="","",IF(COUNTIF(F$3:F41,F41)>1,"⚠ DUPLICATE DISPATCH",""))
E42: =IF(F42="","",IFERROR(INDEX('Bundle Formation'!$C:$C,MATCH(F42,'Bundle Formation'!$G:$G,0)),"")) | G42: =IF(F42="","",SUMIF('Bundle Formation'!$G$3:$G$75,F42,'Bundle Formation'!$E$3:$E$75)) | H42: =IF(F42="","",SUMIF('Bundle Formation'!$G$3:$G$117,F42,'Bundle Formation'!$J$3:$J$117)) | I42: =IF(OR(D42="",H42=""),"",D42-H42) | J42: =IF(F42="","",IFERROR(INDEX('Slit to Tube Conversion'!$E:$E,MATCH(INDEX('Bundle Formation'!$B$3:$B$117,MATCH(F42,'Bundle Formation'!$G$3:$G$117,0)),'Slit to Tube Conversion'!$C:$C,0)),"")) | K42: =IF(F42="","",IFERROR(INDEX('Slit to Tube Conversion'!$F:$F,MATCH(INDEX('Bundle Formation'!$B$3:$B$117,MATCH(F42,'Bundle Formation'!$G$3:$G$117,0)),'Slit to Tube Conversion'!$C:$C,0)),"")) | L42: =IF(F42="","",IFERROR(INDEX('Slit to Tube Conversion'!$G:$G,MATCH(INDEX('Bundle Formation'!$B$3:$B$117,MATCH(F42,'Bundle Formation'!$G$3:$G$117,0)),'Slit to Tube Conversion'!$C:$C,0)),"")) | M42: =IF(OR(F42="",D42="",H42=""),"",IF(H42=0,"",IF(D42/H42<0.85,"🔴 CRITICAL",IF(D42/H42<0.9,"🟠 INVESTIGATE",IF(D42/H42<0.95,"🟡 OPTIMIZE","🟢 GOOD"))))) | N42: =IF(F42="","",IF(COUNTIF(F$3:F42,F42)>1,"⚠ DUPLICATE DISPATCH",""))
E43: =IF(F43="","",IFERROR(INDEX('Bundle Formation'!$C:$C,MATCH(F43,'Bundle Formation'!$G:$G,0)),"")) | G43: =IF(F43="","",SUMIF('Bundle Formation'!$G$3:$G$75,F43,'Bundle Formation'!$E$3:$E$75)) | H43: =IF(F43="","",SUMIF('Bundle Formation'!$G$3:$G$117,F43,'Bundle Formation'!$J$3:$J$117)) | I43: =IF(OR(D43="",H43=""),"",D43-H43) | J43: =IF(F43="","",IFERROR(INDEX('Slit to Tube Conversion'!$E:$E,MATCH(INDEX('Bundle Formation'!$B$3:$B$117,MATCH(F43,'Bundle Formation'!$G$3:$G$117,0)),'Slit to Tube Conversion'!$C:$C,0)),"")) | K43: =IF(F43="","",IFERROR(INDEX('Slit to Tube Conversion'!$F:$F,MATCH(INDEX('Bundle Formation'!$B$3:$B$117,MATCH(F43,'Bundle Formation'!$G$3:$G$117,0)),'Slit to Tube Conversion'!$C:$C,0)),"")) | L43: =IF(F43="","",IFERROR(INDEX('Slit to Tube Conversion'!$G:$G,MATCH(INDEX('Bundle Formation'!$B$3:$B$117,MATCH(F43,'Bundle Formation'!$G$3:$G$117,0)),'Slit to Tube Conversion'!$C:$C,0)),"")) | M43: =IF(OR(F43="",D43="",H43=""),"",IF(H43=0,"",IF(D43/H43<0.85,"🔴 CRITICAL",IF(D43/H43<0.9,"🟠 INVESTIGATE",IF(D43/H43<0.95,"🟡 OPTIMIZE","🟢 GOOD"))))) | N43: =IF(F43="","",IF(COUNTIF(F$3:F43,F43)>1,"⚠ DUPLICATE DISPATCH",""))
E44: =IF(F44="","",IFERROR(INDEX('Bundle Formation'!$C:$C,MATCH(F44,'Bundle Formation'!$G:$G,0)),"")) | G44: =IF(F44="","",SUMIF('Bundle Formation'!$G$3:$G$75,F44,'Bundle Formation'!$E$3:$E$75)) | H44: =IF(F44="","",SUMIF('Bundle Formation'!$G$3:$G$117,F44,'Bundle Formation'!$J$3:$J$117)) | I44: =IF(OR(D44="",H44=""),"",D44-H44) | J44: =IF(F44="","",IFERROR(INDEX('Slit to Tube Conversion'!$E:$E,MATCH(INDEX('Bundle Formation'!$B$3:$B$117,MATCH(F44,'Bundle Formation'!$G$3:$G$117,0)),'Slit to Tube Conversion'!$C:$C,0)),"")) | K44: =IF(F44="","",IFERROR(INDEX('Slit to Tube Conversion'!$F:$F,MATCH(INDEX('Bundle Formation'!$B$3:$B$117,MATCH(F44,'Bundle Formation'!$G$3:$G$117,0)),'Slit to Tube Conversion'!$C:$C,0)),"")) | L44: =IF(F44="","",IFERROR(INDEX('Slit to Tube Conversion'!$G:$G,MATCH(INDEX('Bundle Formation'!$B$3:$B$117,MATCH(F44,'Bundle Formation'!$G$3:$G$117,0)),'Slit to Tube Conversion'!$C:$C,0)),"")) | M44: =IF(OR(F44="",D44="",H44=""),"",IF(H44=0,"",IF(D44/H44<0.85,"🔴 CRITICAL",IF(D44/H44<0.9,"🟠 INVESTIGATE",IF(D44/H44<0.95,"🟡 OPTIMIZE","🟢 GOOD"))))) | N44: =IF(F44="","",IF(COUNTIF(F$3:F44,F44)>1,"⚠ DUPLICATE DISPATCH",""))
E45: =IF(F45="","",IFERROR(INDEX('Bundle Formation'!$C:$C,MATCH(F45,'Bundle Formation'!$G:$G,0)),"")) | G45: =IF(F45="","",SUMIF('Bundle Formation'!$G$3:$G$75,F45,'Bundle Formation'!$E$3:$E$75)) | H45: =IF(F45="","",SUMIF('Bundle Formation'!$G$3:$G$117,F45,'Bundle Formation'!$J$3:$J$117)) | I45: =IF(OR(D45="",H45=""),"",D45-H45) | J45: =IF(F45="","",IFERROR(INDEX('Slit to Tube Conversion'!$E:$E,MATCH(INDEX('Bundle Formation'!$B$3:$B$117,MATCH(F45,'Bundle Formation'!$G$3:$G$117,0)),'Slit to Tube Conversion'!$C:$C,0)),"")) | K45: =IF(F45="","",IFERROR(INDEX('Slit to Tube Conversion'!$F:$F,MATCH(INDEX('Bundle Formation'!$B$3:$B$117,MATCH(F45,'Bundle Formation'!$G$3:$G$117,0)),'Slit to Tube Conversion'!$C:$C,0)),"")) | L45: =IF(F45="","",IFERROR(INDEX('Slit to Tube Conversion'!$G:$G,MATCH(INDEX('Bundle Formation'!$B$3:$B$117,MATCH(F45,'Bundle Formation'!$G$3:$G$117,0)),'Slit to Tube Conversion'!$C:$C,0)),"")) | M45: =IF(OR(F45="",D45="",H45=""),"",IF(H45=0,"",IF(D45/H45<0.85,"🔴 CRITICAL",IF(D45/H45<0.9,"🟠 INVESTIGATE",IF(D45/H45<0.95,"🟡 OPTIMIZE","🟢 GOOD"))))) | N45: =IF(F45="","",IF(COUNTIF(F$3:F45,F45)>1,"⚠ DUPLICATE DISPATCH",""))
E46: =IF(F46="","",IFERROR(INDEX('Bundle Formation'!$C:$C,MATCH(F46,'Bundle Formation'!$G:$G,0)),"")) | G46: =IF(F46="","",SUMIF('Bundle Formation'!$G$3:$G$75,F46,'Bundle Formation'!$E$3:$E$75)) | H46: =IF(F46="","",SUMIF('Bundle Formation'!$G$3:$G$117,F46,'Bundle Formation'!$J$3:$J$117)) | I46: =IF(OR(D46="",H46=""),"",D46-H46) | J46: =IF(F46="","",IFERROR(INDEX('Slit to Tube Conversion'!$E:$E,MATCH(INDEX('Bundle Formation'!$B$3:$B$117,MATCH(F46,'Bundle Formation'!$G$3:$G$117,0)),'Slit to Tube Conversion'!$C:$C,0)),"")) | K46: =IF(F46="","",IFERROR(INDEX('Slit to Tube Conversion'!$F:$F,MATCH(INDEX('Bundle Formation'!$B$3:$B$117,MATCH(F46,'Bundle Formation'!$G$3:$G$117,0)),'Slit to Tube Conversion'!$C:$C,0)),"")) | L46: =IF(F46="","",IFERROR(INDEX('Slit to Tube Conversion'!$G:$G,MATCH(INDEX('Bundle Formation'!$B$3:$B$117,MATCH(F46,'Bundle Formation'!$G$3:$G$117,0)),'Slit to Tube Conversion'!$C:$C,0)),"")) | M46: =IF(OR(F46="",D46="",H46=""),"",IF(H46=0,"",IF(D46/H46<0.85,"🔴 CRITICAL",IF(D46/H46<0.9,"🟠 INVESTIGATE",IF(D46/H46<0.95,"🟡 OPTIMIZE","🟢 GOOD"))))) | N46: =IF(F46="","",IF(COUNTIF(F$3:F46,F46)>1,"⚠ DUPLICATE DISPATCH",""))
